Workbook

Sheet README
B1: Commercial model: venture-diligence finalists F2 / F1 / F3
B3: Purpose
B4: Editable commercial model for the three finalists of the venture-opportunity search (post-red-team order: F2 > F1 > F3). It turns the research notes' pricing anchors, segment counts and cost drivers into unit economics, 10/100/1,000-customer scenarios, a 12-month path to first revenue for the lead finalist (F2), one-way and two-way sensitivities, and an operational-constraints check. Nothing in this workbook is a measured price: every price point is a Hypothesis inspired by a cited anchor and must be validated in customer interviews (experiments F2-A / F2-B / F1-A in decision_brief.md section 7).
B6: Finalists
B7: F2 = C&I open-access settlement / bill-audit + procurement engine for 1–20 MW industrial consumers in Karnataka, Tamil Nadu and Maharashtra (lead; success fee on recovered overcharges, then SaaS per site per year).
B8: F1 = ISTS connectivity / GNA intelligence for RE and BESS developers (per-developer subscription plus per-application reports). Gated by CTUIL data-reuse permission.
B9: F3 = FDRE / BESS dispatch, availability-compliance and IEX bid optimisation for Tier-2 storage awardees (₹ per MW per month, optional revenue share on merchant uplift). 2027+ watch item.
B11: How to use
B12: 1. Go to the Assumptions sheet. Cell C3 is the scenario selector: 1 = Conservative, 2 = Base, 3 = Upside. It drives the 'Active' column (F) on Assumptions, the 'Active' column on Unit economics, the Path to first revenue sheet and the Operational constraints sheet via INDEX.
B13: 2. Scenarios and Sensitivity do not depend on the selector: Scenarios shows all three scenarios side by side at 10 / 100 / 1,000 customers; Sensitivity is always computed on the Base column (D) of Assumptions.
B14: 3. Edit only blue cells. Every number in a blue cell is an input; every black cell is a formula; green cells are links to another sheet. Yellow-filled cells are the key levers and the unknowns that must be validated (CTUIL permission, IEX licence fee, recoverable % of bill).
B15: 4. Currency is INR throughout. The USD/INR rate (Assumptions C4) converts the USD-denominated compute and API costs; it is the only USD input.
... B27: Evidence base: research_notes/Venture scale opportunity search/ (decision_brief.md, opportunities_beyond_thesis.md, energy_software_india_forecasting.md, red_team_counterevidence.md, f1_customers_and_buying.md, solar_forecasting_feasibility.md, f2_f3_commercial_facts.md). No new web research was done for this workbook.

Sheet Assumptions
A1: Assumptions (edit blue cells only; column F = active scenario)
A3: Scenario selector (1 = Conservative, 2 = Base, 3 = Upside) | C3: 2 | D3: =CHOOSE($C$3,"Conservative","Base","Upside") -> Base
A4: USD / INR exchange rate (converts USD compute and API costs) | C4: 87 | G4: Estimate | H4: S37 | J4: Implied by JMK's listing of its OA report at INR 2 lakh + 18% GST ≈ USD 2,700 (₹2.36 lakh / 2,700 ≈ 87). Override with the live rate.
A6: Parameter | B6: Unit | C6: Conservative | D6: Base | E6: Upside | F6: Active | G6: Evidence class | H6: Source | I6: Must validate? | J6: Note / anchor
A7: Global cost drivers (shared by all finalists)
A8: Productive hours per FTE per month | B8: hours | C8: 160 | D8: 160 | E8: 160 | F8: =INDEX(C8:E8,1,$C$3) -> 160 | G8: Estimate | H8: S38 | I8: no | J8: Standard planning figure; used to convert support / onboarding hours into FTEs.
A9: Blended labour rate for onboarding and support (analyst) | B9: ₹ / hour | C9: 500 | D9: 400 | E9: 350 | F9: =INDEX(C9:E9,1,$C$3) -> 400 | G9: Hypothesis | H9: S38 | I9: YES | J9: ≈ ₹55–80k per month analyst salary ÷ 160 h. No salary data in the notes; user input.
A10: Engineer, fully loaded | B10: ₹ / month | C10: 200000 | D10: 150000 | E10: 125000 | F10: =INDEX(C10:E10,1,$C$3) -> 150000 | G10: Hypothesis | H10: S38 | I10: YES | J10: Bengaluru mid-level engineer; no salary data in the notes; user input.
A11: G&A fixed (accounting, legal, tools, insurance) | B11: ₹ / year | C11: 400000 | D11: 300000 | E11: 250000 | F11: =INDEX(C11:E11,1,$C$3) -> 300000 | G11: Hypothesis | H11: S38 | I11: no | J11: Solo-founder company overhead; user input.
A12: Fixed compute + object storage (bare VM, no paid APIs) | B12: US$ / month | C12: 40 | D12: 25 | E12: 15 | F12: =INDEX(C12:E12,1,$C$3) -> 25 | G12: Estimate | H12: S32 | I12: no | J12: solar_forecasting_feasibility.md section F: ≈ $15–40/month without paid APIs (2–4 vCPU VM + object storage).
A13: Open-Meteo Professional subscription (only where flagged) | B13: US$ / month | C13: 99 | D13: 99 | E13: 99 | F13: =INDEX(C13:E13,1,$C$3) -> 99 | G13: Verified | H13: S33 | I13: no | J13: Open-Meteo Professional $99/month (5M calls, historical / ensemble / satellite radiation). Needed only for F3's forecasting component.
A14: F2 — C&I open-access settlement & procurement engine (lead finalist)
A15: Reachable initial segment: OA / group-captive consumer organisations, 1–20 MW, Karnataka + TN + Maharashtra | B15: organisations | C15: 900 | D15: 1500 | E15: 3000 | F15: =INDEX(C15:E15,1,$C$3) -> 1500 | G15: Estimate | H15: S6 | I15: YES | J15: Karnataka: ≈922 distinct consumer organisations parsed from SLDC approved-consumer lists (count verified, de-duplication estimated; GESCOM/HESCOM lists missing). TN: '1,500+ MSME textile mills' on OA/group-captive (association claim, mostly <1 MW). Maharashtra: no public count. Range = Karnataka only → three states.
A16: OA energy drawn per site | B16: MU / year | C16: 10 | D16: 20 | E16: 35 | F16: =INDEX(C16:E16,1,$C$3) -> 20 | G16: Estimate | H16: S8 | I16: YES | J16: E.g. 5 MW contracted × 8,760 h × ~45% utilisation ≈ 20 MU. Cross-check: BESCOM-area OA drawal ≈ 6,230 MU/yr implied by the ₹1,028 Cr ÷ ₹1.65/kWh petition arithmetic.
A17: OA landed cost (energy + wheeling + CSS + surcharges + banking) | B17: ₹ / kWh | C17: 5 | D17: 5 | E17: 5 | F17: =INDEX(C17:E17,1,$C$3) -> 5 | G17: Estimate | H17: S11 | I17: no | J17: Hero Future Energies worked example: landed ₹4.78/unit vs DISCOM ₹7.32 (Manesar). Karnataka additional surcharge alone swung ₹0.82 → ₹0.40/kWh in FY26–27.
A18: Annual OA-related bill per site (formula) | B18: ₹ / site / year | C18: =C16*1000000*C17 -> 50000000 | D18: =D16*1000000*D17 -> 100000000 | E18: =E16*1000000*E17 -> 175000000 | F18: =INDEX(C18:E18,1,$C$3) -> 100000000 | G18: Estimate | H18: S8 | I18: no | J18: Formula: MU × 1,000,000 × ₹/kWh.
A19: Recoverable overcharge / avoidable loss as % of annual OA bill | B19: % of bill | C19: 0.005 | D19: 0.015 | E19: 0.03 | F19: =INDEX(C19:E19,1,$C$3) -> 0.015 | G19: Hypothesis | H19: S13 | I19: YES | J19: Experiment F2-A pass threshold: median ≥1.5% and ≥₹5 lakh/yr for 3 of 5 sites; fail <0.5%. Precedents: MERC-ordered wheeling refunds; ₹0.10/kWh error on 6,230 MU = ₹62 Cr/yr BESCOM-wide (arithmetic). MUST be measured on real bills.
A20: Success fee on verified recoveries | B20: % of recovered | C20: 0.2 | D20: 0.2 | E20: 0.25 | F20: =INDEX(C20:E20,1,$C$3) -> 0.2 | G20: Hypothesis | H20: S3 | I20: YES | J20: Audit-firm contingency structure (20–25%) and Zenatix's '% of energy bill' precedent (8–12% of bill). Not a quoted Indian OA fee: none published.
A21: Months of historical bills audited in the first engagement | B21: months | C21: 12 | D21: 18 | E21: 24 | F21: =INDEX(C21:E21,1,$C$3) -> 18 | G21: Hypothesis | H21: S13 | I21: no | J21: Experiment F2-A uses 12 months; refund windows after APTEL/MERC rulings can reach back 24 months.
A22: Recurring recoveries after the first audit (share of first-year recoverable) | B22: % of year-1 | C22: 0 | D22: 0.25 | E22: 0.5 | F22: =INDEX(C22:E22,1,$C$3) -> 0.25 | G22: Hypothesis | H22: S10 | I22: YES | J22: Charges are re-set every tariff order and banking regimes are re-litigated (TN banking rate changed 4×), so some errors recur. Conservative assumes none.
A23: SaaS subscription for monthly settlement + procurement optimisation | B23: ₹ / site / year | C23: 150000 | D23: 300000 | E23: 500000 | F23: =INDEX(C23:E23,1,$C$3) -> 300000 | G23: Hypothesis | H23: S3 | I23: YES | J23: Anchors: JMK OA report ₹2 lakh/yr (what buyers pay for OA data); mid-size factory energy audit ₹1.5–4 lakh; large plant ₹3–8 lakh. No OA-advisory fee is published by any Indian consultant.
A24: Billed sites per customer organisation | B24: sites | C24: 1 | D24: 1.5 | E24: 2 | F24: =INDEX(C24:E24,1,$C$3) -> 1.5 | G24: Estimate | H24: S6 | I24: no | J24: SLDC lists show multi-installation consumers (Shahi Exports ≥6 HT installations; Wipro, Infosys, RMZ, Manyata multiple RR numbers); most organisations have one.
A25: Win rate: qualified prospect → paying customer | B25: % | C25: 0.05 | D25: 0.1 | E25: 0.2 | F25: =INDEX(C25:E25,1,$C$3) -> 0.1 | G25: Hypothesis | H25: S13 | I25: YES | J25: Experiment F2-B pass = ≥3 of 10 interviewees accept a success-fee audit (30% pilot acceptance); paid conversion assumed lower. Incumbents (TPTCL, CES, OAE, BridgeIT) bundle settlement free, which caps the win rate.
A26: Sales cycle (first contact → signed) | B26: months | C26: 6 | D26: 4 | E26: 3 | F26: =INDEX(C26:E26,1,$C$3) -> 4 | G26: Hypothesis | H26: S14 | I26: YES | J26: Plant-head / CFO decision on a success-fee audit; no cycle data in the notes.
A27: Annual logo churn | B27: % / year | C27: 0.25 | D27: 0.15 | E27: 0.1 | F27: =INDEX(C27:E27,1,$C$3) -> 0.15 | G27: Hypothesis | H27: S14 | I27: YES | J27: Risk: developers / traders bundle settlement free; buyers may revert to the generator. No retention data exists.
A28: Onboarding hours per customer (collect 12–24 months of bills + SLDC / banking statements, identify regime) | B28: hours | C28: 40 | D28: 24 | E28: 16 | F28: =INDEX(C28:E28,1,$C$3) -> 24 | G28: Hypothesis | H28: S6 | I28: YES | J28: Two coexisting Karnataka banking regimes (legacy annual 2% in-kind vs 2025 monthly 8%) mean 'which regime applies' is manual work per generator pairing.
A29: Support + monthly statement handling per customer | B29: hours / month | C29: 4 | D29: 2.5 | E29: 1.5 | F29: =INDEX(C29:E29,1,$C$3) -> 2.5 | G29: Hypothesis | H29: S6 | I29: YES | J29: Monthly DISCOM bill + generator invoice + SLDC energy-accounting + banking statements per site; manual collection until DISCOM / SLDC exports are automated.
A30: Fixed data cost: JMK 'Open Access C&I RE Market' report subscription (incl. 18% GST) | B30: ₹ / year | C30: 236000 | D30: 236000 | E30: 236000 | F30: =INDEX(C30:E30,1,$C$3) -> 236000 | G30: Verified | H30: S2 | I30: no | J30: ₹2 lakh + GST, quarterly updates. Tariff orders / regulations are free public PDFs.
... A42: Months from audit finding to cash recovery (DISCOM credit or commission order) | B42: months | C42: 9 | D42: 6 | E42: 3 | F42: =INDEX(C42:E42,1,$C$3) -> 6 | G42: Hypothesis | H42: S10 | I42: YES | J42: Over-billing is corrected by commission orders (APTEL 366/2017, MERC 2025 refund orders): slow. Success-fee cash lags the finding.
A43: F1 — ISTS connectivity / GNA intelligence for RE & BESS developers
A44: Reachable initial segment: RE / BESS developers, lenders and advisors with live ISTS applications | B44: organisations | C44: 70 | D44: 200 | E44: 400 | F44: =INDEX(C44:E44,1,$C$3) -> 200 | G44: Estimate | H44: S16 | I44: YES | J44: ≈70 LoA-holding developers on CTUIL's 11/SM/2026 stranded list (verified count); 'a few hundred developers' nationally (brief); ≥25 named organisations with documented exposure.
A45: Subscription per developer | B45: ₹ / developer / year | C45: 300000 | D45: 500000 | E45: 1000000 | F45: =INDEX(C45:E45,1,$C$3) -> 500000 | G45: Hypothesis | H45: S15 | I45: YES | J45: H7 proposed ₹3–10 lakh/yr per developer seat, modelled on US interconnection-intelligence vendors; no Indian fee evidence. Sits below board-approval thresholds (inference).
A46: Paid per-application / per-substation reports per customer per year | B46: reports | C46: 0 | D46: 1 | E46: 2 | F46: =INDEX(C46:E46,1,$C$3) -> 1 | G46: Hypothesis | H46: S15 | I46: YES | J46: H7: ₹50k–2 lakh per report. Episodic need (60-day election windows, reallocation notices).
A47: Price per report | B47: ₹ / report | C47: 50000 | D47: 100000 | E47: 200000 | F47: =INDEX(C47:E47,1,$C$3) -> 100000 | G47: Hypothesis | H47: S15 | I47: YES | J47: Anchors: RERC consultancy estimate ₹10 lakh for a regulation-drafting assignment; law-firm CERC petition ₹10–50 lakh (unsourced estimate).
A48: Win rate: qualified prospect → paying customer | B48: % | C48: 0.05 | D48: 0.1 | E48: 0.15 | F48: =INDEX(C48:E48,1,$C$3) -> 0.1 | G48: Hypothesis | H48: S18 | I48: YES | J48: Tier-2 developers file their own CERC comments (in-house regulatory capacity); no software line item exists today.
A49: Sales cycle | B49: months | C49: 6 | D49: 4 | E49: 3 | F49: =INDEX(C49:E49,1,$C$3) -> 4 | G49: Hypothesis | H49: S18 | I49: YES | J49: BD / regulatory head discretionary budget (inference).
A50: Annual logo churn | B50: % / year | C50: 0.3 | D50: 0.2 | E50: 0.15 | F50: =INDEX(C50:E50,1,$C$3) -> 0.2 | G50: Hypothesis | H50: S21 | I50: YES | J50: Episodic need; CTUIL already publishes a filterable 636-row effective-connectivity table, so retention depends on the prediction / alert layer.
A51: Onboarding hours per customer (map portfolio of applications, alert rules) | B51: hours | C51: 16 | D51: 8 | E51: 6 | F51: =INDEX(C51:E51,1,$C$3) -> 8 | G51: Hypothesis | H51: S21 | I51: no | J51: Public data; customer supplies application IDs only.
A52: Support + alert curation per customer | B52: hours / month | C52: 3 | D52: 2 | E52: 1 | F52: =INDEX(C52:E52,1,$C$3) -> 2 | G52: Hypothesis | H52: S21 | I52: no | J52: Interpretation of CERC orders / CTUIL notices for the customer's substations.
A53: CTUIL written permission to reuse published data commercially (1 = obtained, 0 = refused / not yet) | B53: flag | C53: 0 | D53: 1 | E53: 1 | F53: =INDEX(C53:E53,1,$C$3) -> 1 | G53: Unknown | H53: S20 | I53: YES | J53: CTUIL copyright policy: contents 'may not be reproduced partially or fully, without due permission'; margin PDFs stamped RESTRICTED. Conservative = refused → revenue not bankable (F1-A0 gate).
A54: CTUIL data licence / MoU fee (placeholder; no fee schedule exists) | B54: ₹ / year | C54: 500000 | D54: 0 | E54: 0 | F54: =INDEX(C54:E54,1,$C$3) -> 0 | G54: Unknown | H54: S20 | I54: YES | J54: Placeholder only. Trade publishers re-publish CTUIL lists without visible licences (practice suggests tolerance, policy suggests risk).
A55: Data cost per customer | B55: ₹ / year | C55: 0 | D55: 0 | E55: 0 | F55: =INDEX(C55:E55,1,$C$3) -> 0 | G55: Verified | H55: S21 | I55: no | J55: All inputs are public CTUIL / CERC / RLDC PDFs and HTML tables.
... A65: Payment terms / DSO | B65: days | C65: 90 | D65: 60 | E65: 45 | F65: =INDEX(C65:E65,1,$C$3) -> 60 | G65: Hypothesis | H65: S38 | I65: YES | J65: Large developers; corporate procurement; no data in the notes.
A66: F3 — FDRE / BESS dispatch, availability-compliance & bid optimisation
A67: Reachable initial segment: Tier-2 BESS / FDRE awardees without trading desks | B67: organisations | C67: 15 | D67: 30 | E67: 60 | F67: =INDEX(C67:E67,1,$C$3) -> 30 | G67: Estimate | H67: S28 | I67: YES | J67: ≈19 named Tier-2 awardees from 2025–26 state auctions (KPTCL, TGGENCO, NVVN-Kerala, TNGECL, MSEDCL, GUVNL-IX, SJVN) plus FDRE winners; contracted pipeline ≈3.9 GW / 8.6 GWh with 2027–28 SCODs.
A68: Compliance / dispatch fee | B68: ₹ / MW / month | C68: 2000 | D68: 3000 | E68: 5000 | F68: =INDEX(C68:E68,1,$C$3) -> 3000 | G68: Hypothesis | H68: S23 | I68: YES | J68: H2 proposed ₹2,000–5,000/MW/month ≈ 1–2.5% of a ₹2.2 lakh/MW/month capacity charge. Comparable: QCA forecasting fees imply only ₹4k–33k/MW/yr (₹330–2,750/MW/month) — a ceiling risk.
A69: MW under management per customer | B69: MW | C69: 100 | D69: 250 | E69: 400 | F69: =INDEX(C69:E69,1,$C$3) -> 250 | G69: Estimate | H69: S28 | I69: no | J69: Awards range 50 MW (Sarala, Bondada) to ~1,000 MW (Oriana); Pace Digitek 375 MW; GK Energy 150 MW.
A70: Share of customer MW with merchant / co-optimisation headroom | B70: % of MW | C70: 0 | D70: 0.1 | E70: 0.3 | F70: =INDEX(C70:E70,1,$C$3) -> 0.1 | G70: Hypothesis | H70: S29 | I70: YES | J70: State DISCOM capacity contracts give no merchant rights; SECI tenders had a 40% developer tranche; FDRE allows ≤5% market sourcing. Merchant fleet (~80% of operational GWh) is Adani / ACME (in-house).
A71: Merchant revenue per MW (2-hour system; Ember ₹2.4 million / MWh / yr × 2) | B71: ₹ / MW / year | C71: 4800000 | D71: 4800000 | E71: 4800000 | F71: =INDEX(C71:E71,1,$C$3) -> 4800000 | G71: Corroborated | H71: S26 | I71: no | J71: Ember 2025: merchant BESS revenue ≈ INR 2.4 million/MWh/yr; DAM-only. IEX FY26 average arbitrage spread ₹4.81/kWh.
A72: Optimiser uplift over naive dispatch | B72: % of merchant revenue | C72: 0.03 | D72: 0.05 | E72: 0.08 | F72: =INDEX(C72:E72,1,$C$3) -> 0.05 | G72: Hypothesis | H72: S29 | I72: YES | J72: No Indian optimiser track record; GB optimisers claim up to 2× vs peers (vendor claim). Must be backtested on IEX 15-minute prices.
A73: Vendor share of uplift | B73: % of uplift | C73: 0.2 | D73: 0.25 | E73: 0.3 | F73: =INDEX(C73:E73,1,$C$3) -> 0.25 | G73: Hypothesis | H73: S23 | I73: YES | J73: GB floor-plus-share structures exist (Gresham House / Statkraft, Danske) but no optimiser publishes its share %.
A74: Win rate: qualified prospect → paying customer | B74: % | C74: 0.05 | D74: 0.1 | E74: 0.2 | F74: =INDEX(C74:E74,1,$C$3) -> 0.1 | G74: Hypothesis | H74: S40 | I74: YES | J74: Hook: MSEDCL BESPA requires 'indigenous EMS software', 95% availability, 85% RTE. Risk: OEM EMS bundles (Envision at Juniper; Fluence–ReNew JV).
A75: Sales cycle | B75: months | C75: 9 | D75: 6 | E75: 4 | F75: =INDEX(C75:E75,1,$C$3) -> 6 | G75: Hypothesis | H75: S28 | I75: YES | J75: Assets reach COD 2027–28; procurement tied to commissioning.
A76: Annual logo churn | B76: % / year | C76: 0.2 | D76: 0.15 | E76: 0.1 | F76: =INDEX(C76:E76,1,$C$3) -> 0.15 | G76: Hypothesis | H76: S39 | I76: YES | J76: OEM EMS bundling and in-house desks are the churn paths.
A77: Onboarding hours per customer (EMS / SCADA telemetry integration, contract encoding) | B77: hours | C77: 120 | D77: 80 | E77: 60 | F77: =INDEX(C77:E77,1,$C$3) -> 80 | G77: Hypothesis | H77: S40 | I77: YES | J77: Per-site integration with OEM EMS; BESPA clause encoding (cycles, RTE, availability tests).
A78: Support / dispatch desk per customer | B78: hours / month | C78: 12 | D78: 8 | E78: 5 | F78: =INDEX(C78:E78,1,$C$3) -> 8 | G78: Hypothesis | H78: S40 | I78: YES | J78: Daily dispatch plans, monthly availability certificates; could require 24×7 cover at scale.
... A90: Payment terms / DSO | B90: days | C90: 90 | D90: 60 | E90: 45 | F90: =INDEX(C90:E90,1,$C$3) -> 60 | G90: Hypothesis | H90: S38 | I90: YES | J90: Infra / EPC-origin companies; no data in the notes.
A92: Legend: blue = input; black = formula; column F picks the active scenario with INDEX(C:E, 1, $C$3). 'Must validate = YES' rows have no measured evidence and are the subject of experiments F2-A, F2-B and F1-A0/A (decision_brief.md §7).

Sheet Unit economics
A1: Unit economics per finalist (columns C–E = scenarios; F = active scenario)
A2: All cells are formulas on the Assumptions sheet. Steady-state ARPA excludes one-time fees. Payback uses steady-state gross margin. LTV = one-time fee + annual gross margin × (1 / churn), undiscounted.
F3: ="Active: "&Assumptions!$D$3 -> Active: Base
A4: Metric | B4: Unit | C4: Conservative | D4: Base | E4: Upside | F4: Active | G4: Formula / note
A5: F2 — C&I open-access settlement & procurement engine
A6: Annual OA bill per site | B6: ₹ / site / yr | C6: =Assumptions!C18 -> 50000000 | D6: =Assumptions!D18 -> 100000000 | E6: =Assumptions!E18 -> 175000000 | F6: =INDEX(C6:E6,1,Assumptions!$C$3) -> 100000000 | G6: Link: MU × ₹/kWh.
A7: SaaS revenue per account (sites × ₹/site/yr) | B7: ₹ / yr | C7: =Assumptions!C23*Assumptions!C24 -> 150000 | D7: =Assumptions!D23*Assumptions!D24 -> 450000 | E7: =Assumptions!E23*Assumptions!E24 -> 1000000 | F7: =INDEX(C7:E7,1,Assumptions!$C$3) -> 450000
A8: One-time audit success fee (first engagement) | B8: ₹ (one-time) | C8: =Assumptions!C18*Assumptions!C24*Assumptions!C19*Assumptions!C20*Assumptions!C21/12 -> 50000 | D8: =Assumptions!D18*Assumptions!D24*Assumptions!D19*Assumptions!D20*Assumptions!D21/12 -> 675000 | E8: =Assumptions!E18*Assumptions!E24*Assumptions!E19*Assumptions!E20*Assumptions!E21/12 -> 5250000 | F8: =INDEX(C8:E8,1,Assumptions!$C$3) -> 675000 | G8: Formula: bill × sites × recoverable % × fee % × months audited / 12.
A9: Recurring success fees per account per year | B9: ₹ / yr | C9: =Assumptions!C18*Assumptions!C24*Assumptions!C19*Assumptions!C20*Assumptions!C22 -> 0 | D9: =Assumptions!D18*Assumptions!D24*Assumptions!D19*Assumptions!D20*Assumptions!D22 -> 112500 | E9: =Assumptions!E18*Assumptions!E24*Assumptions!E19*Assumptions!E20*Assumptions!E22 -> 1312500 | F9: =INDEX(C9:E9,1,Assumptions!$C$3) -> 112500 | G9: Formula: bill × sites × recoverable % × fee % × recurring share.
A10: Year-1 revenue per account (SaaS + one-time fee) | B10: ₹ / yr | C10: =C7+C8 -> 200000 | D10: =D7+D8 -> 1125000 | E10: =E7+E8 -> 6250000 | F10: =INDEX(C10:E10,1,Assumptions!$C$3) -> 1125000
A11: ARPA, steady state (SaaS + recurring fees) | B11: ₹ / yr | C11: =C7+C9 -> 150000 | D11: =D7+D9 -> 562500 | E11: =E7+E9 -> 2312500 | F11: =INDEX(C11:E11,1,Assumptions!$C$3) -> 562500 | G11: Headline ARPA.
A12: Variable cost per account per year (data + compute + support hours × rate) | B12: ₹ / yr | C12: =Assumptions!C31+Assumptions!C32*12+Assumptions!C29*12*Assumptions!C9 -> 26400 | D12: =Assumptions!D31+Assumptions!D32*12+Assumptions!D29*12*Assumptions!D9 -> 13200 | E12: =Assumptions!E31+Assumptions!E32*12+Assumptions!E29*12*Assumptions!E9 -> 6900 | F12: =INDEX(C12:E12,1,Assumptions!$C$3) -> 13200
A13: Gross margin per account per year | B13: ₹ / yr | C13: =C11-C12 -> 123600 | D13: =D11-D12 -> 549300 | E13: =E11-E12 -> 2305600 | F13: =INDEX(C13:E13,1,Assumptions!$C$3) -> 549300
A14: Gross margin % | B14: % | C14: =IF(C11=0,0,C13/C11) -> 0.824 | D14: =IF(D11=0,0,D13/D11) -> 0.97653333 | E14: =IF(E11=0,0,E13/E11) -> 0.99701622 | F14: =INDEX(C14:E14,1,Assumptions!$C$3) -> 0.97653333
A15: CAC (outbound hours × rate + travel) ÷ win rate + event spend per new customer | B15: ₹ / customer | C15: =(Assumptions!C37*Assumptions!C9+Assumptions!C38)/Assumptions!C25+Assumptions!C39/Assumptions!C40 -> 170000 | D15: =(Assumptions!D37*Assumptions!D9+Assumptions!D38)/Assumptions!D25+Assumptions!D39/Assumptions!D40 -> 54000 | E15: =(Assumptions!E37*Assumptions!E9+Assumptions!E38)/Assumptions!E25+Assumptions!E39/Assumptions!E40 -> 17000 | F15: =INDEX(C15:E15,1,Assumptions!$C$3) -> 54000
A16: Onboarding cost (hours × rate) | B16: ₹ / customer | C16: =Assumptions!C28*Assumptions!C9 -> 20000 | D16: =Assumptions!D28*Assumptions!D9 -> 9600 | E16: =Assumptions!E28*Assumptions!E9 -> 5600 | F16: =INDEX(C16:E16,1,Assumptions!$C$3) -> 9600
A17: Total cost to acquire and onboard | B17: ₹ / customer | C17: =C15+C16 -> 190000 | D17: =D15+D16 -> 63600 | E17: =E15+E16 -> 22600 | F17: =INDEX(C17:E17,1,Assumptions!$C$3) -> 63600
A18: Payback on steady-state gross margin | B18: months | C18: =IF(C13<=0,"n/a (GM<=0)",C17/(C13/12)) -> 18.446602 | D18: =IF(D13<=0,"n/a (GM<=0)",D17/(D13/12)) -> 1.3894047 | E18: =IF(E13<=0,"n/a (GM<=0)",E17/(E13/12)) -> 0.11762665 | F18: =INDEX(C18:E18,1,Assumptions!$C$3) -> 1.3894047 | G18: Formula: (CAC + onboarding) ÷ (annual GM / 12).
A19: Payback net of one-time fee | B19: months | C19: =IF(C13<=0,"n/a (GM<=0)",MAX(0,C17-C8)/(C13/12)) -> 13.592233 | D19: =IF(D13<=0,"n/a (GM<=0)",MAX(0,D17-D8)/(D13/12)) -> 0 | E19: =IF(E13<=0,"n/a (GM<=0)",MAX(0,E17-E8)/(E13/12)) -> 0 | F19: =INDEX(C19:E19,1,Assumptions!$C$3) -> 0 | G19: One-time audit fee offsets acquisition cost (F2 only).
A20: Expected customer lifetime (1 / churn) | B20: years | C20: =IF(Assumptions!C27=0,0,1/Assumptions!C27) -> 4 | D20: =IF(Assumptions!D27=0,0,1/Assumptions!D27) -> 6.6666667 | E20: =IF(Assumptions!E27=0,0,1/Assumptions!E27) -> 10 | F20: =INDEX(C20:E20,1,Assumptions!$C$3) -> 6.6666667
A21: LTV (one-time fee + GM × lifetime, undiscounted) | B21: ₹ / customer | C21: =C8+C13*C20 -> 544400 | D21: =D8+D13*D20 -> 4337000 | E21: =E8+E13*E20 -> 28306000 | F21: =INDEX(C21:E21,1,Assumptions!$C$3) -> 4337000
A22: LTV / cost to acquire | B22: x | C22: =IF(C17=0,0,C21/C17) -> 2.8652632 | D22: =IF(D17=0,0,D21/D17) -> 68.191824 | E22: =IF(E17=0,0,E21/E17) -> 1252.4779 | F22: =INDEX(C22:E22,1,Assumptions!$C$3) -> 68.191824
A23: Receivables tied up per account (ARPA × DSO / 365) | B23: ₹ / customer | C23: =C11*Assumptions!C41/365 -> 24657.534 | D23: =D11*Assumptions!D41/365 -> 69349.315 | E23: =E11*Assumptions!E41/365 -> 190068.49 | F23: =INDEX(C23:E23,1,Assumptions!$C$3) -> 69349.315
A25: F1 — ISTS connectivity / GNA intelligence
A26: Subscription revenue per account | B26: ₹ / yr | C26: =Assumptions!C45 -> 300000 | D26: =Assumptions!D45 -> 500000 | E26: =Assumptions!E45 -> 1000000 | F26: =INDEX(C26:E26,1,Assumptions!$C$3) -> 500000
A27: Report revenue per account per year | B27: ₹ / yr | C27: =Assumptions!C46*Assumptions!C47 -> 0 | D27: =Assumptions!D46*Assumptions!D47 -> 100000 | E27: =Assumptions!E46*Assumptions!E47 -> 400000 | F27: =INDEX(C27:E27,1,Assumptions!$C$3) -> 100000
A28: One-time fees | B28: ₹ (one-time) | C28: =0 -> 0 | D28: =0 -> 0 | E28: =0 -> 0 | F28: =INDEX(C28:E28,1,Assumptions!$C$3) -> 0 | G28: None modelled.
A29: ARPA, steady state | B29: ₹ / yr | C29: =C26+C27 -> 300000 | D29: =D26+D27 -> 600000 | E29: =E26+E27 -> 1400000 | F29: =INDEX(C29:E29,1,Assumptions!$C$3) -> 600000 | G29: Headline ARPA (before the CTUIL gate).
A30: CTUIL permission gate (1 = permission assumed, 0 = blocked) | B30: flag | C30: =Assumptions!C53 -> 0 | D30: =Assumptions!D53 -> 1 | E30: =Assumptions!E53 -> 1 | F30: =INDEX(C30:E30,1,Assumptions!$C$3) -> 1 | G30: Conservative = refused. If 0, revenue is not bankable: see Scenarios.
A31: Bankable ARPA (ARPA × gate) | B31: ₹ / yr | C31: =C29*C30 -> 0 | D31: =D29*D30 -> 600000 | E31: =E29*E30 -> 1400000 | F31: =INDEX(C31:E31,1,Assumptions!$C$3) -> 600000
A32: Variable cost per account per year (data + compute + support hours × rate) | B32: ₹ / yr | C32: =Assumptions!C55+Assumptions!C56*12+Assumptions!C52*12*Assumptions!C9 -> 19200 | D32: =Assumptions!D55+Assumptions!D56*12+Assumptions!D52*12*Assumptions!D9 -> 10200 | E32: =Assumptions!E55+Assumptions!E56*12+Assumptions!E52*12*Assumptions!E9 -> 4500 | F32: =INDEX(C32:E32,1,Assumptions!$C$3) -> 10200
A33: Gross margin per account per year | B33: ₹ / yr | C33: =C29-C32 -> 280800 | D33: =D29-D32 -> 589800 | E33: =E29-E32 -> 1395500 | F33: =INDEX(C33:E33,1,Assumptions!$C$3) -> 589800
A34: Gross margin % | B34: % | C34: =IF(C29=0,0,C33/C29) -> 0.936 | D34: =IF(D29=0,0,D33/D29) -> 0.983 | E34: =IF(E29=0,0,E33/E29) -> 0.99678571 | F34: =INDEX(C34:E34,1,Assumptions!$C$3) -> 0.983
A35: CAC (outbound hours × rate + travel) ÷ win rate + event spend per new customer | B35: ₹ / customer | C35: =(Assumptions!C61*Assumptions!C9+Assumptions!C62)/Assumptions!C48+Assumptions!C63/Assumptions!C64 -> 450000 | D35: =(Assumptions!D61*Assumptions!D9+Assumptions!D62)/Assumptions!D48+Assumptions!D63/Assumptions!D64 -> 150750 | E35: =(Assumptions!E61*Assumptions!E9+Assumptions!E62)/Assumptions!E48+Assumptions!E63/Assumptions!E64 -> 60666.667 | F35: =INDEX(C35:E35,1,Assumptions!$C$3) -> 150750
A36: Onboarding cost (hours × rate) | B36: ₹ / customer | C36: =Assumptions!C51*Assumptions!C9 -> 8000 | D36: =Assumptions!D51*Assumptions!D9 -> 3200 | E36: =Assumptions!E51*Assumptions!E9 -> 2100 | F36: =INDEX(C36:E36,1,Assumptions!$C$3) -> 3200
A37: Total cost to acquire and onboard | B37: ₹ / customer | C37: =C35+C36 -> 458000 | D37: =D35+D36 -> 153950 | E37: =E35+E36 -> 62766.667 | F37: =INDEX(C37:E37,1,Assumptions!$C$3) -> 153950
A38: Payback on steady-state gross margin | B38: months | C38: =IF(C33<=0,"n/a (GM<=0)",C37/(C33/12)) -> 19.57265 | D38: =IF(D33<=0,"n/a (GM<=0)",D37/(D33/12)) -> 3.1322482 | E38: =IF(E33<=0,"n/a (GM<=0)",E37/(E33/12)) -> 0.53973486 | F38: =INDEX(C38:E38,1,Assumptions!$C$3) -> 3.1322482 | G38: Formula: (CAC + onboarding) ÷ (annual GM / 12).
A39: Payback net of one-time fee | B39: months | C39: =IF(C33<=0,"n/a (GM<=0)",MAX(0,C37-C28)/(C33/12)) -> 19.57265 | D39: =IF(D33<=0,"n/a (GM<=0)",MAX(0,D37-D28)/(D33/12)) -> 3.1322482 | E39: =IF(E33<=0,"n/a (GM<=0)",MAX(0,E37-E28)/(E33/12)) -> 0.53973486 | F39: =INDEX(C39:E39,1,Assumptions!$C$3) -> 3.1322482 | G39: One-time audit fee offsets acquisition cost (F2 only).
A40: Expected customer lifetime (1 / churn) | B40: years | C40: =IF(Assumptions!C50=0,0,1/Assumptions!C50) -> 3.3333333 | D40: =IF(Assumptions!D50=0,0,1/Assumptions!D50) -> 5 | E40: =IF(Assumptions!E50=0,0,1/Assumptions!E50) -> 6.6666667 | F40: =INDEX(C40:E40,1,Assumptions!$C$3) -> 5
A41: LTV (one-time fee + GM × lifetime, undiscounted) | B41: ₹ / customer | C41: =C28+C33*C40 -> 936000 | D41: =D28+D33*D40 -> 2949000 | E41: =E28+E33*E40 -> 9303333.3 | F41: =INDEX(C41:E41,1,Assumptions!$C$3) -> 2949000
A42: LTV / cost to acquire | B42: x | C42: =IF(C37=0,0,C41/C37) -> 2.0436681 | D42: =IF(D37=0,0,D41/D37) -> 19.15557 | E42: =IF(E37=0,0,E41/E37) -> 148.22092 | F42: =INDEX(C42:E42,1,Assumptions!$C$3) -> 19.15557
A43: Receivables tied up per account (ARPA × DSO / 365) | B43: ₹ / customer | C43: =C29*Assumptions!C65/365 -> 73972.603 | D43: =D29*Assumptions!D65/365 -> 98630.137 | E43: =E29*Assumptions!E65/365 -> 172602.74 | F43: =INDEX(C43:E43,1,Assumptions!$C$3) -> 98630.137
A45: F3 — BESS / FDRE dispatch & compliance
A46: Fixed fee revenue per account (₹/MW/month × MW × 12) | B46: ₹ / yr | C46: =Assumptions!C68*Assumptions!C69*12 -> 2400000 | D46: =Assumptions!D68*Assumptions!D69*12 -> 9000000 | E46: =Assumptions!E68*Assumptions!E69*12 -> 24000000 | F46: =INDEX(C46:E46,1,Assumptions!$C$3) -> 9000000
A47: Revenue share on merchant uplift per account | B47: ₹ / yr | C47: =Assumptions!C69*Assumptions!C70*Assumptions!C71*Assumptions!C72*Assumptions!C73 -> 0 | D47: =Assumptions!D69*Assumptions!D70*Assumptions!D71*Assumptions!D72*Assumptions!D73 -> 1500000 | E47: =Assumptions!E69*Assumptions!E70*Assumptions!E71*Assumptions!E72*Assumptions!E73 -> 13824000 | F47: =INDEX(C47:E47,1,Assumptions!$C$3) -> 1500000 | G47: Formula: MW × merchant share × ₹/MW/yr merchant revenue × uplift % × vendor share %.
A48: One-time fees | B48: ₹ (one-time) | C48: =0 -> 0 | D48: =0 -> 0 | E48: =0 -> 0 | F48: =INDEX(C48:E48,1,Assumptions!$C$3) -> 0 | G48: Integration is costed, not charged (could be charged: test in interviews).
A49: ARPA, steady state | B49: ₹ / yr | C49: =C46+C47 -> 2400000 | D49: =D46+D47 -> 10500000 | E49: =E46+E47 -> 37824000 | F49: =INDEX(C49:E49,1,Assumptions!$C$3) -> 10500000 | G49: Headline ARPA.
A50: Fixed fee as % of capacity charge (₹2.4 lakh/MW/month reference) | B50: % | C50: =Assumptions!C68/240000 -> 0.0083333333 | D50: =Assumptions!D68/240000 -> 0.0125 | E50: =Assumptions!E68/240000 -> 0.020833333 | F50: =INDEX(C50:E50,1,Assumptions!$C$3) -> 0.0125 | G50: Reference: MSEDCL Sep-2026 award ₹2.38–2.40 lakh/MW/month (S24).
A51: Variable cost per account per year (data + compute + support hours × rate) | B51: ₹ / yr | C51: =Assumptions!C80+Assumptions!C81*12+Assumptions!C78*12*Assumptions!C9 -> 84000 | D51: =Assumptions!D80+Assumptions!D81*12+Assumptions!D78*12*Assumptions!D9 -> 44400 | E51: =Assumptions!E80+Assumptions!E81*12+Assumptions!E78*12*Assumptions!E9 -> 24600 | F51: =INDEX(C51:E51,1,Assumptions!$C$3) -> 44400
A52: Gross margin per account per year | B52: ₹ / yr | C52: =C49-C51 -> 2316000 | D52: =D49-D51 -> 10455600 | E52: =E49-E51 -> 37799400 | F52: =INDEX(C52:E52,1,Assumptions!$C$3) -> 10455600
A53: Gross margin % | B53: % | C53: =IF(C49=0,0,C52/C49) -> 0.965 | D53: =IF(D49=0,0,D52/D49) -> 0.99577143 | E53: =IF(E49=0,0,E52/E49) -> 0.99934962 | F53: =INDEX(C53:E53,1,Assumptions!$C$3) -> 0.99577143
A54: CAC (outbound hours × rate + travel) ÷ win rate + event spend per new customer | B54: ₹ / customer | C54: =(Assumptions!C86*Assumptions!C9+Assumptions!C87)/Assumptions!C74+Assumptions!C88/Assumptions!C89 -> 850000 | D54: =(Assumptions!D86*Assumptions!D9+Assumptions!D87)/Assumptions!D74+Assumptions!D88/Assumptions!D89 -> 300000 | E54: =(Assumptions!E86*Assumptions!E9+Assumptions!E87)/Assumptions!E74+Assumptions!E88/Assumptions!E89 -> 107500 | F54: =INDEX(C54:E54,1,Assumptions!$C$3) -> 300000
A55: Onboarding cost (hours × rate) | B55: ₹ / customer | C55: =Assumptions!C77*Assumptions!C9 -> 60000 | D55: =Assumptions!D77*Assumptions!D9 -> 32000 | E55: =Assumptions!E77*Assumptions!E9 -> 21000 | F55: =INDEX(C55:E55,1,Assumptions!$C$3) -> 32000
A56: Total cost to acquire and onboard | B56: ₹ / customer | C56: =C54+C55 -> 910000 | D56: =D54+D55 -> 332000 | E56: =E54+E55 -> 128500 | F56: =INDEX(C56:E56,1,Assumptions!$C$3) -> 332000
A57: Payback on steady-state gross margin | B57: months | C57: =IF(C52<=0,"n/a (GM<=0)",C56/(C52/12)) -> 4.7150259 | D57: =IF(D52<=0,"n/a (GM<=0)",D56/(D52/12)) -> 0.38103983 | E57: =IF(E52<=0,"n/a (GM<=0)",E56/(E52/12)) -> 0.040794298 | F57: =INDEX(C57:E57,1,Assumptions!$C$3) -> 0.38103983 | G57: Formula: (CAC + onboarding) ÷ (annual GM / 12).
A58: Payback net of one-time fee | B58: months | C58: =IF(C52<=0,"n/a (GM<=0)",MAX(0,C56-C48)/(C52/12)) -> 4.7150259 | D58: =IF(D52<=0,"n/a (GM<=0)",MAX(0,D56-D48)/(D52/12)) -> 0.38103983 | E58: =IF(E52<=0,"n/a (GM<=0)",MAX(0,E56-E48)/(E52/12)) -> 0.040794298 | F58: =INDEX(C58:E58,1,Assumptions!$C$3) -> 0.38103983 | G58: One-time audit fee offsets acquisition cost (F2 only).
A59: Expected customer lifetime (1 / churn) | B59: years | C59: =IF(Assumptions!C76=0,0,1/Assumptions!C76) -> 5 | D59: =IF(Assumptions!D76=0,0,1/Assumptions!D76) -> 6.6666667 | E59: =IF(Assumptions!E76=0,0,1/Assumptions!E76) -> 10 | F59: =INDEX(C59:E59,1,Assumptions!$C$3) -> 6.6666667
A60: LTV (one-time fee + GM × lifetime, undiscounted) | B60: ₹ / customer | C60: =C48+C52*C59 -> 11580000 | D60: =D48+D52*D59 -> 69704000 | E60: =E48+E52*E59 -> 377994000 | F60: =INDEX(C60:E60,1,Assumptions!$C$3) -> 69704000
A61: LTV / cost to acquire | B61: x | C61: =IF(C56=0,0,C60/C56) -> 12.725275 | D61: =IF(D56=0,0,D60/D56) -> 209.95181 | E61: =IF(E56=0,0,E60/E56) -> 2941.5875 | F61: =INDEX(C61:E61,1,Assumptions!$C$3) -> 209.95181
A62: Receivables tied up per account (ARPA × DSO / 365) | B62: ₹ / customer | C62: =C49*Assumptions!C90/365 -> 591780.82 | D62: =D49*Assumptions!D90/365 -> 1726027.4 | E62: =E49*Assumptions!E90/365 -> 4663232.9 | F62: =INDEX(C62:E62,1,Assumptions!$C$3) -> 1726027.4

Sheet Path to first revenue
A1: Path to first revenue — F2, month-by-month (active scenario)
A2: ="Active scenario: "&Assumptions!$D$3&". Blue cells are inputs; the pilot plan (row 19) is the main lever." -> Active scenario: Base. Blue cells are inputs; the pilot plan (row 19) is the main lever.
A4: Input | B4: Value | O4: Note
A5: Founder capital available | B5: 1000000 | O5: Default ₹10 lakh (brief: founder has limited capital).
A6: Founder stipend | B6: 50000 | O6: ₹ per month, cash. Also used as founder cost in Scenarios opex.
A7: Founder delivery hours available per month (audits + support) | B7: 80 | O7: Remaining founder time goes to sales and building.
A8: Prospect meetings per pilot started | B8: 5 | O8: Travel cost driver: meetings × ₹ per prospect trip.
A9: Pilot → paying conversion rate | B9: 0.3 | O9: Experiment F2-B pass threshold: ≥3 of 10 accept a success-fee audit. Hypothesis.
A10: Months from pilot start to conversion | B10: =ROUND(Assumptions!$F$26,0) -> 4 | O10: Link: active sales cycle.
A11: Months from conversion to recovery cash (audit fee billable) | B11: =ROUND(Assumptions!$F$42,0) -> 6 | O11: Link: active recovery lag.
A12: DSO in months (rounded) | B12: =ROUND(Assumptions!$F$41/30,0) -> 2 | O12: Link: active DSO / 30.
A13: SaaS billing per paying customer per month | B13: ='Unit economics'!$F$7/12 -> 37500 | O13: Link: active ARPA (SaaS) / 12.
A14: One-time audit success fee per conversion | B14: ='Unit economics'!$F$8 -> 675000 | O14: Link: active one-time fee.
A15: Audit / onboarding hours per pilot | B15: =Assumptions!$F$28 -> 24 | O15: Link.
A16: Support hours per paying customer per month | B16: =Assumptions!$F$29 -> 2.5 | O16: Link.
A17: Contract analyst rate (₹/hour) when founder hours are exceeded | B17: =Assumptions!$F$9 -> 400 | O17: Link.
A18: Travel per prospect meeting | B18: =Assumptions!$F$38 -> 2000 | O18: Link.
A19: Fixed compute per month (₹) | B19: =Assumptions!$F$12*Assumptions!$C$4 -> 2175 | O19: Link: bare VM $ × USD/INR.
A20: Compute per paying customer per month | B20: =Assumptions!$F$32 -> 100 | O20: Link.
A21: Events spend per month | B21: =Assumptions!$F$39/12 -> 8333.3333 | O21: Link: annual / 12.
A22: Data subscription per month (JMK report) | B22: =Assumptions!$F$30/12 -> 19666.667 | O22: Link: annual / 12.
A24: Month | C24: M1 | D24: M2 | E24: M3 | F24: M4 | G24: M5 | H24: M6 | I24: M7 | J24: M8 | K24: M9 | L24: M10 | M24: M11 | N24: M12 | O24: Note
A25: Month number | C25: 1 | D25: 2 | E25: 3 | F25: 4 | G25: 5 | H25: 6 | I25: 7 | J25: 8 | K25: 9 | L25: 10 | M25: 11 | N25: 12
A26: Pilots (success-fee audits) started | C26: 1 | D26: 2 | E26: 2 | F26: 2 | G26: 2 | H26: 2 | I26: 2 | J26: 2 | K26: 2 | L26: 2 | M26: 2 | N26: 2 | O26: INPUT: pilot plan. Default: 1 in month 1 then 2 per month.
A27: Conversions to paying (pilots started 'cycle' months earlier × conversion rate) | C27: =IF(C25-$B$10>=1,INDEX($C$26:$N$26,1,C25-$B$10)*$B$9,0) -> 0 | D27: =IF(D25-$B$10>=1,INDEX($C$26:$N$26,1,D25-$B$10)*$B$9,0) -> 0 | E27: =IF(E25-$B$10>=1,INDEX($C$26:$N$26,1,E25-$B$10)*$B$9,0) -> 0 | F27: =IF(F25-$B$10>=1,INDEX($C$26:$N$26,1,F25-$B$10)*$B$9,0) -> 0 | G27: =IF(G25-$B$10>=1,INDEX($C$26:$N$26,1,G25-$B$10)*$B$9,0) -> 0.3 | H27: =IF(H25-$B$10>=1,INDEX($C$26:$N$26,1,H25-$B$10)*$B$9,0) -> 0.6 | I27: =IF(I25-$B$10>=1,INDEX($C$26:$N$26,1,I25-$B$10)*$B$9,0) -> 0.6 | J27: =IF(J25-$B$10>=1,INDEX($C$26:$N$26,1,J25-$B$10)*$B$9,0) -> 0.6 | ... N27: =IF(N25-$B$10>=1,INDEX($C$26:$N$26,1,N25-$B$10)*$B$9,0) -> 0.6
A28: Paying customers (cumulative) | C28: =C27 -> 0 | D28: =C28+D27 -> 0 | E28: =D28+E27 -> 0 | F28: =E28+F27 -> 0 | G28: =F28+G27 -> 0.3 | H28: =G28+H27 -> 0.9 | I28: =H28+I27 -> 1.5 | J28: =I28+J27 -> 2.1 | K28: =J28+K27 -> 2.7 | ... N28: =M28+N27 -> 4.5
A29: SaaS billed | C29: =C28*$B$13 -> 0 | D29: =D28*$B$13 -> 0 | E29: =E28*$B$13 -> 0 | F29: =F28*$B$13 -> 0 | G29: =G28*$B$13 -> 11250 | H29: =H28*$B$13 -> 33750 | I29: =I28*$B$13 -> 56250 | J29: =J28*$B$13 -> 78750 | ... N29: =N28*$B$13 -> 168750
A30: Audit success fee billed (conversions 'lag' months earlier × fee) | C30: =IF(C25-$B$11>=1,INDEX($C$27:$N$27,1,C25-$B$11)*$B$14,0) -> 0 | D30: =IF(D25-$B$11>=1,INDEX($C$27:$N$27,1,D25-$B$11)*$B$14,0) -> 0 | E30: =IF(E25-$B$11>=1,INDEX($C$27:$N$27,1,E25-$B$11)*$B$14,0) -> 0 | F30: =IF(F25-$B$11>=1,INDEX($C$27:$N$27,1,F25-$B$11)*$B$14,0) -> 0 | G30: =IF(G25-$B$11>=1,INDEX($C$27:$N$27,1,G25-$B$11)*$B$14,0) -> 0 | H30: =IF(H25-$B$11>=1,INDEX($C$27:$N$27,1,H25-$B$11)*$B$14,0) -> 0 | I30: =IF(I25-$B$11>=1,INDEX($C$27:$N$27,1,I25-$B$11)*$B$14,0) -> 0 | J30: =IF(J25-$B$11>=1,INDEX($C$27:$N$27,1,J25-$B$11)*$B$14,0) -> 0 | ... N30: =IF(N25-$B$11>=1,INDEX($C$27:$N$27,1,N25-$B$11)*$B$14,0) -> 405000
A31: Revenue recognised (billed) | C31: =C29+C30 -> 0 | D31: =D29+D30 -> 0 | E31: =E29+E30 -> 0 | F31: =F29+F30 -> 0 | G31: =G29+G30 -> 11250 | H31: =H29+H30 -> 33750 | I31: =I29+I30 -> 56250 | J31: =J29+J30 -> 78750 | ... N31: =N29+N30 -> 573750
A32: Cash in: SaaS (billed 'DSO months' earlier) | C32: =IF(C25-$B$12>=1,INDEX($C$29:$N$29,1,C25-$B$12),0) -> 0 | D32: =IF(D25-$B$12>=1,INDEX($C$29:$N$29,1,D25-$B$12),0) -> 0 | E32: =IF(E25-$B$12>=1,INDEX($C$29:$N$29,1,E25-$B$12),0) -> 0 | F32: =IF(F25-$B$12>=1,INDEX($C$29:$N$29,1,F25-$B$12),0) -> 0 | G32: =IF(G25-$B$12>=1,INDEX($C$29:$N$29,1,G25-$B$12),0) -> 0 | H32: =IF(H25-$B$12>=1,INDEX($C$29:$N$29,1,H25-$B$12),0) -> 0 | I32: =IF(I25-$B$12>=1,INDEX($C$29:$N$29,1,I25-$B$12),0) -> 11250 | J32: =IF(J25-$B$12>=1,INDEX($C$29:$N$29,1,J25-$B$12),0) -> 33750 | ... N32: =IF(N25-$B$12>=1,INDEX($C$29:$N$29,1,N25-$B$12),0) -> 123750
A33: Cash in: audit fees (billed 'DSO months' earlier) | C33: =IF(C25-$B$12>=1,INDEX($C$30:$N$30,1,C25-$B$12),0) -> 0 | D33: =IF(D25-$B$12>=1,INDEX($C$30:$N$30,1,D25-$B$12),0) -> 0 | E33: =IF(E25-$B$12>=1,INDEX($C$30:$N$30,1,E25-$B$12),0) -> 0 | F33: =IF(F25-$B$12>=1,INDEX($C$30:$N$30,1,F25-$B$12),0) -> 0 | G33: =IF(G25-$B$12>=1,INDEX($C$30:$N$30,1,G25-$B$12),0) -> 0 | H33: =IF(H25-$B$12>=1,INDEX($C$30:$N$30,1,H25-$B$12),0) -> 0 | I33: =IF(I25-$B$12>=1,INDEX($C$30:$N$30,1,I25-$B$12),0) -> 0 | J33: =IF(J25-$B$12>=1,INDEX($C$30:$N$30,1,J25-$B$12),0) -> 0 | ... N33: =IF(N25-$B$12>=1,INDEX($C$30:$N$30,1,N25-$B$12),0) -> 0
A34: Total cash in | C34: =C32+C33 -> 0 | D34: =D32+D33 -> 0 | E34: =E32+E33 -> 0 | F34: =F32+F33 -> 0 | G34: =G32+G33 -> 0 | H34: =H32+H33 -> 0 | I34: =I32+I33 -> 11250 | J34: =J32+J33 -> 33750 | ... N34: =N32+N33 -> 123750
A35: Delivery hours needed (pilots × audit hours + customers × support hours) | C35: =C26*$B$15+C28*$B$16 -> 24 | D35: =D26*$B$15+D28*$B$16 -> 48 | E35: =E26*$B$15+E28*$B$16 -> 48 | F35: =F26*$B$15+F28*$B$16 -> 48 | G35: =G26*$B$15+G28*$B$16 -> 48.75 | H35: =H26*$B$15+H28*$B$16 -> 50.25 | I35: =I26*$B$15+I28*$B$16 -> 51.75 | J35: =J26*$B$15+J28*$B$16 -> 53.25 | ... N35: =N26*$B$15+N28*$B$16 -> 59.25
A36: Cost: founder stipend | C36: =$B$6 -> 50000 | D36: =$B$6 -> 50000 | E36: =$B$6 -> 50000 | F36: =$B$6 -> 50000 | G36: =$B$6 -> 50000 | H36: =$B$6 -> 50000 | I36: =$B$6 -> 50000 | J36: =$B$6 -> 50000 | ... N36: =$B$6 -> 50000
A37: Cost: contract analyst (hours above founder capacity × rate) | C37: =MAX(0,C35-$B$7)*$B$17 -> 0 | D37: =MAX(0,D35-$B$7)*$B$17 -> 0 | E37: =MAX(0,E35-$B$7)*$B$17 -> 0 | F37: =MAX(0,F35-$B$7)*$B$17 -> 0 | G37: =MAX(0,G35-$B$7)*$B$17 -> 0 | H37: =MAX(0,H35-$B$7)*$B$17 -> 0 | I37: =MAX(0,I35-$B$7)*$B$17 -> 0 | J37: =MAX(0,J35-$B$7)*$B$17 -> 0 | ... N37: =MAX(0,N35-$B$7)*$B$17 -> 0
A38: Cost: compute (fixed + per customer) | C38: =$B$19+C28*$B$20 -> 2175 | D38: =$B$19+D28*$B$20 -> 2175 | E38: =$B$19+E28*$B$20 -> 2175 | F38: =$B$19+F28*$B$20 -> 2175 | G38: =$B$19+G28*$B$20 -> 2205 | H38: =$B$19+H28*$B$20 -> 2265 | I38: =$B$19+I28*$B$20 -> 2325 | J38: =$B$19+J28*$B$20 -> 2385 | ... N38: =$B$19+N28*$B$20 -> 2625
A39: Cost: travel (pilots × meetings × ₹/trip) | C39: =C26*$B$8*$B$18 -> 10000 | D39: =D26*$B$8*$B$18 -> 20000 | E39: =E26*$B$8*$B$18 -> 20000 | F39: =F26*$B$8*$B$18 -> 20000 | G39: =G26*$B$8*$B$18 -> 20000 | H39: =H26*$B$8*$B$18 -> 20000 | I39: =I26*$B$8*$B$18 -> 20000 | J39: =J26*$B$8*$B$18 -> 20000 | ... N39: =N26*$B$8*$B$18 -> 20000
A40: Cost: events / associations | C40: =$B$21 -> 8333.3333 | D40: =$B$21 -> 8333.3333 | E40: =$B$21 -> 8333.3333 | F40: =$B$21 -> 8333.3333 | G40: =$B$21 -> 8333.3333 | H40: =$B$21 -> 8333.3333 | I40: =$B$21 -> 8333.3333 | J40: =$B$21 -> 8333.3333 | ... N40: =$B$21 -> 8333.3333
A41: Cost: data subscription | C41: =$B$22 -> 19666.667 | D41: =$B$22 -> 19666.667 | E41: =$B$22 -> 19666.667 | F41: =$B$22 -> 19666.667 | G41: =$B$22 -> 19666.667 | H41: =$B$22 -> 19666.667 | I41: =$B$22 -> 19666.667 | J41: =$B$22 -> 19666.667 | ... N41: =$B$22 -> 19666.667
A42: Total cash out (burn) | C42: =SUM(C36:C41) -> 90175 | D42: =SUM(D36:D41) -> 100175 | E42: =SUM(E36:E41) -> 100175 | F42: =SUM(F36:F41) -> 100175 | G42: =SUM(G36:G41) -> 100205 | H42: =SUM(H36:H41) -> 100265 | I42: =SUM(I36:I41) -> 100325 | J42: =SUM(J36:J41) -> 100385 | ... N42: =SUM(N36:N41) -> 100625
A43: Net cash flow | C43: =C34-C42 -> -90175 | D43: =D34-D42 -> -100175 | E43: =E34-E42 -> -100175 | F43: =F34-F42 -> -100175 | G43: =G34-G42 -> -100205 | H43: =H34-H42 -> -100265 | I43: =I34-I42 -> -89075 | J43: =J34-J42 -> -66635 | ... N43: =N34-N42 -> 23125
A44: Cumulative burn | C44: =C42 -> 90175 | D44: =C44+D42 -> 190350 | E44: =D44+E42 -> 290525 | F44: =E44+F42 -> 390700 | G44: =F44+G42 -> 490905 | H44: =G44+H42 -> 591170 | I44: =H44+I42 -> 691495 | J44: =I44+J42 -> 791880 | K44: =J44+K42 -> 892325 | ... N44: =M44+N42 -> 1194020
A45: Cumulative cash in | C45: =C34 -> 0 | D45: =C45+D34 -> 0 | E45: =D45+E34 -> 0 | F45: =E45+F34 -> 0 | G45: =F45+G34 -> 0 | H45: =G45+H34 -> 0 | I45: =H45+I34 -> 11250 | J45: =I45+J34 -> 45000 | K45: =J45+K34 -> 101250 | ... N45: =M45+N34 -> 405000
A46: Cash balance (budget + cumulative cash in − cumulative burn) | C46: =$B$5+C45-C44 -> 909825 | D46: =$B$5+D45-D44 -> 809650 | E46: =$B$5+E45-E44 -> 709475 | F46: =$B$5+F45-F44 -> 609300 | G46: =$B$5+G45-G44 -> 509095 | H46: =$B$5+H45-H44 -> 408830 | I46: =$B$5+I45-I44 -> 319755 | J46: =$B$5+J45-J44 -> 253120 | ... N46: =$B$5+N45-N44 -> 210980
A47: Runway flag | C47: =IF(C46<0,"CASH OUT","ok") -> ok | D47: =IF(D46<0,"CASH OUT","ok") -> ok | E47: =IF(E46<0,"CASH OUT","ok") -> ok | F47: =IF(F46<0,"CASH OUT","ok") -> ok | G47: =IF(G46<0,"CASH OUT","ok") -> ok | H47: =IF(H46<0,"CASH OUT","ok") -> ok | I47: =IF(I46<0,"CASH OUT","ok") -> ok | J47: =IF(J46<0,"CASH OUT","ok") -> ok | ... N47: =IF(N46<0,"CASH OUT","ok") -> ok
A48: First-cash marker (month number when cash in first > 0) | C48: =IF(AND(C34>0,SUM($C$34:C34)=C34),C25,"") | D48: =IF(AND(D34>0,SUM($C$34:D34)=D34),D25,"") | E48: =IF(AND(E34>0,SUM($C$34:E34)=E34),E25,"") | F48: =IF(AND(F34>0,SUM($C$34:F34)=F34),F25,"") | G48: =IF(AND(G34>0,SUM($C$34:G34)=G34),G25,"") | H48: =IF(AND(H34>0,SUM($C$34:H34)=H34),H25,"") | I48: =IF(AND(I34>0,SUM($C$34:I34)=I34),I25,"") -> 7 | J48: =IF(AND(J34>0,SUM($C$34:J34)=J34),J25,"") | ... N48: =IF(AND(N34>0,SUM($C$34:N34)=N34),N25,"") | O48: Helper for the summary below.
A50: Summary (12 months)
A51: First month with cash in | B51: =IF(COUNT($C$48:$N$48)=0,"none in 12 months",MIN($C$48:$N$48)) -> 7
A52: First month with revenue billed | B52: =IF(COUNTIF($C$31:$N$31,">0")=0,"none in 12 months",13-COUNTIF($C$31:$N$31,">0")) -> 5
A53: Pilots started in 12 months | B53: =SUM($C$26:$N$26) -> 23
A54: Paying customers at month 12 | B54: =N28 -> 4.5
A55: Revenue billed in 12 months | B55: =SUM($C$31:$N$31) -> 1327500
A56: Cash collected in 12 months | B56: =SUM($C$34:$N$34) -> 405000
A57: Cumulative burn at month 12 | B57: =N44 -> 1194020
A58: Lowest cash balance in the year | B58: =MIN($C$46:$N$46) -> 187170
A59: Cash balance at month 12 | B59: =N46 -> 210980
A60: Months of runway breached? | B60: =IF(COUNTIF($C$47:$N$47,"CASH OUT")>0,"YES — "&COUNTIF($C$47:$N$47,"CASH OUT")&" month(s) below zero","no") -> no
A61: Exit ARR (SaaS only, customers × SaaS/yr) | B61: =N28*$B$13*12 -> 2025000
A63: Reading: success-fee cash arrives only after conversion + recovery lag + DSO, so the first year is financed by the founder budget; the 'First month with revenue billed' formula assumes revenue, once started, continues every month (true for this plan).

Sheet Scenarios
A1: Scenarios — steady-state annual P&L at 10 / 100 / 1,000 customers, all three scenarios
A2: Independent of the selector. Customer counts in row 5 are inputs. Opex includes replacement acquisition (customers × churn × cost to acquire). Feasibility flags compare the customer count with the reachable segment and with segment × win rate.
C4: Conservative | F4: Base | I4: Upside | L4: Note
A5: Customers (input) | C5: 10 | D5: 100 | E5: 1000 | F5: 10 | G5: 100 | H5: 1000 | I5: 10 | J5: 100 | K5: 1000
A7: F2 — C&I open-access settlement & procurement engine
A8: Customers | B8: count | C8: =C$5 -> 10 | D8: =D$5 -> 100 | E8: =E$5 -> 1000 | F8: =F$5 -> 10 | G8: =G$5 -> 100 | H8: =H$5 -> 1000 | I8: =I$5 -> 10 | J8: =J$5 -> 100 | K8: =K$5 -> 1000
A9: Recurring revenue (customers × steady-state ARPA) | B9: ₹ / yr | C9: =C$5*'Unit economics'!$C$11 -> 1500000 | D9: =D$5*'Unit economics'!$C$11 -> 15000000 | E9: =E$5*'Unit economics'!$C$11 -> 150000000 | F9: =F$5*'Unit economics'!$D$11 -> 5625000 | G9: =G$5*'Unit economics'!$D$11 -> 56250000 | H9: =H$5*'Unit economics'!$D$11 -> 562500000 | I9: =I$5*'Unit economics'!$E$11 -> 23125000 | J9: =J$5*'Unit economics'!$E$11 -> 231250000 | K9: =K$5*'Unit economics'!$E$11 -> 2312500000
A10: One-time fees on replacement customers (customers × churn × one-time fee) | B10: ₹ / yr | C10: =C$5*Assumptions!$C$27*'Unit economics'!$C$8 -> 125000 | D10: =D$5*Assumptions!$C$27*'Unit economics'!$C$8 -> 1250000 | E10: =E$5*Assumptions!$C$27*'Unit economics'!$C$8 -> 12500000 | F10: =F$5*Assumptions!$D$27*'Unit economics'!$D$8 -> 1012500 | G10: =G$5*Assumptions!$D$27*'Unit economics'!$D$8 -> 10125000 | H10: =H$5*Assumptions!$D$27*'Unit economics'!$D$8 -> 101250000 | I10: =I$5*Assumptions!$E$27*'Unit economics'!$E$8 -> 5250000 | J10: =J$5*Assumptions!$E$27*'Unit economics'!$E$8 -> 52500000 | K10: =K$5*Assumptions!$E$27*'Unit economics'!$E$8 -> 525000000
A11: Total revenue | B11: ₹ / yr | C11: =C9+C10 -> 1625000 | D11: =D9+D10 -> 16250000 | E11: =E9+E10 -> 162500000 | F11: =F9+F10 -> 6637500 | G11: =G9+G10 -> 66375000 | H11: =H9+H10 -> 663750000 | I11: =I9+I10 -> 28375000 | J11: =J9+J10 -> 283750000 | K11: =K9+K10 -> 2837500000
A12: COGS (customers × variable cost) | B12: ₹ / yr | C12: =C$5*'Unit economics'!$C$12 -> 264000 | D12: =D$5*'Unit economics'!$C$12 -> 2640000 | E12: =E$5*'Unit economics'!$C$12 -> 26400000 | F12: =F$5*'Unit economics'!$D$12 -> 132000 | G12: =G$5*'Unit economics'!$D$12 -> 1320000 | H12: =H$5*'Unit economics'!$D$12 -> 13200000 | I12: =I$5*'Unit economics'!$E$12 -> 69000 | J12: =J$5*'Unit economics'!$E$12 -> 690000 | K12: =K$5*'Unit economics'!$E$12 -> 6900000
A13: Gross margin | B13: ₹ / yr | C13: =C11-C12 -> 1361000 | D13: =D11-D12 -> 13610000 | E13: =E11-E12 -> 136100000 | F13: =F11-F12 -> 6505500 | G13: =G11-G12 -> 65055000 | H13: =H11-H12 -> 650550000 | I13: =I11-I12 -> 28306000 | J13: =J11-J12 -> 283060000 | K13: =K11-K12 -> 2830600000
A14: Gross margin % | B14: % | C14: =IF(C11=0,0,C13/C11) -> 0.83753846 | D14: =IF(D11=0,0,D13/D11) -> 0.83753846 | E14: =IF(E11=0,0,E13/E11) -> 0.83753846 | F14: =IF(F11=0,0,F13/F11) -> 0.98011299 | G14: =IF(G11=0,0,G13/G11) -> 0.98011299 | H14: =IF(H11=0,0,H13/H11) -> 0.98011299 | I14: =IF(I11=0,0,I13/I11) -> 0.99756828 | J14: =IF(J11=0,0,J13/J11) -> 0.99756828 | K14: =IF(K11=0,0,K13/K11) -> 0.99756828
A15: Engineers at this stage (excl. founder) | B15: FTE | C15: =IF(C$5<=10,Assumptions!$C$34,IF(C$5<=100,Assumptions!$C$35,Assumptions!$C$36)) -> 0 | D15: =IF(D$5<=10,Assumptions!$C$34,IF(D$5<=100,Assumptions!$C$35,Assumptions!$C$36)) -> 2 | E15: =IF(E$5<=10,Assumptions!$C$34,IF(E$5<=100,Assumptions!$C$35,Assumptions!$C$36)) -> 4 | F15: =IF(F$5<=10,Assumptions!$D$34,IF(F$5<=100,Assumptions!$D$35,Assumptions!$D$36)) -> 0 | G15: =IF(G$5<=10,Assumptions!$D$34,IF(G$5<=100,Assumptions!$D$35,Assumptions!$D$36)) -> 1 | H15: =IF(H$5<=10,Assumptions!$D$34,IF(H$5<=100,Assumptions!$D$35,Assumptions!$D$36)) -> 2 | I15: =IF(I$5<=10,Assumptions!$E$34,IF(I$5<=100,Assumptions!$E$35,Assumptions!$E$36)) -> 0 | J15: =IF(J$5<=10,Assumptions!$E$34,IF(J$5<=100,Assumptions!$E$35,Assumptions!$E$36)) -> 1 | K15: =IF(K$5<=10,Assumptions!$E$34,IF(K$5<=100,Assumptions!$E$35,Assumptions!$E$36)) -> 2 | L15: Stage lookup on Assumptions eng10 / eng100 / eng1000.
A16: Opex: founder stipend | B16: ₹ / yr | C16: ='Path to first revenue'!$B$6*12 -> 600000 | D16: ='Path to first revenue'!$B$6*12 -> 600000 | E16: ='Path to first revenue'!$B$6*12 -> 600000 | F16: ='Path to first revenue'!$B$6*12 -> 600000 | G16: ='Path to first revenue'!$B$6*12 -> 600000 | H16: ='Path to first revenue'!$B$6*12 -> 600000 | I16: ='Path to first revenue'!$B$6*12 -> 600000 | J16: ='Path to first revenue'!$B$6*12 -> 600000 | K16: ='Path to first revenue'!$B$6*12 -> 600000 | L16: From Path to first revenue (input).
A17: Opex: engineers | B17: ₹ / yr | C17: =C15*Assumptions!$C$10*12 -> 0 | D17: =D15*Assumptions!$C$10*12 -> 4800000 | E17: =E15*Assumptions!$C$10*12 -> 9600000 | F17: =F15*Assumptions!$D$10*12 -> 0 | G17: =G15*Assumptions!$D$10*12 -> 1800000 | H17: =H15*Assumptions!$D$10*12 -> 3600000 | I17: =I15*Assumptions!$E$10*12 -> 0 | J17: =J15*Assumptions!$E$10*12 -> 1500000 | K17: =K15*Assumptions!$E$10*12 -> 3000000
A18: Opex: G&A fixed | B18: ₹ / yr | C18: =Assumptions!$C$11 -> 400000 | D18: =Assumptions!$C$11 -> 400000 | E18: =Assumptions!$C$11 -> 400000 | F18: =Assumptions!$D$11 -> 300000 | G18: =Assumptions!$D$11 -> 300000 | H18: =Assumptions!$D$11 -> 300000 | I18: =Assumptions!$E$11 -> 250000 | J18: =Assumptions!$E$11 -> 250000 | K18: =Assumptions!$E$11 -> 250000
A19: Opex: conferences / events | B19: ₹ / yr | C19: =Assumptions!$C$39 -> 150000 | D19: =Assumptions!$C$39 -> 150000 | E19: =Assumptions!$C$39 -> 150000 | F19: =Assumptions!$D$39 -> 100000 | G19: =Assumptions!$D$39 -> 100000 | H19: =Assumptions!$D$39 -> 100000 | I19: =Assumptions!$E$39 -> 50000 | J19: =Assumptions!$E$39 -> 50000 | K19: =Assumptions!$E$39 -> 50000
A20: Opex: fixed data / licence | B20: ₹ / yr | C20: =Assumptions!$C$30 -> 236000 | D20: =Assumptions!$C$30 -> 236000 | E20: =Assumptions!$C$30 -> 236000 | F20: =Assumptions!$D$30 -> 236000 | G20: =Assumptions!$D$30 -> 236000 | H20: =Assumptions!$D$30 -> 236000 | I20: =Assumptions!$E$30 -> 236000 | J20: =Assumptions!$E$30 -> 236000 | K20: =Assumptions!$E$30 -> 236000 | L20: JMK report.
A21: Opex: fixed compute (+ Open-Meteo if flagged) × USD/INR | B21: ₹ / yr | C21: =(Assumptions!$C$12+Assumptions!$C$33*Assumptions!$C$13)*Assumptions!$C$4*12 -> 41760 | D21: =(Assumptions!$C$12+Assumptions!$C$33*Assumptions!$C$13)*Assumptions!$C$4*12 -> 41760 | E21: =(Assumptions!$C$12+Assumptions!$C$33*Assumptions!$C$13)*Assumptions!$C$4*12 -> 41760 | F21: =(Assumptions!$D$12+Assumptions!$D$33*Assumptions!$D$13)*Assumptions!$C$4*12 -> 26100 | G21: =(Assumptions!$D$12+Assumptions!$D$33*Assumptions!$D$13)*Assumptions!$C$4*12 -> 26100 | H21: =(Assumptions!$D$12+Assumptions!$D$33*Assumptions!$D$13)*Assumptions!$C$4*12 -> 26100 | I21: =(Assumptions!$E$12+Assumptions!$E$33*Assumptions!$E$13)*Assumptions!$C$4*12 -> 15660 | J21: =(Assumptions!$E$12+Assumptions!$E$33*Assumptions!$E$13)*Assumptions!$C$4*12 -> 15660 | K21: =(Assumptions!$E$12+Assumptions!$E$33*Assumptions!$E$13)*Assumptions!$C$4*12 -> 15660
A22: Opex: replacement acquisition (customers × churn × cost to acquire) | B22: ₹ / yr | C22: =C$5*Assumptions!$C$27*'Unit economics'!$C$17 -> 475000 | D22: =D$5*Assumptions!$C$27*'Unit economics'!$C$17 -> 4750000 | E22: =E$5*Assumptions!$C$27*'Unit economics'!$C$17 -> 47500000 | F22: =F$5*Assumptions!$D$27*'Unit economics'!$D$17 -> 95400 | G22: =G$5*Assumptions!$D$27*'Unit economics'!$D$17 -> 954000 | H22: =H$5*Assumptions!$D$27*'Unit economics'!$D$17 -> 9540000 | I22: =I$5*Assumptions!$E$27*'Unit economics'!$E$17 -> 22600 | J22: =J$5*Assumptions!$E$27*'Unit economics'!$E$17 -> 226000 | K22: =K$5*Assumptions!$E$27*'Unit economics'!$E$17 -> 2260000
A23: Total opex | B23: ₹ / yr | C23: =SUM(C16:C22) -> 1902760 | D23: =SUM(D16:D22) -> 10977760 | E23: =SUM(E16:E22) -> 58527760 | F23: =SUM(F16:F22) -> 1357500 | G23: =SUM(G16:G22) -> 4016100 | H23: =SUM(H16:H22) -> 14402100 | I23: =SUM(I16:I22) -> 1174260 | J23: =SUM(J16:J22) -> 2877660 | K23: =SUM(K16:K22) -> 6411660
A24: EBITDA | B24: ₹ / yr | C24: =C13-C23 -> -541760 | D24: =D13-D23 -> 2632240 | E24: =E13-E23 -> 77572240 | F24: =F13-F23 -> 5148000 | G24: =G13-G23 -> 61038900 | H24: =H13-H23 -> 636147900 | I24: =I13-I23 -> 27131740 | J24: =J13-J23 -> 280182340 | K24: =K13-K23 -> 2824188340
A25: EBITDA margin | B25: % | C25: =IF(C11=0,0,C24/C11) -> -0.33339077 | D25: =IF(D11=0,0,D24/D11) -> 0.161984 | E25: =IF(E11=0,0,E24/E11) -> 0.47736763 | F25: =IF(F11=0,0,F24/F11) -> 0.77559322 | G25: =IF(G11=0,0,G24/G11) -> 0.91960678 | H25: =IF(H11=0,0,H24/H11) -> 0.95841492 | I25: =IF(I11=0,0,I24/I11) -> 0.95618467 | J25: =IF(J11=0,0,J24/J11) -> 0.98742675 | K25: =IF(K11=0,0,K24/K11) -> 0.99530867
A26: Reachable segment (organisations) | B26: count | C26: =Assumptions!$C$15 -> 900 | D26: =Assumptions!$C$15 -> 900 | E26: =Assumptions!$C$15 -> 900 | F26: =Assumptions!$D$15 -> 1500 | G26: =Assumptions!$D$15 -> 1500 | H26: =Assumptions!$D$15 -> 1500 | I26: =Assumptions!$E$15 -> 3000 | J26: =Assumptions!$E$15 -> 3000 | K26: =Assumptions!$E$15 -> 3000
A27: Customers reachable at the assumed win rate (segment × win rate) | B27: count | C27: =Assumptions!$C$15*Assumptions!$C$25 -> 45 | D27: =Assumptions!$C$15*Assumptions!$C$25 -> 45 | E27: =Assumptions!$C$15*Assumptions!$C$25 -> 45 | F27: =Assumptions!$D$15*Assumptions!$D$25 -> 150 | G27: =Assumptions!$D$15*Assumptions!$D$25 -> 150 | H27: =Assumptions!$D$15*Assumptions!$D$25 -> 150 | I27: =Assumptions!$E$15*Assumptions!$E$25 -> 600 | J27: =Assumptions!$E$15*Assumptions!$E$25 -> 600 | K27: =Assumptions!$E$15*Assumptions!$E$25 -> 600
A28: Feasibility flag | C28: =IF(C$5>Assumptions!$C$15,"EXCEEDS reachable segment",IF(C$5>Assumptions!$C$15*Assumptions!$C$25,"Needs "&TEXT(C$5/Assumptions!$C$15,"0%")&" of segment (> win rate)","Within reach")) -> Within reach | D28: =IF(D$5>Assumptions!$C$15,"EXCEEDS reachable segment",IF(D$5>Assumptions!$C$15*Assumptions!$C$25,"Needs "&TEXT(D$5/Assumptions!$C$15,"0%")&" of segment (> win rate)","Within reach")) -> Needs 11% of segment (> win rate) | E28: =IF(E$5>Assumptions!$C$15,"EXCEEDS reachable segment",IF(E$5>Assumptions!$C$15*Assumptions!$C$25,"Needs "&TEXT(E$5/Assumptions!$C$15,"0%")&" of segment (> win rate)","Within reach")) -> EXCEEDS reachable segment | F28: =IF(F$5>Assumptions!$D$15,"EXCEEDS reachable segment",IF(F$5>Assumptions!$D$15*Assumptions!$D$25,"Needs "&TEXT(F$5/Assumptions!$D$15,"0%")&" of segment (> win rate)","Within reach")) -> Within reach | G28: =IF(G$5>Assumptions!$D$15,"EXCEEDS reachable segment",IF(G$5>Assumptions!$D$15*Assumptions!$D$25,"Needs "&TEXT(G$5/Assumptions!$D$15,"0%")&" of segment (> win rate)","Within reach")) -> Within reach | H28: =IF(H$5>Assumptions!$D$15,"EXCEEDS reachable segment",IF(H$5>Assumptions!$D$15*Assumptions!$D$25,"Needs "&TEXT(H$5/Assumptions!$D$15,"0%")&" of segment (> win rate)","Within reach")) -> Needs 67% of segment (> win rate) | I28: =IF(I$5>Assumptions!$E$15,"EXCEEDS reachable segment",IF(I$5>Assumptions!$E$15*Assumptions!$E$25,"Needs "&TEXT(I$5/Assumptions!$E$15,"0%")&" of segment (> win rate)","Within reach")) -> Within reach | J28: =IF(J$5>Assumptions!$E$15,"EXCEEDS reachable segment",IF(J$5>Assumptions!$E$15*Assumptions!$E$25,"Needs "&TEXT(J$5/Assumptions!$E$15,"0%")&" of segment (> win rate)","Within reach")) -> Within reach | K28: =IF(K$5>Assumptions!$E$15,"EXCEEDS reachable segment",IF(K$5>Assumptions!$E$15*Assumptions!$E$25,"Needs "&TEXT(K$5/Assumptions!$E$15,"0%")&" of segment (> win rate)","Within reach")) -> Needs 33% of segment (> win rate)
A30: F1 — ISTS connectivity / GNA intelligence
A31: Customers | B31: count | C31: =C$5 -> 10 | D31: =D$5 -> 100 | E31: =E$5 -> 1000 | F31: =F$5 -> 10 | G31: =G$5 -> 100 | H31: =H$5 -> 1000 | I31: =I$5 -> 10 | J31: =J$5 -> 100 | K31: =K$5 -> 1000
A32: Recurring revenue (customers × steady-state ARPA) | B32: ₹ / yr | C32: =C$5*'Unit economics'!$C$29 -> 3000000 | D32: =D$5*'Unit economics'!$C$29 -> 30000000 | E32: =E$5*'Unit economics'!$C$29 -> 300000000 | F32: =F$5*'Unit economics'!$D$29 -> 6000000 | G32: =G$5*'Unit economics'!$D$29 -> 60000000 | H32: =H$5*'Unit economics'!$D$29 -> 600000000 | I32: =I$5*'Unit economics'!$E$29 -> 14000000 | J32: =J$5*'Unit economics'!$E$29 -> 140000000 | K32: =K$5*'Unit economics'!$E$29 -> 1400000000
A33: One-time fees on replacement customers (customers × churn × one-time fee) | B33: ₹ / yr | C33: =C$5*Assumptions!$C$50*'Unit economics'!$C$28 -> 0 | D33: =D$5*Assumptions!$C$50*'Unit economics'!$C$28 -> 0 | E33: =E$5*Assumptions!$C$50*'Unit economics'!$C$28 -> 0 | F33: =F$5*Assumptions!$D$50*'Unit economics'!$D$28 -> 0 | G33: =G$5*Assumptions!$D$50*'Unit economics'!$D$28 -> 0 | H33: =H$5*Assumptions!$D$50*'Unit economics'!$D$28 -> 0 | I33: =I$5*Assumptions!$E$50*'Unit economics'!$E$28 -> 0 | J33: =J$5*Assumptions!$E$50*'Unit economics'!$E$28 -> 0 | K33: =K$5*Assumptions!$E$50*'Unit economics'!$E$28 -> 0
A34: Total revenue | B34: ₹ / yr | C34: =C32+C33 -> 3000000 | D34: =D32+D33 -> 30000000 | E34: =E32+E33 -> 300000000 | F34: =F32+F33 -> 6000000 | G34: =G32+G33 -> 60000000 | H34: =H32+H33 -> 600000000 | I34: =I32+I33 -> 14000000 | J34: =J32+J33 -> 140000000 | K34: =K32+K33 -> 1400000000
A35: COGS (customers × variable cost) | B35: ₹ / yr | C35: =C$5*'Unit economics'!$C$32 -> 192000 | D35: =D$5*'Unit economics'!$C$32 -> 1920000 | E35: =E$5*'Unit economics'!$C$32 -> 19200000 | F35: =F$5*'Unit economics'!$D$32 -> 102000 | G35: =G$5*'Unit economics'!$D$32 -> 1020000 | H35: =H$5*'Unit economics'!$D$32 -> 10200000 | I35: =I$5*'Unit economics'!$E$32 -> 45000 | J35: =J$5*'Unit economics'!$E$32 -> 450000 | K35: =K$5*'Unit economics'!$E$32 -> 4500000
A36: Gross margin | B36: ₹ / yr | C36: =C34-C35 -> 2808000 | D36: =D34-D35 -> 28080000 | E36: =E34-E35 -> 280800000 | F36: =F34-F35 -> 5898000 | G36: =G34-G35 -> 58980000 | H36: =H34-H35 -> 589800000 | I36: =I34-I35 -> 13955000 | J36: =J34-J35 -> 139550000 | K36: =K34-K35 -> 1395500000
A37: Gross margin % | B37: % | C37: =IF(C34=0,0,C36/C34) -> 0.936 | D37: =IF(D34=0,0,D36/D34) -> 0.936 | E37: =IF(E34=0,0,E36/E34) -> 0.936 | F37: =IF(F34=0,0,F36/F34) -> 0.983 | G37: =IF(G34=0,0,G36/G34) -> 0.983 | H37: =IF(H34=0,0,H36/H34) -> 0.983 | I37: =IF(I34=0,0,I36/I34) -> 0.99678571 | J37: =IF(J34=0,0,J36/J34) -> 0.99678571 | K37: =IF(K34=0,0,K36/K34) -> 0.99678571
A38: Engineers at this stage (excl. founder) | B38: FTE | C38: =IF(C$5<=10,Assumptions!$C$58,IF(C$5<=100,Assumptions!$C$59,Assumptions!$C$60)) -> 0 | D38: =IF(D$5<=10,Assumptions!$C$58,IF(D$5<=100,Assumptions!$C$59,Assumptions!$C$60)) -> 2 | E38: =IF(E$5<=10,Assumptions!$C$58,IF(E$5<=100,Assumptions!$C$59,Assumptions!$C$60)) -> 3 | F38: =IF(F$5<=10,Assumptions!$D$58,IF(F$5<=100,Assumptions!$D$59,Assumptions!$D$60)) -> 0 | G38: =IF(G$5<=10,Assumptions!$D$58,IF(G$5<=100,Assumptions!$D$59,Assumptions!$D$60)) -> 1 | H38: =IF(H$5<=10,Assumptions!$D$58,IF(H$5<=100,Assumptions!$D$59,Assumptions!$D$60)) -> 2 | I38: =IF(I$5<=10,Assumptions!$E$58,IF(I$5<=100,Assumptions!$E$59,Assumptions!$E$60)) -> 0 | J38: =IF(J$5<=10,Assumptions!$E$58,IF(J$5<=100,Assumptions!$E$59,Assumptions!$E$60)) -> 1 | K38: =IF(K$5<=10,Assumptions!$E$58,IF(K$5<=100,Assumptions!$E$59,Assumptions!$E$60)) -> 2 | L38: Stage lookup on Assumptions eng10 / eng100 / eng1000.
A39: Opex: founder stipend | B39: ₹ / yr | C39: ='Path to first revenue'!$B$6*12 -> 600000 | D39: ='Path to first revenue'!$B$6*12 -> 600000 | E39: ='Path to first revenue'!$B$6*12 -> 600000 | F39: ='Path to first revenue'!$B$6*12 -> 600000 | G39: ='Path to first revenue'!$B$6*12 -> 600000 | H39: ='Path to first revenue'!$B$6*12 -> 600000 | I39: ='Path to first revenue'!$B$6*12 -> 600000 | J39: ='Path to first revenue'!$B$6*12 -> 600000 | K39: ='Path to first revenue'!$B$6*12 -> 600000 | L39: From Path to first revenue (input).
A40: Opex: engineers | B40: ₹ / yr | C40: =C38*Assumptions!$C$10*12 -> 0 | D40: =D38*Assumptions!$C$10*12 -> 4800000 | E40: =E38*Assumptions!$C$10*12 -> 7200000 | F40: =F38*Assumptions!$D$10*12 -> 0 | G40: =G38*Assumptions!$D$10*12 -> 1800000 | H40: =H38*Assumptions!$D$10*12 -> 3600000 | I40: =I38*Assumptions!$E$10*12 -> 0 | J40: =J38*Assumptions!$E$10*12 -> 1500000 | K40: =K38*Assumptions!$E$10*12 -> 3000000
A41: Opex: G&A fixed | B41: ₹ / yr | C41: =Assumptions!$C$11 -> 400000 | D41: =Assumptions!$C$11 -> 400000 | E41: =Assumptions!$C$11 -> 400000 | F41: =Assumptions!$D$11 -> 300000 | G41: =Assumptions!$D$11 -> 300000 | H41: =Assumptions!$D$11 -> 300000 | I41: =Assumptions!$E$11 -> 250000 | J41: =Assumptions!$E$11 -> 250000 | K41: =Assumptions!$E$11 -> 250000
A42: Opex: conferences / events | B42: ₹ / yr | C42: =Assumptions!$C$63 -> 200000 | D42: =Assumptions!$C$63 -> 200000 | E42: =Assumptions!$C$63 -> 200000 | F42: =Assumptions!$D$63 -> 150000 | G42: =Assumptions!$D$63 -> 150000 | H42: =Assumptions!$D$63 -> 150000 | I42: =Assumptions!$E$63 -> 100000 | J42: =Assumptions!$E$63 -> 100000 | K42: =Assumptions!$E$63 -> 100000
A43: Opex: fixed data / licence | B43: ₹ / yr | C43: =Assumptions!$C$54 -> 500000 | D43: =Assumptions!$C$54 -> 500000 | E43: =Assumptions!$C$54 -> 500000 | F43: =Assumptions!$D$54 -> 0 | G43: =Assumptions!$D$54 -> 0 | H43: =Assumptions!$D$54 -> 0 | I43: =Assumptions!$E$54 -> 0 | J43: =Assumptions!$E$54 -> 0 | K43: =Assumptions!$E$54 -> 0 | L43: CTUIL licence placeholder (unknown).
A44: Opex: fixed compute (+ Open-Meteo if flagged) × USD/INR | B44: ₹ / yr | C44: =(Assumptions!$C$12+Assumptions!$C$57*Assumptions!$C$13)*Assumptions!$C$4*12 -> 41760 | D44: =(Assumptions!$C$12+Assumptions!$C$57*Assumptions!$C$13)*Assumptions!$C$4*12 -> 41760 | E44: =(Assumptions!$C$12+Assumptions!$C$57*Assumptions!$C$13)*Assumptions!$C$4*12 -> 41760 | F44: =(Assumptions!$D$12+Assumptions!$D$57*Assumptions!$D$13)*Assumptions!$C$4*12 -> 26100 | G44: =(Assumptions!$D$12+Assumptions!$D$57*Assumptions!$D$13)*Assumptions!$C$4*12 -> 26100 | H44: =(Assumptions!$D$12+Assumptions!$D$57*Assumptions!$D$13)*Assumptions!$C$4*12 -> 26100 | I44: =(Assumptions!$E$12+Assumptions!$E$57*Assumptions!$E$13)*Assumptions!$C$4*12 -> 15660 | J44: =(Assumptions!$E$12+Assumptions!$E$57*Assumptions!$E$13)*Assumptions!$C$4*12 -> 15660 | K44: =(Assumptions!$E$12+Assumptions!$E$57*Assumptions!$E$13)*Assumptions!$C$4*12 -> 15660
A45: Opex: replacement acquisition (customers × churn × cost to acquire) | B45: ₹ / yr | C45: =C$5*Assumptions!$C$50*'Unit economics'!$C$37 -> 1374000 | D45: =D$5*Assumptions!$C$50*'Unit economics'!$C$37 -> 13740000 | E45: =E$5*Assumptions!$C$50*'Unit economics'!$C$37 -> 137400000 | F45: =F$5*Assumptions!$D$50*'Unit economics'!$D$37 -> 307900 | G45: =G$5*Assumptions!$D$50*'Unit economics'!$D$37 -> 3079000 | H45: =H$5*Assumptions!$D$50*'Unit economics'!$D$37 -> 30790000 | I45: =I$5*Assumptions!$E$50*'Unit economics'!$E$37 -> 94150 | J45: =J$5*Assumptions!$E$50*'Unit economics'!$E$37 -> 941500 | K45: =K$5*Assumptions!$E$50*'Unit economics'!$E$37 -> 9415000
A46: Total opex | B46: ₹ / yr | C46: =SUM(C39:C45) -> 3115760 | D46: =SUM(D39:D45) -> 20281760 | E46: =SUM(E39:E45) -> 146341760 | F46: =SUM(F39:F45) -> 1384000 | G46: =SUM(G39:G45) -> 5955100 | H46: =SUM(H39:H45) -> 35466100 | I46: =SUM(I39:I45) -> 1059810 | J46: =SUM(J39:J45) -> 3407160 | K46: =SUM(K39:K45) -> 13380660
A47: EBITDA | B47: ₹ / yr | C47: =C36-C46 -> -307760 | D47: =D36-D46 -> 7798240 | E47: =E36-E46 -> 134458240 | F47: =F36-F46 -> 4514000 | G47: =G36-G46 -> 53024900 | H47: =H36-H46 -> 554333900 | I47: =I36-I46 -> 12895190 | J47: =J36-J46 -> 136142840 | K47: =K36-K46 -> 1382119340
A48: EBITDA margin | B48: % | C48: =IF(C34=0,0,C47/C34) -> -0.10258667 | D48: =IF(D34=0,0,D47/D34) -> 0.25994133 | E48: =IF(E34=0,0,E47/E34) -> 0.44819413 | F48: =IF(F34=0,0,F47/F34) -> 0.75233333 | G48: =IF(G34=0,0,G47/G34) -> 0.88374833 | H48: =IF(H34=0,0,H47/H34) -> 0.92388983 | I48: =IF(I34=0,0,I47/I34) -> 0.921085 | J48: =IF(J34=0,0,J47/J34) -> 0.97244886 | K48: =IF(K34=0,0,K47/K34) -> 0.9872281
A49: Reachable segment (organisations) | B49: count | C49: =Assumptions!$C$44 -> 70 | D49: =Assumptions!$C$44 -> 70 | E49: =Assumptions!$C$44 -> 70 | F49: =Assumptions!$D$44 -> 200 | G49: =Assumptions!$D$44 -> 200 | H49: =Assumptions!$D$44 -> 200 | I49: =Assumptions!$E$44 -> 400 | J49: =Assumptions!$E$44 -> 400 | K49: =Assumptions!$E$44 -> 400
A50: Customers reachable at the assumed win rate (segment × win rate) | B50: count | C50: =Assumptions!$C$44*Assumptions!$C$48 -> 3.5 | D50: =Assumptions!$C$44*Assumptions!$C$48 -> 3.5 | E50: =Assumptions!$C$44*Assumptions!$C$48 -> 3.5 | F50: =Assumptions!$D$44*Assumptions!$D$48 -> 20 | G50: =Assumptions!$D$44*Assumptions!$D$48 -> 20 | H50: =Assumptions!$D$44*Assumptions!$D$48 -> 20 | I50: =Assumptions!$E$44*Assumptions!$E$48 -> 60 | J50: =Assumptions!$E$44*Assumptions!$E$48 -> 60 | K50: =Assumptions!$E$44*Assumptions!$E$48 -> 60
A51: Feasibility flag | C51: =IF(C$5>Assumptions!$C$44,"EXCEEDS reachable segment",IF(C$5>Assumptions!$C$44*Assumptions!$C$48,"Needs "&TEXT(C$5/Assumptions!$C$44,"0%")&" of segment (> win rate)","Within reach")) -> Needs 14% of segment (> win rate) | D51: =IF(D$5>Assumptions!$C$44,"EXCEEDS reachable segment",IF(D$5>Assumptions!$C$44*Assumptions!$C$48,"Needs "&TEXT(D$5/Assumptions!$C$44,"0%")&" of segment (> win rate)","Within reach")) -> EXCEEDS reachable segment | E51: =IF(E$5>Assumptions!$C$44,"EXCEEDS reachable segment",IF(E$5>Assumptions!$C$44*Assumptions!$C$48,"Needs "&TEXT(E$5/Assumptions!$C$44,"0%")&" of segment (> win rate)","Within reach")) -> EXCEEDS reachable segment | F51: =IF(F$5>Assumptions!$D$44,"EXCEEDS reachable segment",IF(F$5>Assumptions!$D$44*Assumptions!$D$48,"Needs "&TEXT(F$5/Assumptions!$D$44,"0%")&" of segment (> win rate)","Within reach")) -> Within reach | G51: =IF(G$5>Assumptions!$D$44,"EXCEEDS reachable segment",IF(G$5>Assumptions!$D$44*Assumptions!$D$48,"Needs "&TEXT(G$5/Assumptions!$D$44,"0%")&" of segment (> win rate)","Within reach")) -> Needs 50% of segment (> win rate) | H51: =IF(H$5>Assumptions!$D$44,"EXCEEDS reachable segment",IF(H$5>Assumptions!$D$44*Assumptions!$D$48,"Needs "&TEXT(H$5/Assumptions!$D$44,"0%")&" of segment (> win rate)","Within reach")) -> EXCEEDS reachable segment | I51: =IF(I$5>Assumptions!$E$44,"EXCEEDS reachable segment",IF(I$5>Assumptions!$E$44*Assumptions!$E$48,"Needs "&TEXT(I$5/Assumptions!$E$44,"0%")&" of segment (> win rate)","Within reach")) -> Within reach | J51: =IF(J$5>Assumptions!$E$44,"EXCEEDS reachable segment",IF(J$5>Assumptions!$E$44*Assumptions!$E$48,"Needs "&TEXT(J$5/Assumptions!$E$44,"0%")&" of segment (> win rate)","Within reach")) -> Needs 25% of segment (> win rate) | K51: =IF(K$5>Assumptions!$E$44,"EXCEEDS reachable segment",IF(K$5>Assumptions!$E$44*Assumptions!$E$48,"Needs "&TEXT(K$5/Assumptions!$E$44,"0%")&" of segment (> win rate)","Within reach")) -> EXCEEDS reachable segment
A52: CTUIL permission gate | C52: =IF(Assumptions!$C$53=1,"Permission assumed","BLOCKED: revenue not bankable until CTUIL permission") -> BLOCKED: revenue not bankable until CTUIL permission | D52: =IF(Assumptions!$C$53=1,"Permission assumed","BLOCKED: revenue not bankable until CTUIL permission") -> BLOCKED: revenue not bankable until CTUIL permission | E52: =IF(Assumptions!$C$53=1,"Permission assumed","BLOCKED: revenue not bankable until CTUIL permission") -> BLOCKED: revenue not bankable until CTUIL permission | F52: =IF(Assumptions!$D$53=1,"Permission assumed","BLOCKED: revenue not bankable until CTUIL permission") -> Permission assumed | G52: =IF(Assumptions!$D$53=1,"Permission assumed","BLOCKED: revenue not bankable until CTUIL permission") -> Permission assumed | H52: =IF(Assumptions!$D$53=1,"Permission assumed","BLOCKED: revenue not bankable until CTUIL permission") -> Permission assumed | I52: =IF(Assumptions!$E$53=1,"Permission assumed","BLOCKED: revenue not bankable until CTUIL permission") -> Permission assumed | J52: =IF(Assumptions!$E$53=1,"Permission assumed","BLOCKED: revenue not bankable until CTUIL permission") -> Permission assumed | K52: =IF(Assumptions!$E$53=1,"Permission assumed","BLOCKED: revenue not bankable until CTUIL permission") -> Permission assumed | L52: Red-team Q5: reuse needs CTUIL permission; margins PDFs stamped RESTRICTED.
A53: Bankable revenue (total revenue × gate) | B53: ₹ / yr | C53: =C34*Assumptions!$C$53 -> 0 | D53: =D34*Assumptions!$C$53 -> 0 | E53: =E34*Assumptions!$C$53 -> 0 | F53: =F34*Assumptions!$D$53 -> 6000000 | G53: =G34*Assumptions!$D$53 -> 60000000 | H53: =H34*Assumptions!$D$53 -> 600000000 | I53: =I34*Assumptions!$E$53 -> 14000000 | J53: =J34*Assumptions!$E$53 -> 140000000 | K53: =K34*Assumptions!$E$53 -> 1400000000
A55: F3 — BESS / FDRE dispatch & compliance
A56: Customers | B56: count | C56: =C$5 -> 10 | D56: =D$5 -> 100 | E56: =E$5 -> 1000 | F56: =F$5 -> 10 | G56: =G$5 -> 100 | H56: =H$5 -> 1000 | I56: =I$5 -> 10 | J56: =J$5 -> 100 | K56: =K$5 -> 1000
A57: Recurring revenue (customers × steady-state ARPA) | B57: ₹ / yr | C57: =C$5*'Unit economics'!$C$49 -> 24000000 | D57: =D$5*'Unit economics'!$C$49 -> 240000000 | E57: =E$5*'Unit economics'!$C$49 -> 2400000000 | F57: =F$5*'Unit economics'!$D$49 -> 105000000 | G57: =G$5*'Unit economics'!$D$49 -> 1050000000 | H57: =H$5*'Unit economics'!$D$49 -> 10500000000 | I57: =I$5*'Unit economics'!$E$49 -> 378240000 | J57: =J$5*'Unit economics'!$E$49 -> 3782400000 | K57: =K$5*'Unit economics'!$E$49 -> 37824000000
A58: One-time fees on replacement customers (customers × churn × one-time fee) | B58: ₹ / yr | C58: =C$5*Assumptions!$C$76*'Unit economics'!$C$48 -> 0 | D58: =D$5*Assumptions!$C$76*'Unit economics'!$C$48 -> 0 | E58: =E$5*Assumptions!$C$76*'Unit economics'!$C$48 -> 0 | F58: =F$5*Assumptions!$D$76*'Unit economics'!$D$48 -> 0 | G58: =G$5*Assumptions!$D$76*'Unit economics'!$D$48 -> 0 | H58: =H$5*Assumptions!$D$76*'Unit economics'!$D$48 -> 0 | I58: =I$5*Assumptions!$E$76*'Unit economics'!$E$48 -> 0 | J58: =J$5*Assumptions!$E$76*'Unit economics'!$E$48 -> 0 | K58: =K$5*Assumptions!$E$76*'Unit economics'!$E$48 -> 0
A59: Total revenue | B59: ₹ / yr | C59: =C57+C58 -> 24000000 | D59: =D57+D58 -> 240000000 | E59: =E57+E58 -> 2400000000 | F59: =F57+F58 -> 105000000 | G59: =G57+G58 -> 1050000000 | H59: =H57+H58 -> 10500000000 | I59: =I57+I58 -> 378240000 | J59: =J57+J58 -> 3782400000 | K59: =K57+K58 -> 37824000000
A60: COGS (customers × variable cost) | B60: ₹ / yr | C60: =C$5*'Unit economics'!$C$51 -> 840000 | D60: =D$5*'Unit economics'!$C$51 -> 8400000 | E60: =E$5*'Unit economics'!$C$51 -> 84000000 | F60: =F$5*'Unit economics'!$D$51 -> 444000 | G60: =G$5*'Unit economics'!$D$51 -> 4440000 | H60: =H$5*'Unit economics'!$D$51 -> 44400000 | I60: =I$5*'Unit economics'!$E$51 -> 246000 | J60: =J$5*'Unit economics'!$E$51 -> 2460000 | K60: =K$5*'Unit economics'!$E$51 -> 24600000
A61: Gross margin | B61: ₹ / yr | C61: =C59-C60 -> 23160000 | D61: =D59-D60 -> 231600000 | E61: =E59-E60 -> 2316000000 | F61: =F59-F60 -> 104556000 | G61: =G59-G60 -> 1045560000 | H61: =H59-H60 -> 10455600000 | I61: =I59-I60 -> 377994000 | J61: =J59-J60 -> 3779940000 | K61: =K59-K60 -> 37799400000
A62: Gross margin % | B62: % | C62: =IF(C59=0,0,C61/C59) -> 0.965 | D62: =IF(D59=0,0,D61/D59) -> 0.965 | E62: =IF(E59=0,0,E61/E59) -> 0.965 | F62: =IF(F59=0,0,F61/F59) -> 0.99577143 | G62: =IF(G59=0,0,G61/G59) -> 0.99577143 | H62: =IF(H59=0,0,H61/H59) -> 0.99577143 | I62: =IF(I59=0,0,I61/I59) -> 0.99934962 | J62: =IF(J59=0,0,J61/J59) -> 0.99934962 | K62: =IF(K59=0,0,K61/K59) -> 0.99934962
A63: Engineers at this stage (excl. founder) | B63: FTE | C63: =IF(C$5<=10,Assumptions!$C$83,IF(C$5<=100,Assumptions!$C$84,Assumptions!$C$85)) -> 1 | D63: =IF(D$5<=10,Assumptions!$C$83,IF(D$5<=100,Assumptions!$C$84,Assumptions!$C$85)) -> 2 | E63: =IF(E$5<=10,Assumptions!$C$83,IF(E$5<=100,Assumptions!$C$84,Assumptions!$C$85)) -> 4 | F63: =IF(F$5<=10,Assumptions!$D$83,IF(F$5<=100,Assumptions!$D$84,Assumptions!$D$85)) -> 1 | G63: =IF(G$5<=10,Assumptions!$D$83,IF(G$5<=100,Assumptions!$D$84,Assumptions!$D$85)) -> 2 | H63: =IF(H$5<=10,Assumptions!$D$83,IF(H$5<=100,Assumptions!$D$84,Assumptions!$D$85)) -> 3 | I63: =IF(I$5<=10,Assumptions!$E$83,IF(I$5<=100,Assumptions!$E$84,Assumptions!$E$85)) -> 0 | J63: =IF(J$5<=10,Assumptions!$E$83,IF(J$5<=100,Assumptions!$E$84,Assumptions!$E$85)) -> 1 | K63: =IF(K$5<=10,Assumptions!$E$83,IF(K$5<=100,Assumptions!$E$84,Assumptions!$E$85)) -> 2 | L63: Stage lookup on Assumptions eng10 / eng100 / eng1000.
A64: Opex: founder stipend | B64: ₹ / yr | C64: ='Path to first revenue'!$B$6*12 -> 600000 | D64: ='Path to first revenue'!$B$6*12 -> 600000 | E64: ='Path to first revenue'!$B$6*12 -> 600000 | F64: ='Path to first revenue'!$B$6*12 -> 600000 | G64: ='Path to first revenue'!$B$6*12 -> 600000 | H64: ='Path to first revenue'!$B$6*12 -> 600000 | I64: ='Path to first revenue'!$B$6*12 -> 600000 | J64: ='Path to first revenue'!$B$6*12 -> 600000 | K64: ='Path to first revenue'!$B$6*12 -> 600000 | L64: From Path to first revenue (input).
A65: Opex: engineers | B65: ₹ / yr | C65: =C63*Assumptions!$C$10*12 -> 2400000 | D65: =D63*Assumptions!$C$10*12 -> 4800000 | E65: =E63*Assumptions!$C$10*12 -> 9600000 | F65: =F63*Assumptions!$D$10*12 -> 1800000 | G65: =G63*Assumptions!$D$10*12 -> 3600000 | H65: =H63*Assumptions!$D$10*12 -> 5400000 | I65: =I63*Assumptions!$E$10*12 -> 0 | J65: =J63*Assumptions!$E$10*12 -> 1500000 | K65: =K63*Assumptions!$E$10*12 -> 3000000
A66: Opex: G&A fixed | B66: ₹ / yr | C66: =Assumptions!$C$11 -> 400000 | D66: =Assumptions!$C$11 -> 400000 | E66: =Assumptions!$C$11 -> 400000 | F66: =Assumptions!$D$11 -> 300000 | G66: =Assumptions!$D$11 -> 300000 | H66: =Assumptions!$D$11 -> 300000 | I66: =Assumptions!$E$11 -> 250000 | J66: =Assumptions!$E$11 -> 250000 | K66: =Assumptions!$E$11 -> 250000
A67: Opex: conferences / events | B67: ₹ / yr | C67: =Assumptions!$C$88 -> 300000 | D67: =Assumptions!$C$88 -> 300000 | E67: =Assumptions!$C$88 -> 300000 | F67: =Assumptions!$D$88 -> 200000 | G67: =Assumptions!$D$88 -> 200000 | H67: =Assumptions!$D$88 -> 200000 | I67: =Assumptions!$E$88 -> 150000 | J67: =Assumptions!$E$88 -> 150000 | K67: =Assumptions!$E$88 -> 150000
A68: Opex: fixed data / licence | B68: ₹ / yr | C68: =Assumptions!$C$79 -> 1000000 | D68: =Assumptions!$C$79 -> 1000000 | E68: =Assumptions!$C$79 -> 1000000 | F68: =Assumptions!$D$79 -> 500000 | G68: =Assumptions!$D$79 -> 500000 | H68: =Assumptions!$D$79 -> 500000 | I68: =Assumptions!$E$79 -> 200000 | J68: =Assumptions!$E$79 -> 200000 | K68: =Assumptions!$E$79 -> 200000 | L68: IEX data licence placeholder (unknown).
A69: Opex: fixed compute (+ Open-Meteo if flagged) × USD/INR | B69: ₹ / yr | C69: =(Assumptions!$C$12+Assumptions!$C$82*Assumptions!$C$13)*Assumptions!$C$4*12 -> 145116 | D69: =(Assumptions!$C$12+Assumptions!$C$82*Assumptions!$C$13)*Assumptions!$C$4*12 -> 145116 | E69: =(Assumptions!$C$12+Assumptions!$C$82*Assumptions!$C$13)*Assumptions!$C$4*12 -> 145116 | F69: =(Assumptions!$D$12+Assumptions!$D$82*Assumptions!$D$13)*Assumptions!$C$4*12 -> 129456 | G69: =(Assumptions!$D$12+Assumptions!$D$82*Assumptions!$D$13)*Assumptions!$C$4*12 -> 129456 | H69: =(Assumptions!$D$12+Assumptions!$D$82*Assumptions!$D$13)*Assumptions!$C$4*12 -> 129456 | I69: =(Assumptions!$E$12+Assumptions!$E$82*Assumptions!$E$13)*Assumptions!$C$4*12 -> 119016 | J69: =(Assumptions!$E$12+Assumptions!$E$82*Assumptions!$E$13)*Assumptions!$C$4*12 -> 119016 | K69: =(Assumptions!$E$12+Assumptions!$E$82*Assumptions!$E$13)*Assumptions!$C$4*12 -> 119016
A70: Opex: replacement acquisition (customers × churn × cost to acquire) | B70: ₹ / yr | C70: =C$5*Assumptions!$C$76*'Unit economics'!$C$56 -> 1820000 | D70: =D$5*Assumptions!$C$76*'Unit economics'!$C$56 -> 18200000 | E70: =E$5*Assumptions!$C$76*'Unit economics'!$C$56 -> 182000000 | F70: =F$5*Assumptions!$D$76*'Unit economics'!$D$56 -> 498000 | G70: =G$5*Assumptions!$D$76*'Unit economics'!$D$56 -> 4980000 | H70: =H$5*Assumptions!$D$76*'Unit economics'!$D$56 -> 49800000 | I70: =I$5*Assumptions!$E$76*'Unit economics'!$E$56 -> 128500 | J70: =J$5*Assumptions!$E$76*'Unit economics'!$E$56 -> 1285000 | K70: =K$5*Assumptions!$E$76*'Unit economics'!$E$56 -> 12850000
A71: Total opex | B71: ₹ / yr | C71: =SUM(C64:C70) -> 6665116 | D71: =SUM(D64:D70) -> 25445116 | E71: =SUM(E64:E70) -> 194045116 | F71: =SUM(F64:F70) -> 4027456 | G71: =SUM(G64:G70) -> 10309456 | H71: =SUM(H64:H70) -> 56929456 | I71: =SUM(I64:I70) -> 1447516 | J71: =SUM(J64:J70) -> 4104016 | K71: =SUM(K64:K70) -> 17169016
A72: EBITDA | B72: ₹ / yr | C72: =C61-C71 -> 16494884 | D72: =D61-D71 -> 206154884 | E72: =E61-E71 -> 2121954884 | F72: =F61-F71 -> 100528544 | G72: =G61-G71 -> 1035250544 | H72: =H61-H71 -> 10398670544 | I72: =I61-I71 -> 376546484 | J72: =J61-J71 -> 3775835984 | K72: =K61-K71 -> 37782230984
A73: EBITDA margin | B73: % | C73: =IF(C59=0,0,C72/C59) -> 0.68728683 | D73: =IF(D59=0,0,D72/D59) -> 0.85897868 | E73: =IF(E59=0,0,E72/E59) -> 0.88414787 | F73: =IF(F59=0,0,F72/F59) -> 0.9574147 | G73: =IF(G59=0,0,G72/G59) -> 0.9859529 | H73: =IF(H59=0,0,H72/H59) -> 0.99034958 | I73: =IF(I59=0,0,I72/I59) -> 0.99552264 | J73: =IF(J59=0,0,J72/J59) -> 0.99826459 | K73: =IF(K59=0,0,K72/K59) -> 0.9988957
A74: Reachable segment (organisations) | B74: count | C74: =Assumptions!$C$67 -> 15 | D74: =Assumptions!$C$67 -> 15 | E74: =Assumptions!$C$67 -> 15 | F74: =Assumptions!$D$67 -> 30 | G74: =Assumptions!$D$67 -> 30 | H74: =Assumptions!$D$67 -> 30 | I74: =Assumptions!$E$67 -> 60 | J74: =Assumptions!$E$67 -> 60 | K74: =Assumptions!$E$67 -> 60
A75: Customers reachable at the assumed win rate (segment × win rate) | B75: count | C75: =Assumptions!$C$67*Assumptions!$C$74 -> 0.75 | D75: =Assumptions!$C$67*Assumptions!$C$74 -> 0.75 | E75: =Assumptions!$C$67*Assumptions!$C$74 -> 0.75 | F75: =Assumptions!$D$67*Assumptions!$D$74 -> 3 | G75: =Assumptions!$D$67*Assumptions!$D$74 -> 3 | H75: =Assumptions!$D$67*Assumptions!$D$74 -> 3 | I75: =Assumptions!$E$67*Assumptions!$E$74 -> 12 | J75: =Assumptions!$E$67*Assumptions!$E$74 -> 12 | K75: =Assumptions!$E$67*Assumptions!$E$74 -> 12
A76: Feasibility flag | C76: =IF(C$5>Assumptions!$C$67,"EXCEEDS reachable segment",IF(C$5>Assumptions!$C$67*Assumptions!$C$74,"Needs "&TEXT(C$5/Assumptions!$C$67,"0%")&" of segment (> win rate)","Within reach")) -> Needs 67% of segment (> win rate) | D76: =IF(D$5>Assumptions!$C$67,"EXCEEDS reachable segment",IF(D$5>Assumptions!$C$67*Assumptions!$C$74,"Needs "&TEXT(D$5/Assumptions!$C$67,"0%")&" of segment (> win rate)","Within reach")) -> EXCEEDS reachable segment | E76: =IF(E$5>Assumptions!$C$67,"EXCEEDS reachable segment",IF(E$5>Assumptions!$C$67*Assumptions!$C$74,"Needs "&TEXT(E$5/Assumptions!$C$67,"0%")&" of segment (> win rate)","Within reach")) -> EXCEEDS reachable segment | F76: =IF(F$5>Assumptions!$D$67,"EXCEEDS reachable segment",IF(F$5>Assumptions!$D$67*Assumptions!$D$74,"Needs "&TEXT(F$5/Assumptions!$D$67,"0%")&" of segment (> win rate)","Within reach")) -> Needs 33% of segment (> win rate) | G76: =IF(G$5>Assumptions!$D$67,"EXCEEDS reachable segment",IF(G$5>Assumptions!$D$67*Assumptions!$D$74,"Needs "&TEXT(G$5/Assumptions!$D$67,"0%")&" of segment (> win rate)","Within reach")) -> EXCEEDS reachable segment | H76: =IF(H$5>Assumptions!$D$67,"EXCEEDS reachable segment",IF(H$5>Assumptions!$D$67*Assumptions!$D$74,"Needs "&TEXT(H$5/Assumptions!$D$67,"0%")&" of segment (> win rate)","Within reach")) -> EXCEEDS reachable segment | I76: =IF(I$5>Assumptions!$E$67,"EXCEEDS reachable segment",IF(I$5>Assumptions!$E$67*Assumptions!$E$74,"Needs "&TEXT(I$5/Assumptions!$E$67,"0%")&" of segment (> win rate)","Within reach")) -> Within reach | J76: =IF(J$5>Assumptions!$E$67,"EXCEEDS reachable segment",IF(J$5>Assumptions!$E$67*Assumptions!$E$74,"Needs "&TEXT(J$5/Assumptions!$E$67,"0%")&" of segment (> win rate)","Within reach")) -> EXCEEDS reachable segment | K76: =IF(K$5>Assumptions!$E$67,"EXCEEDS reachable segment",IF(K$5>Assumptions!$E$67*Assumptions!$E$74,"Needs "&TEXT(K$5/Assumptions!$E$67,"0%")&" of segment (> win rate)","Within reach")) -> EXCEEDS reachable segment
A77: MW under management (customers × MW per customer) | B77: MW | C77: =C$5*Assumptions!$C$69 -> 1000 | D77: =D$5*Assumptions!$C$69 -> 10000 | E77: =E$5*Assumptions!$C$69 -> 100000 | F77: =F$5*Assumptions!$D$69 -> 2500 | G77: =G$5*Assumptions!$D$69 -> 25000 | H77: =H$5*Assumptions!$D$69 -> 250000 | I77: =I$5*Assumptions!$E$69 -> 4000 | J77: =J$5*Assumptions!$E$69 -> 40000 | K77: =K$5*Assumptions!$E$69 -> 400000
A78: Share of identified Tier-2 contracted pipeline (≈3,900 MW, S28) | B78: % | C78: =C77/3900 -> 0.25641026 | D78: =D77/3900 -> 2.5641026 | E78: =E77/3900 -> 25.641026 | F78: =F77/3900 -> 0.64102564 | G78: =G77/3900 -> 6.4102564 | H78: =H77/3900 -> 64.102564 | I78: =I77/3900 -> 1.025641 | J78: =J77/3900 -> 10.25641 | K78: =K77/3900 -> 102.5641 | L78: >100% = more MW than the identified 2026–28 Tier-2 pipeline.

Sheet Sensitivity
A1: Sensitivity — F2, Base scenario (Assumptions column D), computed with formulas (no Data Tables)
A2: Section 1: one-way tornado on five drivers. Section 2: two-way grid, SaaS price × win rate. Section 3: calculation grid behind both (each column recomputes the full F2 chain with one driver moved).
A4: Low / high shock applied to each driver (input) | B4: -0.3 | C4: 0.3 | D4: ← −30% / +30% of the base value
A6: Section 1 — one-way sensitivities (tornado tables)
A7: Output: Payback months | B7: Base value | C7: Driver low value | D7: Driver high value | E7: Output @ low | F7: Output @ high | G7: Swing (abs)
A8: Base case | B8: =$B$93 -> 1.3894047
A9: SaaS price (₹/site/yr) | B9: =$B$61 -> 300000 | C9: =C$61 -> 210000 | D9: =D$61 -> 390000 | E9: =C$93 -> 1.8421434 | F9: =D$93 -> 1.1153003 | G9: =ABS(F9-E9) -> 0.72684307
A10: Win rate | B10: =$B$74 -> 0.1 | C10: =E$74 -> 0.07 | D10: =F$74 -> 0.13 | E10: =E$93 -> 1.8013576 | F10: =F$93 -> 1.1675839 | G10: =ABS(F10-E10) -> 0.63377365
A11: Recoverable % of bill | B11: =$B$64 -> 0.015 | C11: =G$64 -> 0.0105 | D11: =H$64 -> 0.0195 | E11: =G$93 -> 1.4803608 | F11: =H$93 -> 1.3089786 | G11: =ABS(F11-E11) -> 0.17138213
A12: Annual churn | B12: =$B$78 -> 0.15 | C12: =I$78 -> 0.105 | D12: =J$78 -> 0.195 | E12: =I$93 -> 1.3894047 | F12: =J$93 -> 1.3894047 | G12: =ABS(F12-E12) -> 0
A13: CAC driver: outbound hours per prospect | B13: =$B$72 -> 6 | C13: =K$72 -> 4.2 | D13: =L$72 -> 7.8 | E13: =K$93 -> 1.2321136 | F13: =L$93 -> 1.5466958 | G13: =ABS(F13-E13) -> 0.3145822
A15: Output: LTV / cost to acquire | B15: Base value | C15: Driver low value | D15: Driver high value | E15: Output @ low | F15: Output @ high | G15: Swing (abs)
A16: Base case | B16: =$B$94 -> 68.191824
A17: SaaS price (₹/site/yr) | B17: =$B$61 -> 300000 | C17: =C$61 -> 210000 | D17: =D$61 -> 390000 | E17: =C$94 -> 54.040881 | F17: =D$94 -> 82.342767 | G17: =ABS(F17-E17) -> 28.301887
A18: Win rate | B18: =$B$74 -> 0.1 | C18: =E$74 -> 0.07 | D18: =F$74 -> 0.13 | E18: =E$94 -> 52.59702 | F18: =F$94 -> 81.147093 | G18: =ABS(F18-E18) -> 28.550073
A19: Recoverable % of bill | B19: =$B$64 -> 0.015 | C19: =G$64 -> 0.0105 | D19: =H$64 -> 0.0195 | E19: =G$94 -> 61.470126 | F19: =H$94 -> 74.913522 | G19: =ABS(F19-E19) -> 13.443396
A20: Annual churn | B20: =$B$78 -> 0.15 | C20: =I$78 -> 0.105 | D20: =J$78 -> 0.195 | E20: =I$94 -> 92.868374 | F20: =J$94 -> 54.904451 | G20: =ABS(F20-E20) -> 37.963923
A21: CAC driver: outbound hours per prospect | B21: =$B$72 -> 6 | C21: =K$72 -> 4.2 | D21: =L$72 -> 7.8 | E21: =K$94 -> 76.897163 | F21: =L$94 -> 61.257062 | G21: =ABS(F21-E21) -> 15.640101
A23: Output: EBITDA at 100 customers (₹/yr) | B23: Base value | C23: Driver low value | D23: Driver high value | E23: Output @ low | F23: Output @ high | G23: Swing (abs)
A24: Base case | B24: =$B$95 -> 61038900
A25: SaaS price (₹/site/yr) | B25: =$B$61 -> 300000 | C25: =C$61 -> 210000 | D25: =D$61 -> 390000 | E25: =C$95 -> 47538900 | F25: =D$95 -> 74538900 | G25: =ABS(F25-E25) -> 27000000
A26: Win rate | B26: =$B$74 -> 0.1 | C26: =E$74 -> 0.07 | D26: =F$74 -> 0.13 | E26: =E$95 -> 60756043 | F26: =F$95 -> 61191208 | G26: =ABS(F26-E26) -> 435164.84
A27: Recoverable % of bill | B27: =$B$64 -> 0.015 | C27: =G$64 -> 0.0105 | D27: =H$64 -> 0.0195 | E27: =G$95 -> 54626400 | F27: =H$95 -> 67451400 | G27: =ABS(F27-E27) -> 12825000
A28: Annual churn | B28: =$B$78 -> 0.15 | C28: =I$78 -> 0.105 | D28: =J$78 -> 0.195 | E28: =I$95 -> 58287600 | F28: =J$95 -> 63790200 | G28: =ABS(F28-E28) -> 5502600
A29: CAC driver: outbound hours per prospect | B29: =$B$72 -> 6 | C29: =K$72 -> 4.2 | D29: =L$72 -> 7.8 | E29: =K$95 -> 61146900 | F29: =L$95 -> 60930900 | G29: =ABS(F29-E29) -> 216000
A31: Section 2 — two-way: SaaS price (rows) × win rate (columns)
A32: Output: Payback months (multipliers on base, blue = editable) | B32: price ↓ / win → | C32: 0.5 | D32: 0.7 | E32: 0.85 | F32: 1 | G32: 1.15 | H32: 1.3 | I32: 1.5
B33: win rate → | C33: =$B$74*C32 -> 0.05 | D33: =$B$74*D32 -> 0.07 | E33: =$B$74*E32 -> 0.085 | F33: =$B$74*F32 -> 0.1 | G33: =$B$74*G32 -> 0.115 | H33: =$B$74*H32 -> 0.13 | I33: =$B$74*I32 -> 0.15
A34: 0.5 | B34: =$B$61*A34 -> 150000 | C34: =IF((($B34*$B$62+$B$63*$B$62*$B$64*$B$65*$B$67)-($B$68+$B$69*12+$B$70*12*$B$71))<=0,999,((($B$72*$B$71+$B$73)/C$33+$B$75/$B$76)+$B$77*$B$71)/((($B34*$B$62+$B$63*$B$62*$B$64*$B$65*$B$67)-($B$68+$B$69*12+$B$70*12*$B$71))/12)) -> 3.9814986 | D34: =IF((($B34*$B$62+$B$63*$B$62*$B$64*$B$65*$B$67)-($B$68+$B$69*12+$B$70*12*$B$71))<=0,999,((($B$72*$B$71+$B$73)/D$33+$B$75/$B$76)+$B$77*$B$71)/((($B34*$B$62+$B$63*$B$62*$B$64*$B$65*$B$67)-($B$68+$B$69*12+$B$70*12*$B$71))/12)) -> 3.0511431 | E34: =IF((($B34*$B$62+$B$63*$B$62*$B$64*$B$65*$B$67)-($B$68+$B$69*12+$B$70*12*$B$71))<=0,999,((($B$72*$B$71+$B$73)/E$33+$B$75/$B$76)+$B$77*$B$71)/((($B34*$B$62+$B$63*$B$62*$B$64*$B$65*$B$67)-($B$68+$B$69*12+$B$70*12*$B$71))/12)) -> 2.6406922 | F34: =IF((($B34*$B$62+$B$63*$B$62*$B$64*$B$65*$B$67)-($B$68+$B$69*12+$B$70*12*$B$71))<=0,999,((($B$72*$B$71+$B$73)/F$33+$B$75/$B$76)+$B$77*$B$71)/((($B34*$B$62+$B$63*$B$62*$B$64*$B$65*$B$67)-($B$68+$B$69*12+$B$70*12*$B$71))/12)) -> 2.3533765 | G34: =IF((($B34*$B$62+$B$63*$B$62*$B$64*$B$65*$B$67)-($B$68+$B$69*12+$B$70*12*$B$71))<=0,999,((($B$72*$B$71+$B$73)/G$33+$B$75/$B$76)+$B$77*$B$71)/((($B34*$B$62+$B$63*$B$62*$B$64*$B$65*$B$67)-($B$68+$B$69*12+$B$70*12*$B$71))/12)) -> 2.1410127 | H34: =IF((($B34*$B$62+$B$63*$B$62*$B$64*$B$65*$B$67)-($B$68+$B$69*12+$B$70*12*$B$71))<=0,999,((($B$72*$B$71+$B$73)/H$33+$B$75/$B$76)+$B$77*$B$71)/((($B34*$B$62+$B$63*$B$62*$B$64*$B$65*$B$67)-($B$68+$B$69*12+$B$70*12*$B$71))/12)) -> 1.977656 | I34: =IF((($B34*$B$62+$B$63*$B$62*$B$64*$B$65*$B$67)-($B$68+$B$69*12+$B$70*12*$B$71))<=0,999,((($B$72*$B$71+$B$73)/I$33+$B$75/$B$76)+$B$77*$B$71)/((($B34*$B$62+$B$63*$B$62*$B$64*$B$65*$B$67)-($B$68+$B$69*12+$B$70*12*$B$71))/12)) -> 1.8106691
A35: 0.7 | B35: =$B$61*A35 -> 210000 | C35: =IF((($B35*$B$62+$B$63*$B$62*$B$64*$B$65*$B$67)-($B$68+$B$69*12+$B$70*12*$B$71))<=0,999,((($B$72*$B$71+$B$73)/C$33+$B$75/$B$76)+$B$77*$B$71)/((($B35*$B$62+$B$63*$B$62*$B$64*$B$65*$B$67)-($B$68+$B$69*12+$B$70*12*$B$71))/12)) -> 3.1165822 | D35: =IF((($B35*$B$62+$B$63*$B$62*$B$64*$B$65*$B$67)-($B$68+$B$69*12+$B$70*12*$B$71))<=0,999,((($B$72*$B$71+$B$73)/D$33+$B$75/$B$76)+$B$77*$B$71)/((($B35*$B$62+$B$63*$B$62*$B$64*$B$65*$B$67)-($B$68+$B$69*12+$B$70*12*$B$71))/12)) -> 2.3883314 | E35: =IF((($B35*$B$62+$B$63*$B$62*$B$64*$B$65*$B$67)-($B$68+$B$69*12+$B$70*12*$B$71))<=0,999,((($B$72*$B$71+$B$73)/E$33+$B$75/$B$76)+$B$77*$B$71)/((($B35*$B$62+$B$63*$B$62*$B$64*$B$65*$B$67)-($B$68+$B$69*12+$B$70*12*$B$71))/12)) -> 2.0670443 | F35: =IF((($B35*$B$62+$B$63*$B$62*$B$64*$B$65*$B$67)-($B$68+$B$69*12+$B$70*12*$B$71))<=0,999,((($B$72*$B$71+$B$73)/F$33+$B$75/$B$76)+$B$77*$B$71)/((($B35*$B$62+$B$63*$B$62*$B$64*$B$65*$B$67)-($B$68+$B$69*12+$B$70*12*$B$71))/12)) -> 1.8421434 | G35: =IF((($B35*$B$62+$B$63*$B$62*$B$64*$B$65*$B$67)-($B$68+$B$69*12+$B$70*12*$B$71))<=0,999,((($B$72*$B$71+$B$73)/G$33+$B$75/$B$76)+$B$77*$B$71)/((($B35*$B$62+$B$63*$B$62*$B$64*$B$65*$B$67)-($B$68+$B$69*12+$B$70*12*$B$71))/12)) -> 1.6759122 | H35: =IF((($B35*$B$62+$B$63*$B$62*$B$64*$B$65*$B$67)-($B$68+$B$69*12+$B$70*12*$B$71))<=0,999,((($B$72*$B$71+$B$73)/H$33+$B$75/$B$76)+$B$77*$B$71)/((($B35*$B$62+$B$63*$B$62*$B$64*$B$65*$B$67)-($B$68+$B$69*12+$B$70*12*$B$71))/12)) -> 1.5480421 | I35: =IF((($B35*$B$62+$B$63*$B$62*$B$64*$B$65*$B$67)-($B$68+$B$69*12+$B$70*12*$B$71))<=0,999,((($B$72*$B$71+$B$73)/I$33+$B$75/$B$76)+$B$77*$B$71)/((($B35*$B$62+$B$63*$B$62*$B$64*$B$65*$B$67)-($B$68+$B$69*12+$B$70*12*$B$71))/12)) -> 1.4173304
A36: 0.85 | B36: =$B$61*A36 -> 255000 | C36: =IF((($B36*$B$62+$B$63*$B$62*$B$64*$B$65*$B$67)-($B$68+$B$69*12+$B$70*12*$B$71))<=0,999,((($B$72*$B$71+$B$73)/C$33+$B$75/$B$76)+$B$77*$B$71)/((($B36*$B$62+$B$63*$B$62*$B$64*$B$65*$B$67)-($B$68+$B$69*12+$B$70*12*$B$71))/12)) -> 2.6799502 | D36: =IF((($B36*$B$62+$B$63*$B$62*$B$64*$B$65*$B$67)-($B$68+$B$69*12+$B$70*12*$B$71))<=0,999,((($B$72*$B$71+$B$73)/D$33+$B$75/$B$76)+$B$77*$B$71)/((($B36*$B$62+$B$63*$B$62*$B$64*$B$65*$B$67)-($B$68+$B$69*12+$B$70*12*$B$71))/12)) -> 2.0537271 | E36: =IF((($B36*$B$62+$B$63*$B$62*$B$64*$B$65*$B$67)-($B$68+$B$69*12+$B$70*12*$B$71))<=0,999,((($B$72*$B$71+$B$73)/E$33+$B$75/$B$76)+$B$77*$B$71)/((($B36*$B$62+$B$63*$B$62*$B$64*$B$65*$B$67)-($B$68+$B$69*12+$B$70*12*$B$71))/12)) -> 1.7774522 | F36: =IF((($B36*$B$62+$B$63*$B$62*$B$64*$B$65*$B$67)-($B$68+$B$69*12+$B$70*12*$B$71))<=0,999,((($B$72*$B$71+$B$73)/F$33+$B$75/$B$76)+$B$77*$B$71)/((($B36*$B$62+$B$63*$B$62*$B$64*$B$65*$B$67)-($B$68+$B$69*12+$B$70*12*$B$71))/12)) -> 1.5840598 | G36: =IF((($B36*$B$62+$B$63*$B$62*$B$64*$B$65*$B$67)-($B$68+$B$69*12+$B$70*12*$B$71))<=0,999,((($B$72*$B$71+$B$73)/G$33+$B$75/$B$76)+$B$77*$B$71)/((($B36*$B$62+$B$63*$B$62*$B$64*$B$65*$B$67)-($B$68+$B$69*12+$B$70*12*$B$71))/12)) -> 1.4411175 | H36: =IF((($B36*$B$62+$B$63*$B$62*$B$64*$B$65*$B$67)-($B$68+$B$69*12+$B$70*12*$B$71))<=0,999,((($B$72*$B$71+$B$73)/H$33+$B$75/$B$76)+$B$77*$B$71)/((($B36*$B$62+$B$63*$B$62*$B$64*$B$65*$B$67)-($B$68+$B$69*12+$B$70*12*$B$71))/12)) -> 1.331162 | I36: =IF((($B36*$B$62+$B$63*$B$62*$B$64*$B$65*$B$67)-($B$68+$B$69*12+$B$70*12*$B$71))<=0,999,((($B$72*$B$71+$B$73)/I$33+$B$75/$B$76)+$B$77*$B$71)/((($B36*$B$62+$B$63*$B$62*$B$64*$B$65*$B$67)-($B$68+$B$69*12+$B$70*12*$B$71))/12)) -> 1.218763
A37: 1 | B37: =$B$61*A37 -> 300000 | C37: =IF((($B37*$B$62+$B$63*$B$62*$B$64*$B$65*$B$67)-($B$68+$B$69*12+$B$70*12*$B$71))<=0,999,((($B$72*$B$71+$B$73)/C$33+$B$75/$B$76)+$B$77*$B$71)/((($B37*$B$62+$B$63*$B$62*$B$64*$B$65*$B$67)-($B$68+$B$69*12+$B$70*12*$B$71))/12)) -> 2.3506281 | D37: =IF((($B37*$B$62+$B$63*$B$62*$B$64*$B$65*$B$67)-($B$68+$B$69*12+$B$70*12*$B$71))<=0,999,((($B$72*$B$71+$B$73)/D$33+$B$75/$B$76)+$B$77*$B$71)/((($B37*$B$62+$B$63*$B$62*$B$64*$B$65*$B$67)-($B$68+$B$69*12+$B$70*12*$B$71))/12)) -> 1.8013576 | E37: =IF((($B37*$B$62+$B$63*$B$62*$B$64*$B$65*$B$67)-($B$68+$B$69*12+$B$70*12*$B$71))<=0,999,((($B$72*$B$71+$B$73)/E$33+$B$75/$B$76)+$B$77*$B$71)/((($B37*$B$62+$B$63*$B$62*$B$64*$B$65*$B$67)-($B$68+$B$69*12+$B$70*12*$B$71))/12)) -> 1.5590324 | F37: =IF((($B37*$B$62+$B$63*$B$62*$B$64*$B$65*$B$67)-($B$68+$B$69*12+$B$70*12*$B$71))<=0,999,((($B$72*$B$71+$B$73)/F$33+$B$75/$B$76)+$B$77*$B$71)/((($B37*$B$62+$B$63*$B$62*$B$64*$B$65*$B$67)-($B$68+$B$69*12+$B$70*12*$B$71))/12)) -> 1.3894047 | G37: =IF((($B37*$B$62+$B$63*$B$62*$B$64*$B$65*$B$67)-($B$68+$B$69*12+$B$70*12*$B$71))<=0,999,((($B$72*$B$71+$B$73)/G$33+$B$75/$B$76)+$B$77*$B$71)/((($B37*$B$62+$B$63*$B$62*$B$64*$B$65*$B$67)-($B$68+$B$69*12+$B$70*12*$B$71))/12)) -> 1.2640277 | H37: =IF((($B37*$B$62+$B$63*$B$62*$B$64*$B$65*$B$67)-($B$68+$B$69*12+$B$70*12*$B$71))<=0,999,((($B$72*$B$71+$B$73)/H$33+$B$75/$B$76)+$B$77*$B$71)/((($B37*$B$62+$B$63*$B$62*$B$64*$B$65*$B$67)-($B$68+$B$69*12+$B$70*12*$B$71))/12)) -> 1.1675839 | I37: =IF((($B37*$B$62+$B$63*$B$62*$B$64*$B$65*$B$67)-($B$68+$B$69*12+$B$70*12*$B$71))<=0,999,((($B$72*$B$71+$B$73)/I$33+$B$75/$B$76)+$B$77*$B$71)/((($B37*$B$62+$B$63*$B$62*$B$64*$B$65*$B$67)-($B$68+$B$69*12+$B$70*12*$B$71))/12)) -> 1.0689969
A38: 1.15 | B38: =$B$61*A38 -> 345000 | C38: =IF((($B38*$B$62+$B$63*$B$62*$B$64*$B$65*$B$67)-($B$68+$B$69*12+$B$70*12*$B$71))<=0,999,((($B$72*$B$71+$B$73)/C$33+$B$75/$B$76)+$B$77*$B$71)/((($B38*$B$62+$B$63*$B$62*$B$64*$B$65*$B$67)-($B$68+$B$69*12+$B$70*12*$B$71))/12)) -> 2.0933852 | D38: =IF((($B38*$B$62+$B$63*$B$62*$B$64*$B$65*$B$67)-($B$68+$B$69*12+$B$70*12*$B$71))<=0,999,((($B$72*$B$71+$B$73)/D$33+$B$75/$B$76)+$B$77*$B$71)/((($B38*$B$62+$B$63*$B$62*$B$64*$B$65*$B$67)-($B$68+$B$69*12+$B$70*12*$B$71))/12)) -> 1.6042246 | E38: =IF((($B38*$B$62+$B$63*$B$62*$B$64*$B$65*$B$67)-($B$68+$B$69*12+$B$70*12*$B$71))<=0,999,((($B$72*$B$71+$B$73)/E$33+$B$75/$B$76)+$B$77*$B$71)/((($B38*$B$62+$B$63*$B$62*$B$64*$B$65*$B$67)-($B$68+$B$69*12+$B$70*12*$B$71))/12)) -> 1.3884184 | F38: =IF((($B38*$B$62+$B$63*$B$62*$B$64*$B$65*$B$67)-($B$68+$B$69*12+$B$70*12*$B$71))<=0,999,((($B$72*$B$71+$B$73)/F$33+$B$75/$B$76)+$B$77*$B$71)/((($B38*$B$62+$B$63*$B$62*$B$64*$B$65*$B$67)-($B$68+$B$69*12+$B$70*12*$B$71))/12)) -> 1.2373541 | G38: =IF((($B38*$B$62+$B$63*$B$62*$B$64*$B$65*$B$67)-($B$68+$B$69*12+$B$70*12*$B$71))<=0,999,((($B$72*$B$71+$B$73)/G$33+$B$75/$B$76)+$B$77*$B$71)/((($B38*$B$62+$B$63*$B$62*$B$64*$B$65*$B$67)-($B$68+$B$69*12+$B$70*12*$B$71))/12)) -> 1.1256979 | H38: =IF((($B38*$B$62+$B$63*$B$62*$B$64*$B$65*$B$67)-($B$68+$B$69*12+$B$70*12*$B$71))<=0,999,((($B$72*$B$71+$B$73)/H$33+$B$75/$B$76)+$B$77*$B$71)/((($B38*$B$62+$B$63*$B$62*$B$64*$B$65*$B$67)-($B$68+$B$69*12+$B$70*12*$B$71))/12)) -> 1.0398084 | I38: =IF((($B38*$B$62+$B$63*$B$62*$B$64*$B$65*$B$67)-($B$68+$B$69*12+$B$70*12*$B$71))<=0,999,((($B$72*$B$71+$B$73)/I$33+$B$75/$B$76)+$B$77*$B$71)/((($B38*$B$62+$B$63*$B$62*$B$64*$B$65*$B$67)-($B$68+$B$69*12+$B$70*12*$B$71))/12)) -> 0.95201038
A39: 1.3 | B39: =$B$61*A39 -> 390000 | C39: =IF((($B39*$B$62+$B$63*$B$62*$B$64*$B$65*$B$67)-($B$68+$B$69*12+$B$70*12*$B$71))<=0,999,((($B$72*$B$71+$B$73)/C$33+$B$75/$B$76)+$B$77*$B$71)/((($B39*$B$62+$B$63*$B$62*$B$64*$B$65*$B$67)-($B$68+$B$69*12+$B$70*12*$B$71))/12)) -> 1.8868917 | D39: =IF((($B39*$B$62+$B$63*$B$62*$B$64*$B$65*$B$67)-($B$68+$B$69*12+$B$70*12*$B$71))<=0,999,((($B$72*$B$71+$B$73)/D$33+$B$75/$B$76)+$B$77*$B$71)/((($B39*$B$62+$B$63*$B$62*$B$64*$B$65*$B$67)-($B$68+$B$69*12+$B$70*12*$B$71))/12)) -> 1.4459823 | E39: =IF((($B39*$B$62+$B$63*$B$62*$B$64*$B$65*$B$67)-($B$68+$B$69*12+$B$70*12*$B$71))<=0,999,((($B$72*$B$71+$B$73)/E$33+$B$75/$B$76)+$B$77*$B$71)/((($B39*$B$62+$B$63*$B$62*$B$64*$B$65*$B$67)-($B$68+$B$69*12+$B$70*12*$B$71))/12)) -> 1.2514635 | F39: =IF((($B39*$B$62+$B$63*$B$62*$B$64*$B$65*$B$67)-($B$68+$B$69*12+$B$70*12*$B$71))<=0,999,((($B$72*$B$71+$B$73)/F$33+$B$75/$B$76)+$B$77*$B$71)/((($B39*$B$62+$B$63*$B$62*$B$64*$B$65*$B$67)-($B$68+$B$69*12+$B$70*12*$B$71))/12)) -> 1.1153003 | G39: =IF((($B39*$B$62+$B$63*$B$62*$B$64*$B$65*$B$67)-($B$68+$B$69*12+$B$70*12*$B$71))<=0,999,((($B$72*$B$71+$B$73)/G$33+$B$75/$B$76)+$B$77*$B$71)/((($B39*$B$62+$B$63*$B$62*$B$64*$B$65*$B$67)-($B$68+$B$69*12+$B$70*12*$B$71))/12)) -> 1.0146579 | H39: =IF((($B39*$B$62+$B$63*$B$62*$B$64*$B$65*$B$67)-($B$68+$B$69*12+$B$70*12*$B$71))<=0,999,((($B$72*$B$71+$B$73)/H$33+$B$75/$B$76)+$B$77*$B$71)/((($B39*$B$62+$B$63*$B$62*$B$64*$B$65*$B$67)-($B$68+$B$69*12+$B$70*12*$B$71))/12)) -> 0.93724075 | I39: =IF((($B39*$B$62+$B$63*$B$62*$B$64*$B$65*$B$67)-($B$68+$B$69*12+$B$70*12*$B$71))<=0,999,((($B$72*$B$71+$B$73)/I$33+$B$75/$B$76)+$B$77*$B$71)/((($B39*$B$62+$B$63*$B$62*$B$64*$B$65*$B$67)-($B$68+$B$69*12+$B$70*12*$B$71))/12)) -> 0.85810317
A40: 1.5 | B40: =$B$61*A40 -> 450000 | C40: =IF((($B40*$B$62+$B$63*$B$62*$B$64*$B$65*$B$67)-($B$68+$B$69*12+$B$70*12*$B$71))<=0,999,((($B$72*$B$71+$B$73)/C$33+$B$75/$B$76)+$B$77*$B$71)/((($B40*$B$62+$B$63*$B$62*$B$64*$B$65*$B$67)-($B$68+$B$69*12+$B$70*12*$B$71))/12)) -> 1.6675707 | D40: =IF((($B40*$B$62+$B$63*$B$62*$B$64*$B$65*$B$67)-($B$68+$B$69*12+$B$70*12*$B$71))<=0,999,((($B$72*$B$71+$B$73)/D$33+$B$75/$B$76)+$B$77*$B$71)/((($B40*$B$62+$B$63*$B$62*$B$64*$B$65*$B$67)-($B$68+$B$69*12+$B$70*12*$B$71))/12)) -> 1.27791 | E40: =IF((($B40*$B$62+$B$63*$B$62*$B$64*$B$65*$B$67)-($B$68+$B$69*12+$B$70*12*$B$71))<=0,999,((($B$72*$B$71+$B$73)/E$33+$B$75/$B$76)+$B$77*$B$71)/((($B40*$B$62+$B$63*$B$62*$B$64*$B$65*$B$67)-($B$68+$B$69*12+$B$70*12*$B$71))/12)) -> 1.1060009 | F40: =IF((($B40*$B$62+$B$63*$B$62*$B$64*$B$65*$B$67)-($B$68+$B$69*12+$B$70*12*$B$71))<=0,999,((($B$72*$B$71+$B$73)/F$33+$B$75/$B$76)+$B$77*$B$71)/((($B40*$B$62+$B$63*$B$62*$B$64*$B$65*$B$67)-($B$68+$B$69*12+$B$70*12*$B$71))/12)) -> 0.98566447 | G40: =IF((($B40*$B$62+$B$63*$B$62*$B$64*$B$65*$B$67)-($B$68+$B$69*12+$B$70*12*$B$71))<=0,999,((($B$72*$B$71+$B$73)/G$33+$B$75/$B$76)+$B$77*$B$71)/((($B40*$B$62+$B$63*$B$62*$B$64*$B$65*$B$67)-($B$68+$B$69*12+$B$70*12*$B$71))/12)) -> 0.89672018 | H40: =IF((($B40*$B$62+$B$63*$B$62*$B$64*$B$65*$B$67)-($B$68+$B$69*12+$B$70*12*$B$71))<=0,999,((($B$72*$B$71+$B$73)/H$33+$B$75/$B$76)+$B$77*$B$71)/((($B40*$B$62+$B$63*$B$62*$B$64*$B$65*$B$67)-($B$68+$B$69*12+$B$70*12*$B$71))/12)) -> 0.82830149 | I40: =IF((($B40*$B$62+$B$63*$B$62*$B$64*$B$65*$B$67)-($B$68+$B$69*12+$B$70*12*$B$71))<=0,999,((($B$72*$B$71+$B$73)/I$33+$B$75/$B$76)+$B$77*$B$71)/((($B40*$B$62+$B$63*$B$62*$B$64*$B$65*$B$67)-($B$68+$B$69*12+$B$70*12*$B$71))/12)) -> 0.75836239
A42: Output: LTV / cost to acquire (multipliers on base, blue = editable) | B42: price ↓ / win → | C42: 0.5 | D42: 0.7 | E42: 0.85 | F42: 1 | G42: 1.15 | H42: 1.3 | I42: 1.5
B43: win rate → | C43: =$B$74*C42 -> 0.05 | D43: =$B$74*D42 -> 0.07 | E43: =$B$74*E42 -> 0.085 | F43: =$B$74*F42 -> 0.1 | G43: =$B$74*G42 -> 0.115 | H43: =$B$74*H42 -> 0.13 | I43: =$B$74*I42 -> 0.15
A44: 0.5 | B44: =$B$61*A44 -> 150000 | C44: =IF(((($B$72*$B$71+$B$73)/C$43+$B$75/$B$76)+$B$77*$B$71)=0,0,($B$88+(($B44*$B$62+$B$63*$B$62*$B$64*$B$65*$B$67)-($B$68+$B$69*12+$B$70*12*$B$71))/$B$78)/((($B$72*$B$71+$B$73)/C$43+$B$75/$B$76)+$B$77*$B$71)) -> 26.366171 | D44: =IF(((($B$72*$B$71+$B$73)/D$43+$B$75/$B$76)+$B$77*$B$71)=0,0,($B$88+(($B44*$B$62+$B$63*$B$62*$B$64*$B$65*$B$67)-($B$68+$B$69*12+$B$70*12*$B$71))/$B$78)/((($B$72*$B$71+$B$73)/D$43+$B$75/$B$76)+$B$77*$B$71)) -> 34.405752 | E44: =IF(((($B$72*$B$71+$B$73)/E$43+$B$75/$B$76)+$B$77*$B$71)=0,0,($B$88+(($B44*$B$62+$B$63*$B$62*$B$64*$B$65*$B$67)-($B$68+$B$69*12+$B$70*12*$B$71))/$B$78)/((($B$72*$B$71+$B$73)/E$43+$B$75/$B$76)+$B$77*$B$71)) -> 39.753544 | F44: =IF(((($B$72*$B$71+$B$73)/F$43+$B$75/$B$76)+$B$77*$B$71)=0,0,($B$88+(($B44*$B$62+$B$63*$B$62*$B$64*$B$65*$B$67)-($B$68+$B$69*12+$B$70*12*$B$71))/$B$78)/((($B$72*$B$71+$B$73)/F$43+$B$75/$B$76)+$B$77*$B$71)) -> 44.606918 | G44: =IF(((($B$72*$B$71+$B$73)/G$43+$B$75/$B$76)+$B$77*$B$71)=0,0,($B$88+(($B44*$B$62+$B$63*$B$62*$B$64*$B$65*$B$67)-($B$68+$B$69*12+$B$70*12*$B$71))/$B$78)/((($B$72*$B$71+$B$73)/G$43+$B$75/$B$76)+$B$77*$B$71)) -> 49.03141 | H44: =IF(((($B$72*$B$71+$B$73)/H$43+$B$75/$B$76)+$B$77*$B$71)=0,0,($B$88+(($B44*$B$62+$B$63*$B$62*$B$64*$B$65*$B$67)-($B$68+$B$69*12+$B$70*12*$B$71))/$B$78)/((($B$72*$B$71+$B$73)/H$43+$B$75/$B$76)+$B$77*$B$71)) -> 53.081462 | I44: =IF(((($B$72*$B$71+$B$73)/I$43+$B$75/$B$76)+$B$77*$B$71)=0,0,($B$88+(($B44*$B$62+$B$63*$B$62*$B$64*$B$65*$B$67)-($B$68+$B$69*12+$B$70*12*$B$71))/$B$78)/((($B$72*$B$71+$B$73)/I$43+$B$75/$B$76)+$B$77*$B$71)) -> 57.976839
A45: 0.7 | B45: =$B$61*A45 -> 210000 | C45: =IF(((($B$72*$B$71+$B$73)/C$43+$B$75/$B$76)+$B$77*$B$71)=0,0,($B$88+(($B45*$B$62+$B$63*$B$62*$B$64*$B$65*$B$67)-($B$68+$B$69*12+$B$70*12*$B$71))/$B$78)/((($B$72*$B$71+$B$73)/C$43+$B$75/$B$76)+$B$77*$B$71)) -> 31.942379 | D45: =IF(((($B$72*$B$71+$B$73)/D$43+$B$75/$B$76)+$B$77*$B$71)=0,0,($B$88+(($B45*$B$62+$B$63*$B$62*$B$64*$B$65*$B$67)-($B$68+$B$69*12+$B$70*12*$B$71))/$B$78)/((($B$72*$B$71+$B$73)/D$43+$B$75/$B$76)+$B$77*$B$71)) -> 41.682259 | E45: =IF(((($B$72*$B$71+$B$73)/E$43+$B$75/$B$76)+$B$77*$B$71)=0,0,($B$88+(($B45*$B$62+$B$63*$B$62*$B$64*$B$65*$B$67)-($B$68+$B$69*12+$B$70*12*$B$71))/$B$78)/((($B$72*$B$71+$B$73)/E$43+$B$75/$B$76)+$B$77*$B$71)) -> 48.161062 | F45: =IF(((($B$72*$B$71+$B$73)/F$43+$B$75/$B$76)+$B$77*$B$71)=0,0,($B$88+(($B45*$B$62+$B$63*$B$62*$B$64*$B$65*$B$67)-($B$68+$B$69*12+$B$70*12*$B$71))/$B$78)/((($B$72*$B$71+$B$73)/F$43+$B$75/$B$76)+$B$77*$B$71)) -> 54.040881 | G45: =IF(((($B$72*$B$71+$B$73)/G$43+$B$75/$B$76)+$B$77*$B$71)=0,0,($B$88+(($B45*$B$62+$B$63*$B$62*$B$64*$B$65*$B$67)-($B$68+$B$69*12+$B$70*12*$B$71))/$B$78)/((($B$72*$B$71+$B$73)/G$43+$B$75/$B$76)+$B$77*$B$71)) -> 59.401112 | H45: =IF(((($B$72*$B$71+$B$73)/H$43+$B$75/$B$76)+$B$77*$B$71)=0,0,($B$88+(($B45*$B$62+$B$63*$B$62*$B$64*$B$65*$B$67)-($B$68+$B$69*12+$B$70*12*$B$71))/$B$78)/((($B$72*$B$71+$B$73)/H$43+$B$75/$B$76)+$B$77*$B$71)) -> 64.307714 | I45: =IF(((($B$72*$B$71+$B$73)/I$43+$B$75/$B$76)+$B$77*$B$71)=0,0,($B$88+(($B45*$B$62+$B$63*$B$62*$B$64*$B$65*$B$67)-($B$68+$B$69*12+$B$70*12*$B$71))/$B$78)/((($B$72*$B$71+$B$73)/I$43+$B$75/$B$76)+$B$77*$B$71)) -> 70.23842
A46: 0.85 | B46: =$B$61*A46 -> 255000 | C46: =IF(((($B$72*$B$71+$B$73)/C$43+$B$75/$B$76)+$B$77*$B$71)=0,0,($B$88+(($B46*$B$62+$B$63*$B$62*$B$64*$B$65*$B$67)-($B$68+$B$69*12+$B$70*12*$B$71))/$B$78)/((($B$72*$B$71+$B$73)/C$43+$B$75/$B$76)+$B$77*$B$71)) -> 36.124535 | D46: =IF(((($B$72*$B$71+$B$73)/D$43+$B$75/$B$76)+$B$77*$B$71)=0,0,($B$88+(($B46*$B$62+$B$63*$B$62*$B$64*$B$65*$B$67)-($B$68+$B$69*12+$B$70*12*$B$71))/$B$78)/((($B$72*$B$71+$B$73)/D$43+$B$75/$B$76)+$B$77*$B$71)) -> 47.13964 | E46: =IF(((($B$72*$B$71+$B$73)/E$43+$B$75/$B$76)+$B$77*$B$71)=0,0,($B$88+(($B46*$B$62+$B$63*$B$62*$B$64*$B$65*$B$67)-($B$68+$B$69*12+$B$70*12*$B$71))/$B$78)/((($B$72*$B$71+$B$73)/E$43+$B$75/$B$76)+$B$77*$B$71)) -> 54.4667 | F46: =IF(((($B$72*$B$71+$B$73)/F$43+$B$75/$B$76)+$B$77*$B$71)=0,0,($B$88+(($B46*$B$62+$B$63*$B$62*$B$64*$B$65*$B$67)-($B$68+$B$69*12+$B$70*12*$B$71))/$B$78)/((($B$72*$B$71+$B$73)/F$43+$B$75/$B$76)+$B$77*$B$71)) -> 61.116352 | G46: =IF(((($B$72*$B$71+$B$73)/G$43+$B$75/$B$76)+$B$77*$B$71)=0,0,($B$88+(($B46*$B$62+$B$63*$B$62*$B$64*$B$65*$B$67)-($B$68+$B$69*12+$B$70*12*$B$71))/$B$78)/((($B$72*$B$71+$B$73)/G$43+$B$75/$B$76)+$B$77*$B$71)) -> 67.178389 | H46: =IF(((($B$72*$B$71+$B$73)/H$43+$B$75/$B$76)+$B$77*$B$71)=0,0,($B$88+(($B46*$B$62+$B$63*$B$62*$B$64*$B$65*$B$67)-($B$68+$B$69*12+$B$70*12*$B$71))/$B$78)/((($B$72*$B$71+$B$73)/H$43+$B$75/$B$76)+$B$77*$B$71)) -> 72.727404 | I46: =IF(((($B$72*$B$71+$B$73)/I$43+$B$75/$B$76)+$B$77*$B$71)=0,0,($B$88+(($B46*$B$62+$B$63*$B$62*$B$64*$B$65*$B$67)-($B$68+$B$69*12+$B$70*12*$B$71))/$B$78)/((($B$72*$B$71+$B$73)/I$43+$B$75/$B$76)+$B$77*$B$71)) -> 79.434605
A47: 1 | B47: =$B$61*A47 -> 300000 | C47: =IF(((($B$72*$B$71+$B$73)/C$43+$B$75/$B$76)+$B$77*$B$71)=0,0,($B$88+(($B47*$B$62+$B$63*$B$62*$B$64*$B$65*$B$67)-($B$68+$B$69*12+$B$70*12*$B$71))/$B$78)/((($B$72*$B$71+$B$73)/C$43+$B$75/$B$76)+$B$77*$B$71)) -> 40.306691 | D47: =IF(((($B$72*$B$71+$B$73)/D$43+$B$75/$B$76)+$B$77*$B$71)=0,0,($B$88+(($B47*$B$62+$B$63*$B$62*$B$64*$B$65*$B$67)-($B$68+$B$69*12+$B$70*12*$B$71))/$B$78)/((($B$72*$B$71+$B$73)/D$43+$B$75/$B$76)+$B$77*$B$71)) -> 52.59702 | E47: =IF(((($B$72*$B$71+$B$73)/E$43+$B$75/$B$76)+$B$77*$B$71)=0,0,($B$88+(($B47*$B$62+$B$63*$B$62*$B$64*$B$65*$B$67)-($B$68+$B$69*12+$B$70*12*$B$71))/$B$78)/((($B$72*$B$71+$B$73)/E$43+$B$75/$B$76)+$B$77*$B$71)) -> 60.772338 | F47: =IF(((($B$72*$B$71+$B$73)/F$43+$B$75/$B$76)+$B$77*$B$71)=0,0,($B$88+(($B47*$B$62+$B$63*$B$62*$B$64*$B$65*$B$67)-($B$68+$B$69*12+$B$70*12*$B$71))/$B$78)/((($B$72*$B$71+$B$73)/F$43+$B$75/$B$76)+$B$77*$B$71)) -> 68.191824 | G47: =IF(((($B$72*$B$71+$B$73)/G$43+$B$75/$B$76)+$B$77*$B$71)=0,0,($B$88+(($B47*$B$62+$B$63*$B$62*$B$64*$B$65*$B$67)-($B$68+$B$69*12+$B$70*12*$B$71))/$B$78)/((($B$72*$B$71+$B$73)/G$43+$B$75/$B$76)+$B$77*$B$71)) -> 74.955666 | H47: =IF(((($B$72*$B$71+$B$73)/H$43+$B$75/$B$76)+$B$77*$B$71)=0,0,($B$88+(($B47*$B$62+$B$63*$B$62*$B$64*$B$65*$B$67)-($B$68+$B$69*12+$B$70*12*$B$71))/$B$78)/((($B$72*$B$71+$B$73)/H$43+$B$75/$B$76)+$B$77*$B$71)) -> 81.147093 | I47: =IF(((($B$72*$B$71+$B$73)/I$43+$B$75/$B$76)+$B$77*$B$71)=0,0,($B$88+(($B47*$B$62+$B$63*$B$62*$B$64*$B$65*$B$67)-($B$68+$B$69*12+$B$70*12*$B$71))/$B$78)/((($B$72*$B$71+$B$73)/I$43+$B$75/$B$76)+$B$77*$B$71)) -> 88.63079
A48: 1.15 | B48: =$B$61*A48 -> 345000 | C48: =IF(((($B$72*$B$71+$B$73)/C$43+$B$75/$B$76)+$B$77*$B$71)=0,0,($B$88+(($B48*$B$62+$B$63*$B$62*$B$64*$B$65*$B$67)-($B$68+$B$69*12+$B$70*12*$B$71))/$B$78)/((($B$72*$B$71+$B$73)/C$43+$B$75/$B$76)+$B$77*$B$71)) -> 44.488848 | D48: =IF(((($B$72*$B$71+$B$73)/D$43+$B$75/$B$76)+$B$77*$B$71)=0,0,($B$88+(($B48*$B$62+$B$63*$B$62*$B$64*$B$65*$B$67)-($B$68+$B$69*12+$B$70*12*$B$71))/$B$78)/((($B$72*$B$71+$B$73)/D$43+$B$75/$B$76)+$B$77*$B$71)) -> 58.054401 | E48: =IF(((($B$72*$B$71+$B$73)/E$43+$B$75/$B$76)+$B$77*$B$71)=0,0,($B$88+(($B48*$B$62+$B$63*$B$62*$B$64*$B$65*$B$67)-($B$68+$B$69*12+$B$70*12*$B$71))/$B$78)/((($B$72*$B$71+$B$73)/E$43+$B$75/$B$76)+$B$77*$B$71)) -> 67.077976 | F48: =IF(((($B$72*$B$71+$B$73)/F$43+$B$75/$B$76)+$B$77*$B$71)=0,0,($B$88+(($B48*$B$62+$B$63*$B$62*$B$64*$B$65*$B$67)-($B$68+$B$69*12+$B$70*12*$B$71))/$B$78)/((($B$72*$B$71+$B$73)/F$43+$B$75/$B$76)+$B$77*$B$71)) -> 75.267296 | G48: =IF(((($B$72*$B$71+$B$73)/G$43+$B$75/$B$76)+$B$77*$B$71)=0,0,($B$88+(($B48*$B$62+$B$63*$B$62*$B$64*$B$65*$B$67)-($B$68+$B$69*12+$B$70*12*$B$71))/$B$78)/((($B$72*$B$71+$B$73)/G$43+$B$75/$B$76)+$B$77*$B$71)) -> 82.732943 | H48: =IF(((($B$72*$B$71+$B$73)/H$43+$B$75/$B$76)+$B$77*$B$71)=0,0,($B$88+(($B48*$B$62+$B$63*$B$62*$B$64*$B$65*$B$67)-($B$68+$B$69*12+$B$70*12*$B$71))/$B$78)/((($B$72*$B$71+$B$73)/H$43+$B$75/$B$76)+$B$77*$B$71)) -> 89.566782 | I48: =IF(((($B$72*$B$71+$B$73)/I$43+$B$75/$B$76)+$B$77*$B$71)=0,0,($B$88+(($B48*$B$62+$B$63*$B$62*$B$64*$B$65*$B$67)-($B$68+$B$69*12+$B$70*12*$B$71))/$B$78)/((($B$72*$B$71+$B$73)/I$43+$B$75/$B$76)+$B$77*$B$71)) -> 97.826975
A49: 1.3 | B49: =$B$61*A49 -> 390000 | C49: =IF(((($B$72*$B$71+$B$73)/C$43+$B$75/$B$76)+$B$77*$B$71)=0,0,($B$88+(($B49*$B$62+$B$63*$B$62*$B$64*$B$65*$B$67)-($B$68+$B$69*12+$B$70*12*$B$71))/$B$78)/((($B$72*$B$71+$B$73)/C$43+$B$75/$B$76)+$B$77*$B$71)) -> 48.671004 | D49: =IF(((($B$72*$B$71+$B$73)/D$43+$B$75/$B$76)+$B$77*$B$71)=0,0,($B$88+(($B49*$B$62+$B$63*$B$62*$B$64*$B$65*$B$67)-($B$68+$B$69*12+$B$70*12*$B$71))/$B$78)/((($B$72*$B$71+$B$73)/D$43+$B$75/$B$76)+$B$77*$B$71)) -> 63.511781 | E49: =IF(((($B$72*$B$71+$B$73)/E$43+$B$75/$B$76)+$B$77*$B$71)=0,0,($B$88+(($B49*$B$62+$B$63*$B$62*$B$64*$B$65*$B$67)-($B$68+$B$69*12+$B$70*12*$B$71))/$B$78)/((($B$72*$B$71+$B$73)/E$43+$B$75/$B$76)+$B$77*$B$71)) -> 73.383614 | F49: =IF(((($B$72*$B$71+$B$73)/F$43+$B$75/$B$76)+$B$77*$B$71)=0,0,($B$88+(($B49*$B$62+$B$63*$B$62*$B$64*$B$65*$B$67)-($B$68+$B$69*12+$B$70*12*$B$71))/$B$78)/((($B$72*$B$71+$B$73)/F$43+$B$75/$B$76)+$B$77*$B$71)) -> 82.342767 | G49: =IF(((($B$72*$B$71+$B$73)/G$43+$B$75/$B$76)+$B$77*$B$71)=0,0,($B$88+(($B49*$B$62+$B$63*$B$62*$B$64*$B$65*$B$67)-($B$68+$B$69*12+$B$70*12*$B$71))/$B$78)/((($B$72*$B$71+$B$73)/G$43+$B$75/$B$76)+$B$77*$B$71)) -> 90.510219 | H49: =IF(((($B$72*$B$71+$B$73)/H$43+$B$75/$B$76)+$B$77*$B$71)=0,0,($B$88+(($B49*$B$62+$B$63*$B$62*$B$64*$B$65*$B$67)-($B$68+$B$69*12+$B$70*12*$B$71))/$B$78)/((($B$72*$B$71+$B$73)/H$43+$B$75/$B$76)+$B$77*$B$71)) -> 97.986471 | I49: =IF(((($B$72*$B$71+$B$73)/I$43+$B$75/$B$76)+$B$77*$B$71)=0,0,($B$88+(($B49*$B$62+$B$63*$B$62*$B$64*$B$65*$B$67)-($B$68+$B$69*12+$B$70*12*$B$71))/$B$78)/((($B$72*$B$71+$B$73)/I$43+$B$75/$B$76)+$B$77*$B$71)) -> 107.02316
A50: 1.5 | B50: =$B$61*A50 -> 450000 | C50: =IF(((($B$72*$B$71+$B$73)/C$43+$B$75/$B$76)+$B$77*$B$71)=0,0,($B$88+(($B50*$B$62+$B$63*$B$62*$B$64*$B$65*$B$67)-($B$68+$B$69*12+$B$70*12*$B$71))/$B$78)/((($B$72*$B$71+$B$73)/C$43+$B$75/$B$76)+$B$77*$B$71)) -> 54.247212 | D50: =IF(((($B$72*$B$71+$B$73)/D$43+$B$75/$B$76)+$B$77*$B$71)=0,0,($B$88+(($B50*$B$62+$B$63*$B$62*$B$64*$B$65*$B$67)-($B$68+$B$69*12+$B$70*12*$B$71))/$B$78)/((($B$72*$B$71+$B$73)/D$43+$B$75/$B$76)+$B$77*$B$71)) -> 70.788288 | E50: =IF(((($B$72*$B$71+$B$73)/E$43+$B$75/$B$76)+$B$77*$B$71)=0,0,($B$88+(($B50*$B$62+$B$63*$B$62*$B$64*$B$65*$B$67)-($B$68+$B$69*12+$B$70*12*$B$71))/$B$78)/((($B$72*$B$71+$B$73)/E$43+$B$75/$B$76)+$B$77*$B$71)) -> 81.791131 | F50: =IF(((($B$72*$B$71+$B$73)/F$43+$B$75/$B$76)+$B$77*$B$71)=0,0,($B$88+(($B50*$B$62+$B$63*$B$62*$B$64*$B$65*$B$67)-($B$68+$B$69*12+$B$70*12*$B$71))/$B$78)/((($B$72*$B$71+$B$73)/F$43+$B$75/$B$76)+$B$77*$B$71)) -> 91.77673 | G50: =IF(((($B$72*$B$71+$B$73)/G$43+$B$75/$B$76)+$B$77*$B$71)=0,0,($B$88+(($B50*$B$62+$B$63*$B$62*$B$64*$B$65*$B$67)-($B$68+$B$69*12+$B$70*12*$B$71))/$B$78)/((($B$72*$B$71+$B$73)/G$43+$B$75/$B$76)+$B$77*$B$71)) -> 100.87992 | H50: =IF(((($B$72*$B$71+$B$73)/H$43+$B$75/$B$76)+$B$77*$B$71)=0,0,($B$88+(($B50*$B$62+$B$63*$B$62*$B$64*$B$65*$B$67)-($B$68+$B$69*12+$B$70*12*$B$71))/$B$78)/((($B$72*$B$71+$B$73)/H$43+$B$75/$B$76)+$B$77*$B$71)) -> 109.21272 | I50: =IF(((($B$72*$B$71+$B$73)/I$43+$B$75/$B$76)+$B$77*$B$71)=0,0,($B$88+(($B50*$B$62+$B$63*$B$62*$B$64*$B$65*$B$67)-($B$68+$B$69*12+$B$70*12*$B$71))/$B$78)/((($B$72*$B$71+$B$73)/I$43+$B$75/$B$76)+$B$77*$B$71)) -> 119.28474
A59: Section 3 — calculation grid (column B = base; each pair of columns moves one driver by the shock in B4 / C4)
A60: Input / output | B60: Base | C60: SaaS price (₹/site/yr) low | D60: SaaS price (₹/site/yr) high | E60: Win rate low | F60: Win rate high | G60: Recoverable % of bill low | H60: Recoverable % of bill high | I60: Annual churn low | J60: Annual churn high | K60: CAC driver: outbound hours per prospect low | L60: CAC driver: outbound hours per prospect high
A61: SaaS ₹/site/yr | B61: =Assumptions!$D$23 -> 300000 | C61: =$B61*(1+$B$4) -> 210000 | D61: =$B61*(1+$C$4) -> 390000 | E61: =$B61 -> 300000 | F61: =$B61 -> 300000 | G61: =$B61 -> 300000 | H61: =$B61 -> 300000 | I61: =$B61 -> 300000 | J61: =$B61 -> 300000 | K61: =$B61 -> 300000 | L61: =$B61 -> 300000
A62: Sites per customer | B62: =Assumptions!$D$24 -> 1.5 | C62: =$B62 -> 1.5 | D62: =$B62 -> 1.5 | E62: =$B62 -> 1.5 | F62: =$B62 -> 1.5 | G62: =$B62 -> 1.5 | H62: =$B62 -> 1.5 | I62: =$B62 -> 1.5 | J62: =$B62 -> 1.5 | ... L62: =$B62 -> 1.5
A63: Annual OA bill per site | B63: =Assumptions!$D$18 -> 100000000 | C63: =$B63 -> 100000000 | D63: =$B63 -> 100000000 | E63: =$B63 -> 100000000 | F63: =$B63 -> 100000000 | G63: =$B63 -> 100000000 | H63: =$B63 -> 100000000 | I63: =$B63 -> 100000000 | J63: =$B63 -> 100000000 | ... L63: =$B63 -> 100000000
A64: Recoverable % of bill | B64: =Assumptions!$D$19 -> 0.015 | C64: =$B64 -> 0.015 | D64: =$B64 -> 0.015 | E64: =$B64 -> 0.015 | F64: =$B64 -> 0.015 | G64: =$B64*(1+$B$4) -> 0.0105 | H64: =$B64*(1+$C$4) -> 0.0195 | I64: =$B64 -> 0.015 | J64: =$B64 -> 0.015 | K64: =$B64 -> 0.015 | L64: =$B64 -> 0.015
A65: Success fee % | B65: =Assumptions!$D$20 -> 0.2 | C65: =$B65 -> 0.2 | D65: =$B65 -> 0.2 | E65: =$B65 -> 0.2 | F65: =$B65 -> 0.2 | G65: =$B65 -> 0.2 | H65: =$B65 -> 0.2 | I65: =$B65 -> 0.2 | J65: =$B65 -> 0.2 | ... L65: =$B65 -> 0.2
A66: Months audited | B66: =Assumptions!$D$21 -> 18 | C66: =$B66 -> 18 | D66: =$B66 -> 18 | E66: =$B66 -> 18 | F66: =$B66 -> 18 | G66: =$B66 -> 18 | H66: =$B66 -> 18 | I66: =$B66 -> 18 | J66: =$B66 -> 18 | ... L66: =$B66 -> 18
A67: Recurring share | B67: =Assumptions!$D$22 -> 0.25 | C67: =$B67 -> 0.25 | D67: =$B67 -> 0.25 | E67: =$B67 -> 0.25 | F67: =$B67 -> 0.25 | G67: =$B67 -> 0.25 | H67: =$B67 -> 0.25 | I67: =$B67 -> 0.25 | J67: =$B67 -> 0.25 | ... L67: =$B67 -> 0.25
A68: Data per customer ₹/yr | B68: =Assumptions!$D$31 -> 0 | C68: =$B68 -> 0 | D68: =$B68 -> 0 | E68: =$B68 -> 0 | F68: =$B68 -> 0 | G68: =$B68 -> 0 | H68: =$B68 -> 0 | I68: =$B68 -> 0 | J68: =$B68 -> 0 | ... L68: =$B68 -> 0
A69: Compute per customer ₹/mo | B69: =Assumptions!$D$32 -> 100 | C69: =$B69 -> 100 | D69: =$B69 -> 100 | E69: =$B69 -> 100 | F69: =$B69 -> 100 | G69: =$B69 -> 100 | H69: =$B69 -> 100 | I69: =$B69 -> 100 | J69: =$B69 -> 100 | ... L69: =$B69 -> 100
A70: Support hours/customer/mo | B70: =Assumptions!$D$29 -> 2.5 | C70: =$B70 -> 2.5 | D70: =$B70 -> 2.5 | E70: =$B70 -> 2.5 | F70: =$B70 -> 2.5 | G70: =$B70 -> 2.5 | H70: =$B70 -> 2.5 | I70: =$B70 -> 2.5 | J70: =$B70 -> 2.5 | ... L70: =$B70 -> 2.5
A71: Labour rate ₹/h | B71: =Assumptions!$D$9 -> 400 | C71: =$B71 -> 400 | D71: =$B71 -> 400 | E71: =$B71 -> 400 | F71: =$B71 -> 400 | G71: =$B71 -> 400 | H71: =$B71 -> 400 | I71: =$B71 -> 400 | J71: =$B71 -> 400 | ... L71: =$B71 -> 400
A72: Outbound hours per prospect | B72: =Assumptions!$D$37 -> 6 | C72: =$B72 -> 6 | D72: =$B72 -> 6 | E72: =$B72 -> 6 | F72: =$B72 -> 6 | G72: =$B72 -> 6 | H72: =$B72 -> 6 | I72: =$B72 -> 6 | J72: =$B72 -> 6 | K72: =$B72*(1+$B$4) -> 4.2 | L72: =$B72*(1+$C$4) -> 7.8
A73: Travel per prospect ₹ | B73: =Assumptions!$D$38 -> 2000 | C73: =$B73 -> 2000 | D73: =$B73 -> 2000 | E73: =$B73 -> 2000 | F73: =$B73 -> 2000 | G73: =$B73 -> 2000 | H73: =$B73 -> 2000 | I73: =$B73 -> 2000 | J73: =$B73 -> 2000 | ... L73: =$B73 -> 2000
A74: Win rate | B74: =Assumptions!$D$25 -> 0.1 | C74: =$B74 -> 0.1 | D74: =$B74 -> 0.1 | E74: =$B74*(1+$B$4) -> 0.07 | F74: =$B74*(1+$C$4) -> 0.13 | G74: =$B74 -> 0.1 | H74: =$B74 -> 0.1 | I74: =$B74 -> 0.1 | J74: =$B74 -> 0.1 | K74: =$B74 -> 0.1 | L74: =$B74 -> 0.1
A75: Events ₹/yr | B75: =Assumptions!$D$39 -> 100000 | C75: =$B75 -> 100000 | D75: =$B75 -> 100000 | E75: =$B75 -> 100000 | F75: =$B75 -> 100000 | G75: =$B75 -> 100000 | H75: =$B75 -> 100000 | I75: =$B75 -> 100000 | J75: =$B75 -> 100000 | ... L75: =$B75 -> 100000
A76: Planned new customers/yr | B76: =Assumptions!$D$40 -> 10 | C76: =$B76 -> 10 | D76: =$B76 -> 10 | E76: =$B76 -> 10 | F76: =$B76 -> 10 | G76: =$B76 -> 10 | H76: =$B76 -> 10 | I76: =$B76 -> 10 | J76: =$B76 -> 10 | ... L76: =$B76 -> 10
A77: Onboarding hours | B77: =Assumptions!$D$28 -> 24 | C77: =$B77 -> 24 | D77: =$B77 -> 24 | E77: =$B77 -> 24 | F77: =$B77 -> 24 | G77: =$B77 -> 24 | H77: =$B77 -> 24 | I77: =$B77 -> 24 | J77: =$B77 -> 24 | ... L77: =$B77 -> 24
A78: Churn | B78: =Assumptions!$D$27 -> 0.15 | C78: =$B78 -> 0.15 | D78: =$B78 -> 0.15 | E78: =$B78 -> 0.15 | F78: =$B78 -> 0.15 | G78: =$B78 -> 0.15 | H78: =$B78 -> 0.15 | I78: =$B78*(1+$B$4) -> 0.105 | J78: =$B78*(1+$C$4) -> 0.195 | K78: =$B78 -> 0.15 | L78: =$B78 -> 0.15
A79: Engineers at 100 | B79: =Assumptions!$D$35 -> 1 | C79: =$B79 -> 1 | D79: =$B79 -> 1 | E79: =$B79 -> 1 | F79: =$B79 -> 1 | G79: =$B79 -> 1 | H79: =$B79 -> 1 | I79: =$B79 -> 1 | J79: =$B79 -> 1 | ... L79: =$B79 -> 1
A80: Engineer ₹/mo | B80: =Assumptions!$D$10 -> 150000 | C80: =$B80 -> 150000 | D80: =$B80 -> 150000 | E80: =$B80 -> 150000 | F80: =$B80 -> 150000 | G80: =$B80 -> 150000 | H80: =$B80 -> 150000 | I80: =$B80 -> 150000 | J80: =$B80 -> 150000 | ... L80: =$B80 -> 150000
A81: G&A ₹/yr | B81: =Assumptions!$D$11 -> 300000 | C81: =$B81 -> 300000 | D81: =$B81 -> 300000 | E81: =$B81 -> 300000 | F81: =$B81 -> 300000 | G81: =$B81 -> 300000 | H81: =$B81 -> 300000 | I81: =$B81 -> 300000 | J81: =$B81 -> 300000 | ... L81: =$B81 -> 300000
A82: Fixed data ₹/yr | B82: =Assumptions!$D$30 -> 236000 | C82: =$B82 -> 236000 | D82: =$B82 -> 236000 | E82: =$B82 -> 236000 | F82: =$B82 -> 236000 | G82: =$B82 -> 236000 | H82: =$B82 -> 236000 | I82: =$B82 -> 236000 | J82: =$B82 -> 236000 | ... L82: =$B82 -> 236000
A83: Fixed compute $/mo | B83: =Assumptions!$D$12 -> 25 | C83: =$B83 -> 25 | D83: =$B83 -> 25 | E83: =$B83 -> 25 | F83: =$B83 -> 25 | G83: =$B83 -> 25 | H83: =$B83 -> 25 | I83: =$B83 -> 25 | J83: =$B83 -> 25 | ... L83: =$B83 -> 25
A84: USD/INR | B84: =Assumptions!$C$4 -> 87 | C84: =$B84 -> 87 | D84: =$B84 -> 87 | E84: =$B84 -> 87 | F84: =$B84 -> 87 | G84: =$B84 -> 87 | H84: =$B84 -> 87 | I84: =$B84 -> 87 | J84: =$B84 -> 87 | ... L84: =$B84 -> 87
A85: Founder stipend ₹/mo | B85: ='Path to first revenue'!$B$6 -> 50000 | C85: =$B85 -> 50000 | D85: =$B85 -> 50000 | E85: =$B85 -> 50000 | F85: =$B85 -> 50000 | G85: =$B85 -> 50000 | H85: =$B85 -> 50000 | I85: =$B85 -> 50000 | J85: =$B85 -> 50000 | ... L85: =$B85 -> 50000
A87: ARPA steady state ₹/yr | B87: =B61*B62+B63*B62*B64*B65*B67 -> 562500 | C87: =C61*C62+C63*C62*C64*C65*C67 -> 427500 | D87: =D61*D62+D63*D62*D64*D65*D67 -> 697500 | E87: =E61*E62+E63*E62*E64*E65*E67 -> 562500 | F87: =F61*F62+F63*F62*F64*F65*F67 -> 562500 | G87: =G61*G62+G63*G62*G64*G65*G67 -> 528750 | H87: =H61*H62+H63*H62*H64*H65*H67 -> 596250 | I87: =I61*I62+I63*I62*I64*I65*I67 -> 562500 | ... L87: =L61*L62+L63*L62*L64*L65*L67 -> 562500
A88: One-time audit fee ₹ | B88: =B63*B62*B64*B65*B66/12 -> 675000 | C88: =C63*C62*C64*C65*C66/12 -> 675000 | D88: =D63*D62*D64*D65*D66/12 -> 675000 | E88: =E63*E62*E64*E65*E66/12 -> 675000 | F88: =F63*F62*F64*F65*F66/12 -> 675000 | G88: =G63*G62*G64*G65*G66/12 -> 472500 | H88: =H63*H62*H64*H65*H66/12 -> 877500 | I88: =I63*I62*I64*I65*I66/12 -> 675000 | ... L88: =L63*L62*L64*L65*L66/12 -> 675000
A89: Variable cost ₹/yr | B89: =B68+B69*12+B70*12*B71 -> 13200 | C89: =C68+C69*12+C70*12*C71 -> 13200 | D89: =D68+D69*12+D70*12*D71 -> 13200 | E89: =E68+E69*12+E70*12*E71 -> 13200 | F89: =F68+F69*12+F70*12*F71 -> 13200 | G89: =G68+G69*12+G70*12*G71 -> 13200 | H89: =H68+H69*12+H70*12*H71 -> 13200 | I89: =I68+I69*12+I70*12*I71 -> 13200 | ... L89: =L68+L69*12+L70*12*L71 -> 13200
A90: Gross margin ₹/yr | B90: =B87-B89 -> 549300 | C90: =C87-C89 -> 414300 | D90: =D87-D89 -> 684300 | E90: =E87-E89 -> 549300 | F90: =F87-F89 -> 549300 | G90: =G87-G89 -> 515550 | H90: =H87-H89 -> 583050 | I90: =I87-I89 -> 549300 | ... L90: =L87-L89 -> 549300
A91: CAC ₹ | B91: =(B72*B71+B73)/B74+B75/B76 -> 54000 | C91: =(C72*C71+C73)/C74+C75/C76 -> 54000 | D91: =(D72*D71+D73)/D74+D75/D76 -> 54000 | E91: =(E72*E71+E73)/E74+E75/E76 -> 72857.143 | F91: =(F72*F71+F73)/F74+F75/F76 -> 43846.154 | G91: =(G72*G71+G73)/G74+G75/G76 -> 54000 | H91: =(H72*H71+H73)/H74+H75/H76 -> 54000 | I91: =(I72*I71+I73)/I74+I75/I76 -> 54000 | ... L91: =(L72*L71+L73)/L74+L75/L76 -> 61200
A92: Cost to acquire + onboard ₹ | B92: =B91+B77*B71 -> 63600 | C92: =C91+C77*C71 -> 63600 | D92: =D91+D77*D71 -> 63600 | E92: =E91+E77*E71 -> 82457.143 | F92: =F91+F77*F71 -> 53446.154 | G92: =G91+G77*G71 -> 63600 | H92: =H91+H77*H71 -> 63600 | I92: =I91+I77*I71 -> 63600 | ... L92: =L91+L77*L71 -> 70800
A93: Payback months | B93: =IF(B90<=0,999,B92/(B90/12)) -> 1.3894047 | C93: =IF(C90<=0,999,C92/(C90/12)) -> 1.8421434 | D93: =IF(D90<=0,999,D92/(D90/12)) -> 1.1153003 | E93: =IF(E90<=0,999,E92/(E90/12)) -> 1.8013576 | F93: =IF(F90<=0,999,F92/(F90/12)) -> 1.1675839 | G93: =IF(G90<=0,999,G92/(G90/12)) -> 1.4803608 | H93: =IF(H90<=0,999,H92/(H90/12)) -> 1.3089786 | I93: =IF(I90<=0,999,I92/(I90/12)) -> 1.3894047 | ... L93: =IF(L90<=0,999,L92/(L90/12)) -> 1.5466958
A94: LTV / cost to acquire | B94: =IF(B92=0,0,(B88+B90/B78)/B92) -> 68.191824 | C94: =IF(C92=0,0,(C88+C90/C78)/C92) -> 54.040881 | D94: =IF(D92=0,0,(D88+D90/D78)/D92) -> 82.342767 | E94: =IF(E92=0,0,(E88+E90/E78)/E92) -> 52.59702 | F94: =IF(F92=0,0,(F88+F90/F78)/F92) -> 81.147093 | G94: =IF(G92=0,0,(G88+G90/G78)/G92) -> 61.470126 | H94: =IF(H92=0,0,(H88+H90/H78)/H92) -> 74.913522 | I94: =IF(I92=0,0,(I88+I90/I78)/I92) -> 92.868374 | ... L94: =IF(L92=0,0,(L88+L90/L78)/L92) -> 61.257062
A95: EBITDA at 100 customers ₹/yr | B95: =100*(B87-B89)+100*B78*B88-(B85*12+B79*B80*12+B81+B75+B82+B83*B84*12+100*B78*B92) -> 61038900 | C95: =100*(C87-C89)+100*C78*C88-(C85*12+C79*C80*12+C81+C75+C82+C83*C84*12+100*C78*C92) -> 47538900 | D95: =100*(D87-D89)+100*D78*D88-(D85*12+D79*D80*12+D81+D75+D82+D83*D84*12+100*D78*D92) -> 74538900 | E95: =100*(E87-E89)+100*E78*E88-(E85*12+E79*E80*12+E81+E75+E82+E83*E84*12+100*E78*E92) -> 60756043 | F95: =100*(F87-F89)+100*F78*F88-(F85*12+F79*F80*12+F81+F75+F82+F83*F84*12+100*F78*F92) -> 61191208 | G95: =100*(G87-G89)+100*G78*G88-(G85*12+G79*G80*12+G81+G75+G82+G83*G84*12+100*G78*G92) -> 54626400 | H95: =100*(H87-H89)+100*H78*H88-(H85*12+H79*H80*12+H81+H75+H82+H83*H84*12+100*H78*H92) -> 67451400 | I95: =100*(I87-I89)+100*I78*I88-(I85*12+I79*I80*12+I81+I75+I82+I83*I84*12+100*I78*I92) -> 58287600 | ... L95: =100*(L87-L89)+100*L78*L88-(L85*12+L79*L80*12+L81+L75+L82+L83*L84*12+100*L78*L92) -> 60930900

Sheet Operational constraints
A1: Operational constraints — what breaks at 10 / 100 / 1,000 customers (active scenario)
A2: ="Active scenario: "&Assumptions!$D$3&". Hours are formula-driven from the Assumptions sheet and the small input block in each section (blue)." -> Active scenario: Base. Hours are formula-driven from the Assumptions sheet and the small input block in each section (blue).
A4: Item | B4: Unit | C4: 10 customers | D4: 100 customers | E4: 1,000 customers | F4: What breaks / qualitative note
A5: Customers (input) | C5: 10 | D5: 100 | E5: 1000
A7: F2 — settlement engine
A8: Generator pairings (statement sets) per site per month | B8: sets | C8: 1.5 | D8: =$C8 -> 1.5 | E8: =$C8 -> 1.5 | F8: SLDC lists show the same consumer under several IPP groupings; each pairing has its own banking / lapse statement.
A9: Manual hours to collect + reconcile one statement set | B9: hours | C9: 1 | D9: =$C9 -> 1 | E9: =$C9 -> 1 | F9: Until DISCOM / SLDC exports are automated; no SLDC publishes OA energy-accounting statements online (Karnataka SLDC page has none).
A10: State rule libraries that must be current at this stage | B10: states | C10: 1 | D10: 3 | E10: 6 | F10: Karnataka only → KA + TN + MH → six states (adds GJ, RJ, Punjab with 15-minute banking).
A11: Hours per month to maintain one state rule library (tariff orders, APTEL / HC rulings) | B11: hours | C11: 20 | D11: =$C11 -> 20 | E11: =$C11 -> 20 | F11: Karnataka alone has two concurrent banking regimes plus annual surcharge re-sets.
A12: Misstatement rate on audited claims (sign-off liability driver) | B12: % | C12: 0.02 | D12: =$C12 -> 0.02 | E12: =$C12 -> 0.02 | F12: If the engine signs off a claim that is later reversed, the customer may claw back fees or litigate.
A13: Founder delivery hours available per month | B13: hours | C13: 80 | D13: =$C13 -> 80 | E13: =$C13 -> 80 | F13: Same as Path to first revenue input.
A14: Billed sites | B14: sites | C14: =C$5*Assumptions!$F$24 -> 15 | D14: =D$5*Assumptions!$F$24 -> 150 | E14: =E$5*Assumptions!$F$24 -> 1500
A15: Statement sets per month | B15: sets | C15: =C14*$C$8 -> 22.5 | D15: =D14*$C$8 -> 225 | E15: =E14*$C$8 -> 2250
A16: Hours: statement collection + reconciliation | B16: hours / mo | C16: =C15*$C$9 -> 22.5 | D16: =D15*$C$9 -> 225 | E16: =E15*$C$9 -> 2250 | F16: Breaks first: manual collection from customers' DISCOM portals / mailboxes does not scale past ~100 sites without customer-side automation or DISCOM API access.
A17: Hours: support (customers × support hours) | B17: hours / mo | C17: =C$5*Assumptions!$F$29 -> 25 | D17: =D$5*Assumptions!$F$29 -> 250 | E17: =E$5*Assumptions!$F$29 -> 2500
A18: Hours: onboarding of replacement customers (customers × churn / 12 × onboarding hours) | B18: hours / mo | C18: =C$5*Assumptions!$F$27/12*Assumptions!$F$28 -> 3 | D18: =D$5*Assumptions!$F$27/12*Assumptions!$F$28 -> 30 | E18: =E$5*Assumptions!$F$27/12*Assumptions!$F$28 -> 300
A19: Hours: rule-library maintenance (states × hours per state) | B19: hours / mo | C19: =C10*$C$11 -> 20 | D19: =D10*$C$11 -> 60 | E19: =E10*$C$11 -> 120 | F19: Coverage, not volume: every new state is a new regulator, SLDC format and litigation history.
A20: Total delivery hours per month | B20: hours / mo | C20: =SUM(C16:C19) -> 70.5 | D20: =SUM(D16:D19) -> 565 | E20: =SUM(E16:E19) -> 5170
A21: Delivery FTEs required (hours ÷ hours per FTE) | B21: FTE | C21: =C20/Assumptions!$F$8 -> 0.440625 | D21: =D20/Assumptions!$F$8 -> 3.53125 | E21: =E20/Assumptions!$F$8 -> 32.3125
A22: Staffing flag | C22: =IF(C20<=$C$13,"Founder can run","Needs "&TEXT(C21,"0.0")&" delivery FTE") -> Founder can run | D22: =IF(D20<=$C$13,"Founder can run","Needs "&TEXT(D21,"0.0")&" delivery FTE") -> Needs 3.5 delivery FTE | E22: =IF(E20<=$C$13,"Founder can run","Needs "&TEXT(E21,"0.0")&" delivery FTE") -> Needs 32.3 delivery FTE
A23: ₹ of recoveries claimed per year (customers × bill × sites × recoverable %) | B23: ₹ / yr | C23: =C$5*Assumptions!$F$18*Assumptions!$F$24*Assumptions!$F$19 -> 22500000 | D23: =D$5*Assumptions!$F$18*Assumptions!$F$24*Assumptions!$F$19 -> 225000000 | E23: =E$5*Assumptions!$F$18*Assumptions!$F$24*Assumptions!$F$19 -> 2250000000 | F23: Amount the engine signs off and customers dispute with DISCOMs.
A24: Sign-off liability exposure (claims × misstatement rate) | B24: ₹ / yr | C24: =C23*$C$12 -> 450000 | D24: =D23*$C$12 -> 4500000 | E24: =E23*$C$12 -> 45000000 | F24: At 1,000 customers this is a professional-indemnity and audit-trail problem: needs insurance, versioned rule libraries and customer sign-off workflow.
A25: Segment check | C25: =IF(C$5>Assumptions!$F$15,"Exceeds reachable segment",TEXT(C$5/Assumptions!$F$15,"0%")&" of segment") -> 1% of segment | D25: =IF(D$5>Assumptions!$F$15,"Exceeds reachable segment",TEXT(D$5/Assumptions!$F$15,"0%")&" of segment") -> 7% of segment | E25: =IF(E$5>Assumptions!$F$15,"Exceeds reachable segment",TEXT(E$5/Assumptions!$F$15,"0%")&" of segment") -> 67% of segment | F25: 1,000 customers requires national coverage (not three states) and a channel (associations, traders) rather than direct sales.
A27: F1 — connectivity intelligence
A28: CTUIL / CERC / RLDC documents released per month (parse + QA) | B28: docs | C28: 15 | D28: =$C28 -> 15 | E28: =$C28 -> 15 | F28: Monthly bay-margin PDFs (3 per release), grant lists, cluster declarations, CERC orders; formats change without notice.
A29: Hours per document (parse QA, corrupt PDF streams) | B29: hours | C29: 0.5 | D29: =$C29 -> 0.5 | E29: =$C29 -> 0.5 | F29: Margins PDF had 28 corrupt flate streams on extraction.
A30: Hours per paid report | B30: hours | C30: 8 | D30: =$C30 -> 8 | E30: =$C30 -> 8 | F30: Substation-selection / reallocation analysis.
A31: Bank guarantee at risk per customer (advice liability reference) | B31: ₹ | C31: 50000000 | D31: =$C31 -> 50000000 | E31: =$C31 -> 50000000 | F31: Encashments of ₹3.1–11.5 Cr per developer (Prerak, Datta, Sprng); midpoint used.
A32: Founder delivery hours available per month | B32: hours | C32: 80 | D32: =$C32 -> 80 | E32: =$C32 -> 80
A33: Hours: document parsing + QA (fixed, independent of customers) | B33: hours / mo | C33: =$C$28*$C$29 -> 7.5 | D33: =$C$28*$C$29 -> 7.5 | E33: =$C$28*$C$29 -> 7.5 | F33: Fixed cost of staying current; the product is only as good as last month's parse.
A34: Hours: paid reports (customers × reports/yr × hours / 12) | B34: hours / mo | C34: =C$5*Assumptions!$F$46*$C$30/12 -> 6.6666667 | D34: =D$5*Assumptions!$F$46*$C$30/12 -> 66.666667 | E34: =E$5*Assumptions!$F$46*$C$30/12 -> 666.66667 | F34: Reports are bespoke analysis: they do not scale without templating.
A35: Hours: alert curation / support | B35: hours / mo | C35: =C$5*Assumptions!$F$52 -> 20 | D35: =D$5*Assumptions!$F$52 -> 200 | E35: =E$5*Assumptions!$F$52 -> 2000
A36: Hours: onboarding of replacement customers | B36: hours / mo | C36: =C$5*Assumptions!$F$50/12*Assumptions!$F$51 -> 1.3333333 | D36: =D$5*Assumptions!$F$50/12*Assumptions!$F$51 -> 13.333333 | E36: =E$5*Assumptions!$F$50/12*Assumptions!$F$51 -> 133.33333
A37: Total delivery hours per month | B37: hours / mo | C37: =SUM(C33:C36) -> 35.5 | D37: =SUM(D33:D36) -> 287.5 | E37: =SUM(E33:E36) -> 2807.5
A38: Delivery FTEs required | B38: FTE | C38: =C37/Assumptions!$F$8 -> 0.221875 | D38: =D37/Assumptions!$F$8 -> 1.796875 | E38: =E37/Assumptions!$F$8 -> 17.546875
A39: Staffing flag | C39: =IF(C37<=$C$32,"Founder can run","Needs "&TEXT(C38,"0.0")&" delivery FTE") -> Founder can run | D39: =IF(D37<=$C$32,"Founder can run","Needs "&TEXT(D38,"0.0")&" delivery FTE") -> Needs 1.8 delivery FTE | E39: =IF(E37<=$C$32,"Founder can run","Needs "&TEXT(E38,"0.0")&" delivery FTE") -> Needs 17.5 delivery FTE
A40: Advice liability reference (customers × BG at risk) | B40: ₹ | C40: =C$5*$C$31 -> 500000000 | D40: =D$5*$C$31 -> 5000000000 | E40: =E$5*$C$31 -> 50000000000 | F40: A wrong 'effective-date' prediction can cost a customer its BG; terms of service must disclaim, which weakens the value proposition.
A41: Data-reuse gate | C41: =IF(Assumptions!$F$53=1,"CTUIL permission assumed","BLOCKED: CTUIL permission not obtained") -> CTUIL permission assumed | D41: =IF(Assumptions!$F$53=1,"CTUIL permission assumed","BLOCKED: CTUIL permission not obtained") -> CTUIL permission assumed | E41: =IF(Assumptions!$F$53=1,"CTUIL permission assumed","BLOCKED: CTUIL permission not obtained") -> CTUIL permission assumed | F41: Copyright policy requires permission; margins PDFs stamped RESTRICTED (red-team Q5).
A42: Segment check | C42: =IF(C$5>Assumptions!$F$44,"Exceeds reachable segment",TEXT(C$5/Assumptions!$F$44,"0%")&" of segment") -> 5% of segment | D42: =IF(D$5>Assumptions!$F$44,"Exceeds reachable segment",TEXT(D$5/Assumptions!$F$44,"0%")&" of segment") -> 50% of segment | E42: =IF(E$5>Assumptions!$F$44,"Exceeds reachable segment",TEXT(E$5/Assumptions!$F$44,"0%")&" of segment") -> Exceeds reachable segment | F42: Buyer universe is a few hundred developers: 1,000 customers is not reachable in any scenario.
A44: F3 — dispatch & compliance
A45: Capacity charge reference | B45: ₹ / MW / month | C45: 240000 | D45: =$C45 -> 240000 | E45: =$C45 -> 240000 | F45: MSEDCL Sep-2026 award ₹2.38–2.40 lakh/MW/month (S24).
A46: Availability shortfall exposure (share of capacity charge at risk per year) | B46: % | C46: 0.05 | D46: =$C46 -> 0.05 | E46: =$C46 -> 0.05 | F46: 95% annual availability test; LDs on shortfall (contract-specific, not quantified in the notes).
A47: Minimum dispatch-desk hours per month once any merchant MW is live (24×7 cover) | B47: hours | C47: 730 | D47: =$C47 -> 730 | E47: =$C47 -> 730 | F47: A merchant / FDRE desk needs round-the-clock cover regardless of customer count.
A48: Founder delivery hours available per month | B48: hours | C48: 80 | D48: =$C48 -> 80 | E48: =$C48 -> 80
A49: MW under management | B49: MW | C49: =C$5*Assumptions!$F$69 -> 2500 | D49: =D$5*Assumptions!$F$69 -> 25000 | E49: =E$5*Assumptions!$F$69 -> 250000
A50: Hours: dispatch / compliance support (customers × hours) | B50: hours / mo | C50: =C$5*Assumptions!$F$78 -> 80 | D50: =D$5*Assumptions!$F$78 -> 800 | E50: =E$5*Assumptions!$F$78 -> 8000
A51: Hours: 24×7 desk floor (if merchant share > 0) | B51: hours / mo | C51: =IF(Assumptions!$F$70>0,$C$47,0) -> 730 | D51: =IF(Assumptions!$F$70>0,$C$47,0) -> 730 | E51: =IF(Assumptions!$F$70>0,$C$47,0) -> 730 | F51: Breaks first: a solo founder cannot provide 24×7 dispatch cover; needs ≥4 operators or full automation with customer-side fallback.
A52: Hours: integrations for replacement customers | B52: hours / mo | C52: =C$5*Assumptions!$F$76/12*Assumptions!$F$77 -> 10 | D52: =D$5*Assumptions!$F$76/12*Assumptions!$F$77 -> 100 | E52: =E$5*Assumptions!$F$76/12*Assumptions!$F$77 -> 1000 | F52: Every OEM EMS (Envision, Fluence, Sungrow, indigenous EMS) is a separate integration.
A53: Total delivery hours per month | B53: hours / mo | C53: =SUM(C50:C52) -> 820 | D53: =SUM(D50:D52) -> 1630 | E53: =SUM(E50:E52) -> 9730
A54: Delivery FTEs required | B54: FTE | C54: =C53/Assumptions!$F$8 -> 5.125 | D54: =D53/Assumptions!$F$8 -> 10.1875 | E54: =E53/Assumptions!$F$8 -> 60.8125
A55: Staffing flag | C55: =IF(C53<=$C$48,"Founder can run","Needs "&TEXT(C54,"0.0")&" delivery FTE") -> Needs 5.1 delivery FTE | D55: =IF(D53<=$C$48,"Founder can run","Needs "&TEXT(D54,"0.0")&" delivery FTE") -> Needs 10.2 delivery FTE | E55: =IF(E53<=$C$48,"Founder can run","Needs "&TEXT(E54,"0.0")&" delivery FTE") -> Needs 60.8 delivery FTE
A56: Capacity charge at risk under availability tests (MW × charge × 12 × exposure %) | B56: ₹ / yr | C56: =C49*$C$45*12*$C$46 -> 360000000 | D56: =D49*$C$45*12*$C$46 -> 3600000000 | E56: =E49*$C$45*12*$C$46 -> 36000000000 | F56: The compliance module signs the monthly availability certificate: errors translate into LDs the customer will try to recover.
A57: Segment check | C57: =IF(C$5>Assumptions!$F$67,"Exceeds reachable segment",TEXT(C$5/Assumptions!$F$67,"0%")&" of segment") -> 33% of segment | D57: =IF(D$5>Assumptions!$F$67,"Exceeds reachable segment",TEXT(D$5/Assumptions!$F$67,"0%")&" of segment") -> Exceeds reachable segment | E57: =IF(E$5>Assumptions!$F$67,"Exceeds reachable segment",TEXT(E$5/Assumptions!$F$67,"0%")&" of segment") -> Exceeds reachable segment | F57: ≈19 named Tier-2 awardees today; 100+ customers requires the 2027–29 pipeline to commission and merchant rules to settle.

Sheet Sources
A1: Sources — every anchor used in Assumptions (S-number ↔ column H on Assumptions)
A2: Evidence class as recorded in the research note. URLs were accessed by the research tracks on 2026-10-17; no new web research was done for this workbook. 'local note' = finding lives only in the named note.
A4: ID | B4: Anchor / claim | C4: Value | D4: Evidence class | E4: Research note | F4: URL
A5: S1 | B5: Finalist definitions and post-red-team ranking F2 (71) > F1 (63) > F3 (60); experiments F2-A, F2-B, F1-A0/A | C5: ranking | D5: Verified (coordinator synthesis) | E5: decision_brief.md §3, §5, §7 | F5: local note
A6: S2 | B6: JMK 'Open Access C&I RE Market in India' report price | C6: INR 2 lakh + 18% GST (≈ USD 2,700), quarterly updates | D6: Verified | E6: opportunities_beyond_thesis.md H1; f2_f3_commercial_facts.md F2-Q3 | F6: https://jmkresearch.com/open-access-ci-re-market-in-india/
A7: S3 | B7: F2 pricing idea: success fee on recovered overcharges, then ₹2–5 lakh/yr/site SaaS; enterprise ₹15–40 lakh/yr | C7: hypothesis | D7: Hypothesis | E7: opportunities_beyond_thesis.md H1 (Inferences); f2_f3_commercial_facts.md F2-Q3 | F7: https://www.herofutureenergies.com/blog/solar-open-access-for-commercial-industrial-consumers-india/
A8: S4 | B8: Energy-audit price bands: mid-size factory ₹1.5–4 lakh; large plant ₹3–8 lakh; BEE Designated Consumer ₹5–15 lakh | C8: ₹ lakh per audit | D8: Estimate (vendor guide) | E8: f2_f3_commercial_facts.md F2-Q3 | F8: https://elion.co.in/energy-audit-in-india-complete-guide-to-bee-compliance-process-cost-savings-2026/
A9: S5 | B9: Zenatix SaaS fee 8–12% of energy bill; ~₹30,000 per site per year (2017) | C9: % of bill; ₹/site/yr | D9: Corroborated (dated) | E9: f2_f3_commercial_facts.md F2-Q3 | F9: https://www.businesstoday.in/magazine/features/story/the-power-people-84654-2017-08-04
A10: S6 | B10: Karnataka SLDC W&B lists: 556 IPPs / 4,924 MW; ≈922 distinct consumer organisations; multi-installation consumers named | C10: count / MW | D10: Verified (count) / Estimate (dedupe) | E10: f2_f3_commercial_facts.md F2-Q1, F2-Q5 | F10: https://kptclsldc.in/WBUpload.aspx
A11: S7 | B11: Tamil Nadu: '1,500+ MSME textile mills' on OA / group captive | C11: count | D11: Estimate (association claim) | E11: f2_f3_commercial_facts.md F2-Q2 | F11: https://apparelresources.com/business-news/sourcing/struggling-tamil-nadu-textile-industry-urges-not-change-states-energy-policies/
A12: S8 | B12: BESCOM petition: ₹1.65/kWh additional surcharge on ₹1,028.29 Cr stranded cost → implied ≈6,230 MU/yr OA energy | C12: ₹/kWh; MU/yr | D12: Verified / Estimate (arithmetic) | E12: f2_f3_commercial_facts.md F2-Q1 | F12: https://solarquarter.com/2025/10/14/bescom-seeks-kerc-approval-to-levy-%e2%82%b91-65-per-unit-additional-surcharge-on-open-access-consumers-in-karnataka/
A13: S9 | B13: Karnataka additional surcharge ₹0.82/kWh (FY26) → ₹0.40/kWh (from Mar 2026), not on captive drawal | C13: ₹/kWh | D13: Corroborated | E13: f2_f3_commercial_facts.md F2-Q1 | F13: https://mercomindia.com/karnataka-halves-additional-surcharge-for-open-access-power
A14: S10 | B14: MERC ordered MSEDCL to refund unlawfully collected wheeling charges (over-billing precedent); APTEL set aside TN banking orders | C14: precedent | D14: Verified | E14: f2_f3_commercial_facts.md F2-Q2 | F14: https://www.energetica-india.net/keyword/open-access-charges
A15: S11 | B15: Hero Future Energies: landed ₹4.78/unit vs DISCOM ₹7.32; advisory + connection costs paid back in <6 months (amount undisclosed) | C15: ₹/kWh | D15: Estimate (vendor blog) | E15: opportunities_beyond_thesis.md H1 | F15: https://www.herofutureenergies.com/blog/solar-open-access-for-commercial-industrial-consumers-india/
... A44: S40 | B44: MSEDCL 2 GW / 4 GWh BESPA: 15 years, ≥6,300 cycles, 95% annual availability, 85% monthly RTE, indigenous EMS software, VGF ₹18 lakh/MW | C44: contract terms | D44: Verified | E44: f2_f3_commercial_facts.md F3-Q1, F3-Q2 | F44: https://www.energetica-india.net/news/oriana-bsl-engineering-armee-infotech-gk-energy-among-winners-in-msedcl-4-gwh-bess-auction
